Workbook

Sheet Master
A1: Activate/Deactivate | B1: Count | C1: Object_Type | D1: Column1 | E1: F or T # | F1: Indicator Name | G1: Object ID | H1: Figure ID
A2: Activate | B2: 1 | C2: Table | E2: T1 | F2: Demographic Summary by Municipality, 2023 | G2: tbl-demographics-sum | H2: =IF(LEFT(Table3[[#This Row],[Object ID]],4)="tbl-","fig-" & MID(Table3[[#This Row],[Object ID]],5,LEN(Table3[[#This Row],[Object ID]])-4),"") -> fig-demographics-sum
A3: Activate | B3: 2 | C3: Table | E3: T2 | F3: Population by Municipality, 1970–2020 | G3: tbl-pop | H3: =IF(LEFT(Table3[[#This Row],[Object ID]],4)="tbl-","fig-" & MID(Table3[[#This Row],[Object ID]],5,LEN(Table3[[#This Row],[Object ID]])-4),"") -> fig-pop
A4: Activate | B4: 3 | C4: Figure | E4: F1 | F4: Total Population by Municipality, 2023 | G4: tbl-total-pop | H4: =IF(LEFT(Table3[[#This Row],[Object ID]],4)="tbl-","fig-" & MID(Table3[[#This Row],[Object ID]],5,LEN(Table3[[#This Row],[Object ID]])-4),"") -> fig-total-pop
A5: Activate | B5: 4 | C5: Table | E5: T3 | F5: Population Growth by Municipality, 2000–2020 | G5: tbl-pop-growth | H5: =IF(LEFT(Table3[[#This Row],[Object ID]],4)="tbl-","fig-" & MID(Table3[[#This Row],[Object ID]],5,LEN(Table3[[#This Row],[Object ID]])-4),"") -> fig-pop-growth
A6: Activate | B6: 5 | C6: Table | E6: T4 | F6: Population and Housing Unit Density by Municipality, 2023 | G6: tbl-pop-housing-density | H6: =IF(LEFT(Table3[[#This Row],[Object ID]],4)="tbl-","fig-" & MID(Table3[[#This Row],[Object ID]],5,LEN(Table3[[#This Row],[Object ID]])-4),"") -> fig-pop-housing-density
A7: Activate | B7: 6 | C7: Table | E7: T5 | F7: Population of Municipalities by Sex and Age, 2023 | G7: tbl-pop-sex-age | H7: =IF(LEFT(Table3[[#This Row],[Object ID]],4)="tbl-","fig-" & MID(Table3[[#This Row],[Object ID]],5,LEN(Table3[[#This Row],[Object ID]])-4),"") -> fig-pop-sex-age
A8: Activate | B8: 7 | C8: Figure | E8: F2 | F8: Median Age by Municipality, 2023 | G8: tbl-median-age | H8: =IF(LEFT(Table3[[#This Row],[Object ID]],4)="tbl-","fig-" & MID(Table3[[#This Row],[Object ID]],5,LEN(Table3[[#This Row],[Object ID]])-4),"") -> fig-median-age
A9: Activate | B9: 8 | C9: Table | E9: T6 | F9: Population of Municipalities by Race and Ethnicity, 2020 | G9: tbl-pop-race-ethnicity | H9: =IF(LEFT(Table3[[#This Row],[Object ID]],4)="tbl-","fig-" & MID(Table3[[#This Row],[Object ID]],5,LEN(Table3[[#This Row],[Object ID]])-4),"") -> fig-pop-race-ethnicity
A10: Activate | B10: 9 | C10: Table | E10: T7 | F10: Employed Civilians by Industry and Municipality, 2023 | G10: tbl-employed-civilians-industry | H10: =IF(LEFT(Table3[[#This Row],[Object ID]],4)="tbl-","fig-" & MID(Table3[[#This Row],[Object ID]],5,LEN(Table3[[#This Row],[Object ID]])-4),"") -> fig-employed-civilians-industry
A11: Activate | B11: 10 | C11: Table | E11: T8 | F11: Employed Civilian Occupations by Municipality, 2023 | G11: tbl-employed-civilian-occupations | H11: =IF(LEFT(Table3[[#This Row],[Object ID]],4)="tbl-","fig-" & MID(Table3[[#This Row],[Object ID]],5,LEN(Table3[[#This Row],[Object ID]])-4),"") -> fig-employed-civilian-occupations
A12: Activate | B12: 11 | C12: Table | E12: T9 | F12: All-Cause Mortality, Rate per 100,000 Population by Age, ZIP Code, Race and Ethnicity, 2020–2023 | G12: tbl-all-cause-mortal-rate-age-zip-code-rande | H12: =IF(LEFT(Table3[[#This Row],[Object ID]],4)="tbl-","fig-" & MID(Table3[[#This Row],[Object ID]],5,LEN(Table3[[#This Row],[Object ID]])-4),"") -> fig-all-cause-mortal-rate-age-zip-code-rande
A13: Activate | B13: 12 | C13: Figure | E13: F3 | F13: All-Cause Mortality, Age-Adjusted Rate per 100,000 Population by Race and Ethnicity, 2020–2022 | G13: tbl-all-cause-mortal-aar-rande | H13: =IF(LEFT(Table3[[#This Row],[Object ID]],4)="tbl-","fig-" & MID(Table3[[#This Row],[Object ID]],5,LEN(Table3[[#This Row],[Object ID]])-4),"") -> fig-all-cause-mortal-aar-rande
... A127: Activate | B127: 126 | C127: Figure | E127: F89 | F127: Prostate Cancer Mortality, Age-Adjusted Rate per 100,000 Population by Race and Ethnicity, 2018–2022 | G127: tbl-prostate-mortal-rande-aar-five | H127: =IF(LEFT(Table3[[#This Row],[Object ID]],4)="tbl-","fig-" & MID(Table3[[#This Row],[Object ID]],5,LEN(Table3[[#This Row],[Object ID]])-4),"") -> fig-prostate-mortal-rande-aar-five
C128: Table | E128: T38 | F128: General Communicable Diseases, Case Counts and Rates per 100,000 Residents, 2021–2023 | G128: tbl-cd-count-rate | H128: =IF(LEFT(Table3[[#This Row],[Object ID]],4)="tbl-","fig-" & MID(Table3[[#This Row],[Object ID]],5,LEN(Table3[[#This Row],[Object ID]])-4),"") -> fig-cd-count-rate
C129: Figure | E129: F90 | F129: Hepatitis A, Rate per 100,000 Population, 2020–2023 | G129: tbl-hepatitisa-rate | H129: =IF(LEFT(Table3[[#This Row],[Object ID]],4)="tbl-","fig-" & MID(Table3[[#This Row],[Object ID]],5,LEN(Table3[[#This Row],[Object ID]])-4),"") -> fig-hepatitisa-rate
A130: Activate | B130: 127 | C130: Figure | E130: F91 | F130: Chronic Hepatitis B, Rate per 100,000 Population, 2020–2023 | G130: tbl-hepatitisb-chronic-rate | H130: =IF(LEFT(Table3[[#This Row],[Object ID]],4)="tbl-","fig-" & MID(Table3[[#This Row],[Object ID]],5,LEN(Table3[[#This Row],[Object ID]])-4),"") -> fig-hepatitisb-chronic-rate
A131: Activate | B131: 128 | C131: Figure | E131: F92 | F131: Acute Hepatitis C, Rate per 100,000 Population, 2020–2023 | G131: tbl-hepatitisc-acute-rate | H131: =IF(LEFT(Table3[[#This Row],[Object ID]],4)="tbl-","fig-" & MID(Table3[[#This Row],[Object ID]],5,LEN(Table3[[#This Row],[Object ID]])-4),"") -> fig-hepatitisc-acute-rate
A132: Activate | B132: 129 | C132: Figure | E132: F93 | F132: Chronic Hepatitis C, Rate per 100,000 Population, 2020–2023 | G132: tbl-hepatitisc-chronic-rate | H132: =IF(LEFT(Table3[[#This Row],[Object ID]],4)="tbl-","fig-" & MID(Table3[[#This Row],[Object ID]],5,LEN(Table3[[#This Row],[Object ID]])-4),"") -> fig-hepatitisc-chronic-rate
A133: Activate | B133: 130 | C133: Table | E133: T40 | F133: Chlamydia, Case Counts and Infection Rates per 100,000 by Sex, Race and Ethnicity, Age, and ZIP Code, 2021–2024 | G133: tbl-chlamydia-count-rate-sex-rande-age-zip | H133: =IF(LEFT(Table3[[#This Row],[Object ID]],4)="tbl-","fig-" & MID(Table3[[#This Row],[Object ID]],5,LEN(Table3[[#This Row],[Object ID]])-4),"") -> fig-chlamydia-count-rate-sex-rande-age-zip
A134: Activate | B134: 131 | C134: Figure | E134: F94 | F134: Chlamydia, Age-Adjusted Rate per 100,000 Population, 2020–2023 | G134: tbl-chlamydia-aar | H134: =IF(LEFT(Table3[[#This Row],[Object ID]],4)="tbl-","fig-" & MID(Table3[[#This Row],[Object ID]],5,LEN(Table3[[#This Row],[Object ID]])-4),"") -> fig-chlamydia-aar
A135: Activate | B135: 132 | C135: Figure | E135: F95 | F135: Chlamydia, Rate per 100,000 Population by Race and Ethnicity, 2021–2024 | G135: tbl-chlamydia-rande | H135: =IF(LEFT(Table3[[#This Row],[Object ID]],4)="tbl-","fig-" & MID(Table3[[#This Row],[Object ID]],5,LEN(Table3[[#This Row],[Object ID]])-4),"") -> fig-chlamydia-rande
A136: Activate | B136: 133 | C136: Table | E136: T41 | F136: Gonorrhea, Case Counts and Infection Rates per 100,000 by Sex, Race and Ethnicity, Age, and ZIP Code, 2021–2024 | G136: tbl-gonorrhea-count-rate-sex-rande-age-zip | H136: =IF(LEFT(Table3[[#This Row],[Object ID]],4)="tbl-","fig-" & MID(Table3[[#This Row],[Object ID]],5,LEN(Table3[[#This Row],[Object ID]])-4),"") -> fig-gonorrhea-count-rate-sex-rande-age-zip
A137: Activate | B137: 134 | C137: Figure | E137: F96 | F137: Gonorrhea, Age-Adjusted Case Rate per 100,000 Population, 2020–2023 | G137: tbl-gonorrhea-aar | H137: =IF(LEFT(Table3[[#This Row],[Object ID]],4)="tbl-","fig-" & MID(Table3[[#This Row],[Object ID]],5,LEN(Table3[[#This Row],[Object ID]])-4),"") -> fig-gonorrhea-aar
A138: Activate | B138: 135 | C138: Figure | E138: F97 | F138: Gonorrhea, Case Rate per 100,000 Population by Race and Ethnicity, 2021–2024 | G138: tbl-gonorrhea-rande | H138: =IF(LEFT(Table3[[#This Row],[Object ID]],4)="tbl-","fig-" & MID(Table3[[#This Row],[Object ID]],5,LEN(Table3[[#This Row],[Object ID]])-4),"") -> fig-gonorrhea-rande
A139: Activate | B139: 136 | C139: Table | E139: T42 | F139: HIV Prevalence, Rate per 100,000 Population by Race and Ethnicity, Age, and Sex, 2020–2023 | G139: tbl-hiv-prevalence-rate-rande-age-sex | H139: =IF(LEFT(Table3[[#This Row],[Object ID]],4)="tbl-","fig-" & MID(Table3[[#This Row],[Object ID]],5,LEN(Table3[[#This Row],[Object ID]])-4),"") -> fig-hiv-prevalence-rate-rande-age-sex
A140: Activate | B140: 137 | C140: Figure | E140: F98 | F140: HIV and AIDS Incidence, Age-Adjusted Rate per 100,000 Population, 2020–2023 | G140: tbl-hiv-aids-incidence-aar | H140: =IF(LEFT(Table3[[#This Row],[Object ID]],4)="tbl-","fig-" & MID(Table3[[#This Row],[Object ID]],5,LEN(Table3[[#This Row],[Object ID]])-4),"") -> fig-hiv-aids-incidence-aar
A141: Activate | B141: 138 | C141: Figure | E141: F99 | F141: HIV Prevalence by Transmission Category, Count, 2020–2023 | G141: tbl-hiv-prevalence-transmission-category | H141: =IF(LEFT(Table3[[#This Row],[Object ID]],4)="tbl-","fig-" & MID(Table3[[#This Row],[Object ID]],5,LEN(Table3[[#This Row],[Object ID]])-4),"") -> fig-hiv-prevalence-transmission-category
... A175: Activate | B175: 172 | C175: Figure | E175: F125 | F175: Percentage of Opioid Naïve Patients Receiving More than a 7-Day Supply, 2021–2024 | G175: tbl-opioid-naïve-7day-rx | H175: =IF(LEFT(Table3[[#This Row],[Object ID]],4)="tbl-","fig-" & MID(Table3[[#This Row],[Object ID]],5,LEN(Table3[[#This Row],[Object ID]])-4),"") -> fig-opioid-naïve-7day-rx
C176: Figure | E176: F126 | F176: Benzodiazepine Prescriptions, Age-Adjusted Rate per 1,000 Person-Years, 2021–2024 | G176: tbl-benzo-rx-aar | H176: =IF(LEFT(Table3[[#This Row],[Object ID]],4)="tbl-","fig-" & MID(Table3[[#This Row],[Object ID]],5,LEN(Table3[[#This Row],[Object ID]])-4),"") -> fig-benzo-rx-aar
A177: Activate | B177: 173 | C177: Figure | E177: F127 | F177: Percentage of Patients With Overlapping Opioid Analgesic and Benzodiazepine Prescriptions, 2021–2024 | G177: tbl-overlap-opioid-benzo-rx | H177: =IF(LEFT(Table3[[#This Row],[Object ID]],4)="tbl-","fig-" & MID(Table3[[#This Row],[Object ID]],5,LEN(Table3[[#This Row],[Object ID]])-4),"") -> fig-overlap-opioid-benzo-rx
A178: Activate | B178: 174 | C178: Figure | E178: F128 | F178: Patients Who Received at Least One Buprenorphine Prescription for Opioid Use Disorder, Age-Adjusted Rate per 100,000 Population, 2021–2024 | G178: tbl-opioidud-atleast1rx-bup-aar | H178: =IF(LEFT(Table3[[#This Row],[Object ID]],4)="tbl-","fig-" & MID(Table3[[#This Row],[Object ID]],5,LEN(Table3[[#This Row],[Object ID]])-4),"") -> fig-opioidud-atleast1rx-bup-aar
A179: Activate | B179: 175 | C179: Figure | E179: F129 | F179: Percentage of Patients Receiving Continuous Buprenorphine for Treatment of Opioid Use Disorder, 2021–2024 | G179: tbl-opioidud-continuous-bup-rx | H179: =IF(LEFT(Table3[[#This Row],[Object ID]],4)="tbl-","fig-" & MID(Table3[[#This Row],[Object ID]],5,LEN(Table3[[#This Row],[Object ID]])-4),"") -> fig-opioidud-continuous-bup-rx
A180: Activate | B180: 176 | C180: Figure | E180: F130 | F180: Percentage Perception of Harm of Substance use, Moderate Risk or Great Risk, 2025 | G180: tbl-perception-harm-su | H180: =IF(LEFT(Table3[[#This Row],[Object ID]],4)="tbl-","fig-" & MID(Table3[[#This Row],[Object ID]],5,LEN(Table3[[#This Row],[Object ID]])-4),"") -> fig-perception-harm-su
A181: Activate | B181: 177 | C181: Table | E181: T51 | F181: Lifetime Use of Substance by Grade | G181: tbl-lifetime-su | H181: =IF(LEFT(Table3[[#This Row],[Object ID]],4)="tbl-","fig-" & MID(Table3[[#This Row],[Object ID]],5,LEN(Table3[[#This Row],[Object ID]])-4),"") -> fig-lifetime-su
A182: Activate | B182: 178 | C182: Table | E182: T52 | F182: Past 30 Day Use of Substance by Grade | G182: tlb-past-30day-su | H182: =IF(LEFT(Table3[[#This Row],[Object ID]],4)="tbl-","fig-" & MID(Table3[[#This Row],[Object ID]],5,LEN(Table3[[#This Row],[Object ID]])-4),"")
A183: Activate | B183: 179 | C183: Table | E183: T53 | F183: Percentage of Sources of Marijuana for Those Who Reported Use | G183: tbl-source-marijuana-ifused | H183: =IF(LEFT(Table3[[#This Row],[Object ID]],4)="tbl-","fig-" & MID(Table3[[#This Row],[Object ID]],5,LEN(Table3[[#This Row],[Object ID]])-4),"") -> fig-source-marijuana-ifused
A184: Activate | B184: 180 | C184: Table | E184: T54 | F184: Opioid-Related Overdose Fatalities, Rate per 100,000 Population by Age and Sex, 2021–2024 | G184: tbl-opioid-od-fatal-age-sex | H184: =IF(LEFT(Table3[[#This Row],[Object ID]],4)="tbl-","fig-" & MID(Table3[[#This Row],[Object ID]],5,LEN(Table3[[#This Row],[Object ID]])-4),"") -> fig-opioid-od-fatal-age-sex
A185: Activate | B185: 181 | C185: Figure | E185: F131 | F185: Opioid-Related Overdose Fatalities, Rate per 100,000 Population, 2021–2024 | G185: tbl-opioid-od-fatal | H185: =IF(LEFT(Table3[[#This Row],[Object ID]],4)="tbl-","fig-" & MID(Table3[[#This Row],[Object ID]],5,LEN(Table3[[#This Row],[Object ID]])-4),"") -> fig-opioid-od-fatal
A186: Activate | B186: 182 | C186: Figure | E186: F132 | F186: Opioid-Related Overdose Fatalities, Rate per 100,000 Population by Age, 2021–2024 | G186: tbl-opioid-od-fatal-age | H186: =IF(LEFT(Table3[[#This Row],[Object ID]],4)="tbl-","fig-" & MID(Table3[[#This Row],[Object ID]],5,LEN(Table3[[#This Row],[Object ID]])-4),"") -> fig-opioid-od-fatal-age
A187: Activate | B187: 183 | C187: Figure | E187: F133 | F187: Opioid-Related Overdose Fatalities, Rate per 100,000 Population by Sex, 2021–2024 | G187: tbl-opioid-od-fatal-sex | H187: =IF(LEFT(Table3[[#This Row],[Object ID]],4)="tbl-","fig-" & MID(Table3[[#This Row],[Object ID]],5,LEN(Table3[[#This Row],[Object ID]])-4),"") -> fig-opioid-od-fatal-sex
A188: Activate | B188: 184 | C188: Figure | E188: F134 | F188: Percentage of Adults Binge Drinking During the Past Month, 2016, 2018, and 2021 | G188: tbl-binge-drinking-last-month | H188: =IF(LEFT(Table3[[#This Row],[Object ID]],4)="tbl-","fig-" & MID(Table3[[#This Row],[Object ID]],5,LEN(Table3[[#This Row],[Object ID]])-4),"") -> fig-binge-drinking-last-month
... A293: Activate | B293: 289 | C293: Figure | E293: F229 | F293: Vaccinated for Flu, 2024 | G293: tbl-siena-flu-vaccine | H293: =IF(LEFT(Table3[[#This Row],[Object ID]],4)="tbl-","fig-" & MID(Table3[[#This Row],[Object ID]],5,LEN(Table3[[#This Row],[Object ID]])-4),"") -> fig-siena-flu-vaccine
C294: Figure | E294: F230 | F294: Vaccinated for Flu by Income, 2024 | G294: tbl-siena-flu-vaccine-income | H294: =IF(LEFT(Table3[[#This Row],[Object ID]],4)="tbl-","fig-" & MID(Table3[[#This Row],[Object ID]],5,LEN(Table3[[#This Row],[Object ID]])-4),"") -> fig-siena-flu-vaccine-income
C295: Figure | E295: F231 | F295: Vaccinated for Flu 60+, 2024 | G295: tbl-siena-flu-vaccine-60yo | H295: =IF(LEFT(Table3[[#This Row],[Object ID]],4)="tbl-","fig-" & MID(Table3[[#This Row],[Object ID]],5,LEN(Table3[[#This Row],[Object ID]])-4),"") -> fig-siena-flu-vaccine-60yo
C296: Figure | E296: F232 | F296: Feeling Nervous, 2023-2024 | G296: tbl-siena-feeling-nervous | H296: =IF(LEFT(Table3[[#This Row],[Object ID]],4)="tbl-","fig-" & MID(Table3[[#This Row],[Object ID]],5,LEN(Table3[[#This Row],[Object ID]])-4),"") -> fig-siena-feeling-nervous
C297: Figure | E297: F233 | F297: Feeling Nervous by Income, 2024 | G297: tbl-siena-feeling-nervous-income | H297: =IF(LEFT(Table3[[#This Row],[Object ID]],4)="tbl-","fig-" & MID(Table3[[#This Row],[Object ID]],5,LEN(Table3[[#This Row],[Object ID]])-4),"") -> fig-siena-feeling-nervous-income
C298: Figure | E298: F234 | F298: Feeling Hopeless, 2023-2024 | G298: tbl-siena-feeling-hopeless | H298: =IF(LEFT(Table3[[#This Row],[Object ID]],4)="tbl-","fig-" & MID(Table3[[#This Row],[Object ID]],5,LEN(Table3[[#This Row],[Object ID]])-4),"") -> fig-siena-feeling-hopeless
C299: Figure | E299: F235 | F299: Feeling Hopeless by Income, 2024 | G299: tbl-siena-feeling-hopeless-income | H299: =IF(LEFT(Table3[[#This Row],[Object ID]],4)="tbl-","fig-" & MID(Table3[[#This Row],[Object ID]],5,LEN(Table3[[#This Row],[Object ID]])-4),"") -> fig-siena-feeling-hopeless-income
C300: Figure | E300: F236 | F300: Feeling Restless or Fidgety, 2023-2024 | G300: tbl-siena-restless-fidgety | H300: =IF(LEFT(Table3[[#This Row],[Object ID]],4)="tbl-","fig-" & MID(Table3[[#This Row],[Object ID]],5,LEN(Table3[[#This Row],[Object ID]])-4),"") -> fig-siena-restless-fidgety
C301: Figure | E301: F237 | F301: Feeling Restless or Fidgety by Income, 2024 | G301: tbl-siena-restless-fidgety-income | H301: =IF(LEFT(Table3[[#This Row],[Object ID]],4)="tbl-","fig-" & MID(Table3[[#This Row],[Object ID]],5,LEN(Table3[[#This Row],[Object ID]])-4),"") -> fig-siena-restless-fidgety-income
C302: Figure | E302: F238 | F302: Feeling Depressed, 2023-2024 | G302: tbl-siena-depressed | H302: =IF(LEFT(Table3[[#This Row],[Object ID]],4)="tbl-","fig-" & MID(Table3[[#This Row],[Object ID]],5,LEN(Table3[[#This Row],[Object ID]])-4),"") -> fig-siena-depressed
C303: Figure | E303: F239 | F303: Feeling Depressed by Income, 2024 | G303: tbl-siena-depressed-income | H303: =IF(LEFT(Table3[[#This Row],[Object ID]],4)="tbl-","fig-" & MID(Table3[[#This Row],[Object ID]],5,LEN(Table3[[#This Row],[Object ID]])-4),"") -> fig-siena-depressed-income
C304: Figure | E304: F240 | F304: Feeling that Everything was an Effort, 2023-2024 | G304: tbl-siena-everything-effort | H304: =IF(LEFT(Table3[[#This Row],[Object ID]],4)="tbl-","fig-" & MID(Table3[[#This Row],[Object ID]],5,LEN(Table3[[#This Row],[Object ID]])-4),"") -> fig-siena-everything-effort
C305: Figure | E305: F241 | F305: Feeling that Everything was an Effort by Income, 2024 | G305: tbl-siena-everything-effort-income | H305: =IF(LEFT(Table3[[#This Row],[Object ID]],4)="tbl-","fig-" & MID(Table3[[#This Row],[Object ID]],5,LEN(Table3[[#This Row],[Object ID]])-4),"") -> fig-siena-everything-effort-income
... C320: Table | E320: T69 | F320: Short Term Process Indicators and Progress at of 2024 | G320: tbl-short-term-process | H320: =IF(LEFT(Table3[[#This Row],[Object ID]],4)="tbl-","fig-" & MID(Table3[[#This Row],[Object ID]],5,LEN(Table3[[#This Row],[Object ID]])-4),"") -> fig-short-term-process
F321: Primary Focus Groups Themes | G321: tbl-primary-focus-groups | H321: =IF(LEFT(Table3[[#This Row],[Object ID]],4)="tbl-","fig-" & MID(Table3[[#This Row],[Object ID]],5,LEN(Table3[[#This Row],[Object ID]])-4),"") -> fig-primary-focus-groups

Sheet Dropdowns
A1: integer | B1: Y-labels | D1: Footnotes | E1: Sources | F1: Links
A2: number | B2: Case Rate | C2: * | D2: *: BRFSS - Crude rate is unreliable due to large standard error. | E2: Source: Centers for Disease Control and Prevention | F2: https://health.data.ny.gov/Health/Behavioral-Risk-Factor-Surveillance-System-BRFSS-H/jsy7-eb4n/data
A3: percent1 | B3: Index | C3: * | D3: *: BRFSS - Percentage is unreliable due to large standard error. | E3: Source: Community Partner Survey Focus Groups | F3: https://www.cdc.gov/places/
A4: percent2 | B4: Number of Cases | C4: * | D4: *: Data are unstable due to a margin of error greater than 10%. | E4: Source: Feeding America | F4: https://webbi1.health.ny.gov/SASStoredProcess/guest?_program=%2FEBI%2FPHIG%2Fapps%2Fchir_dashboard%2Fchir_dashboard&p=ch&cos=33
A5: currency | B5: Percent | C5: * | D5: *: Data are unstable due to fewer than 10 events in the numerator. | E5: Source: Health Resources and Services Administration Data Warehouse | F5: https://www.health.ny.gov/statistics/community/minority/county/orange.htm
A6: currency2 | B6: Rate per 1,000 | C6: * | D6: *: Data are unstable due to fewer than 20 events in the numerator. | E6: Source: NYC Poison Center | F6: https://www.health.ny.gov/statistics/diseases/communicable/docs/2019_hepc_regional.pdf
A7: ratio | B7: Rate per 10,000 | C7: * | D7: *: The percentage is unstable. | E7: Source: NYS Board of Elections | F7: https://www.health.ny.gov/statistics/chac/perinatal/county/2018-2020/orange.htm
A8: date | B8: Rate per 100,000 | C8: * | D8: *: The rate is unstable. | E8: Source: NYS Cancer Registry and Cancer Statistics | F8: https://www.criminaljustice.ny.gov/crimnet/ojsa/arrests/index.htm
A9: text | B9: Ratio | C9: + | D9: : The 2019 ED data in NYC may be incomplete and subject to change. Thus, the state rates may be underestimated and subject to change. | E9: Source: NYS Community Health Indicator Reports Dashboard | F9: https://data.nysed.gov/gradrate.php?year=2022&county=44
C10: Other | D10: Other (please specify): Some additional responses from participants include access to healthy affordable food, transportation, valuing health as a family priority, affordable housing, lack of chronic disease self-management programs, lack of social support systems, language barriers. | E10: Source: NYS County Health Indicators by Race and Ethnicity | F10: https://webbi1.health.ny.gov/SASStoredProcess/guest?_program=%2FEBI%2FPHIG%2Fapps%2Fmch_dashboard%2Fmch_dashboard&p=ch&cos=33
C11: Other | D11: Other (please specify): Some additional responses from participants include finding child care, access to health care providers who are trained in LGBTQIA+ health care needs, mental health services, immigration issues, language and cultural barriers, and financial issues. | E11: Source: NYS Department of Health Office of Sexual Health and Epidemiology | F11: https://webbi1.health.ny.gov/SASStoredProcess/guest?_program=%2FEBI%2FPHIG%2Fapps%2Fopioid_dashboard%2Fop_dashboard&p=ch&cos=33
C12: Other | D12: Other (please specify): Some additional responses from participants include location of services, lack of financial resources, transportation, affordable housing, and service providers not being aware of biases they bring into marginalized communities. | E12: Source: NYS Division of Criminal Justice Services | F12: https://webbi1.health.ny.gov/SASStoredProcess/guest?_program=%2FEBI%2FPHIG%2Fapps%2Fdashboard%2Fpa_dashboard&p=ch&cos=33
C13: Other | D13: Other (please specify): Some additional responses from participants include navigating health care access, poverty, affordable transportation, and accessibility and availability of quality services. | E13: Source: NYS Education Department | F13: https://www.health.ny.gov/statistics/diseases/communicable/std/docs/sti_surveillance_report_2021.pdf
C14: Other | D14: Other (please specify): Some additional responses from participants include stigma, language barrier as a large portion of the population being served speaks Spanish, navigating the health system, and places to play and/or exercise. | E14: Source: NYS Leading Causes of Death Dashboard | F14: https://statecancerprofiles.cancer.gov/
C15: s | D15: s: Data are suppressed due to unreliable or missing data. | E15: Source: NYS Opioid Data Dashboard | F15: https://data.census.gov/cedsci/
C16: s | D16: s: Data are suppressed due to not meeting reporting criteria. | E16: Source: NYS Prevention Agenda Tracking Dashboard | F16: https://www.americashealthrankings.org/
C17: s | D17: s: Data are suppressed due to lack of preliminary data. | E17: Source: NYS Smoker's Quitline | F17: https://ahead.hiv.gov/
C18: s | D18: s: Data are suppressed due to not meeting confidentialty criteria. | E18: Source: NYSDOH Behavioral Risk Factor Surveillance System | F18: https://wonder.cdc.gov/
C19: s | D19: s: Data are suppressed due to small sample size. | E19: Source: NYSDOH Bureau of Communicable Disease Control | F19: https://nccd.cdc.gov/Youthonline/App/Results.aspx?LID=XX
E20: Source: NYSDOH Communicable Disease Annual Reports | F20: https://www.cdc.gov/injury/wisqars/index.html
E21: Source: NYSDOH Communicable Disease Electronic Surveillance System | F21: https://www.cdc.gov/mmwr/index.html
E22: Source: NYSDOH, Wadsworth Center Rabies Laboratory | F22: https://www.cdc.gov/asthma/asthmadata.htm
E23: Source: United for ALICE | F23: https://www.cdc.gov/nceh/
E24: Source: University of Wisconsin Population Health Institute. County Health Rankings & Roadmaps | F24: https://www.cdc.gov/nchs/index.htm
E25: Source: Upstate NY Poison Center | F25: https://www.cdc.gov/nchs/nhis/shs.htm
E26: Source: US Census Bureau | F26: https://www.cdc.gov/diabetes/data/index.html
E27: Source: US Census Bureau; American Community Survey | F27: https://www.cdc.gov/nchhstp/atlas/index.htm
E28: Source: Vital Statistics of NYS | F28: https://www.cdc.gov/std/statistics/2021/default.htm
F29: https://www.cdc.gov/vaccines/imz-managers/coverage/teenvaxview/data-reports/index.html
F30: https://gis.cdc.gov/grasp/diabetes/diabetesatlas-surveillance.html
F31: https://www.cdc.gov/hepatitis/statistics/SurveillanceRpts.htm
F32: https://www.ghrconnects.org/indicators
F33: https://www.kff.org/
F34: https://progressreport.cancer.gov/detection
F35: https://statecancerprofiles.cancer.gov/index.html
F36: https://nces.ed.gov/
F37: https://www.niaaa.nih.gov/
F38: https://data.oecd.org/
F39: https://data.census.gov/cedsci/
F40: https://www.bls.gov/cps/data-overview.htm
F41: https://health.gov/healthypeople

Sheet Demographic Summary
A1: Name | B1: Demographic Summary by Municipality, 2023
A2: Table/Figure/Both | B2: Both
A3: Object ID | B3: =IF($B$1="","",_xlfn.XLOOKUP($B$1,Master!$F$2:$F$321,Master!$G$2:$G$321,"")) -> tbl-demographics-sum
A4: Figure ID | B4: =IF($B$1="","",_xlfn.XLOOKUP($B$1,Master!$F$2:$F$321,Master!$H$2:$H$321,"")) -> fig-demographics-sum | F4: text | G4: number | H4: number | I4: number | J4: number | K4: number | L4: number | M4: number | N4: percent1
A5: Table Rules | E5: Enter Data | F5: Geographic Area | G5: Population | H5: Age | L5: Sex | N5: Median Age
A6: Multilevel Headers | B6: TRUE | G6: Total | H6: 0-17 year | I6: 18-24 years | J6: 25-64 years | K6: 65+ years | L6: Male | M6: Female
F7: Orange County | G7: 403840 | H7: 103740 | I7: 41468 | J7: 200687 | K7: 57945 | L7: 201512 | M7: 202328 | N7: 36.9
F8: Blooming Grove Town | G8: 18672 | H8: 5333 | I8: 1742 | J8: 9322 | K8: 2275 | L8: 9133 | M8: 9539 | N8: 34.4
A9: Figure Rules | F9: South Blooming Grove Village | G9: 3880 | H9: 1658 | I9: 263 | J9: 1622 | K9: 337 | L9: 1933 | M9: 1947 | N9: 25.2
A10: Figure Type | F10: Washingtonville Village | G10: 5723 | H10: 1287 | I10: 430 | J10: 3121 | K10: 885 | L10: 2883 | M10: 2840 | N10: 39.1
A11: X Column | F11: Chester Town | G11: 12621 | H11: 2702 | I11: 1198 | J11: 6927 | K11: 1794 | L11: 5839 | M11: 6782 | N11: 39.1
A12: Y Column | F12: Chester Village | G12: 4052 | H12: 738 | I12: 313 | J12: 2451 | K12: 550 | L12: 1961 | M12: 2,091 | N12: 36.5
A13: X Axis Title | F13: Cornwall Town | G13: 12801 | H13: 2714 | I13: 1148 | J13: 6435 | K13: 2504 | L13: 6218 | M13: 6,583 | N13: 42.4
A14: Y Axis Title | F14: Cornwall-on-Hudson Village | G14: 3046 | H14: 593 | I14: 321 | J14: 1580 | K14: 552 | L14: 1460 | M14: 1586 | N14: 44.7
A15: Start at Zero | F15: Crawford Town | G15: 9097 | H15: 2086 | I15: 814 | J15: 5014 | K15: 1183 | L15: 4732 | M15: 4365 | N15: 40.8
A16: Pivot For Chart | F16: Deerpark Town | G16: 7471 | H16: 1512 | I16: 508 | J16: 3786 | K16: 1665 | L16: 3753 | M16: 3718 | N16: 45.4
F17: Goshen Town | G17: 14463 | H17: 2871 | I17: 1226 | J17: 7303 | K17: 3063 | L17: 7390 | M17: 7073 | N17: 44.7
A18: Source Specifications | F18: Goshen Village | G18: 5751 | H18: 1108 | I18: 367 | J18: 2744 | K18: 1532 | L18: 2745 | M18: 3006 | N18: 48
A19: Source | B19: Source: US Census Bureau, American Community Survey, 2019–2023 5-Year Population Estimates, Table DP05-Demographic and Housing Estimates, November 2025 https://data.census.gov/table/ACSDP5Y2023.DP05?q=DP05+Orange+County,+NY&g=050XX00US36071 | F19: Greenville Town | G19: 4680 | H19: 1167 | I19: 266 | J19: 2637 | K19: 610 | L19: 2458 | M19: 2222 | N19: 37.8
F20: Hamptonburgh Town | G20: 5507 | H20: 1280 | I20: 499 | J20: 2943 | K20: 785 | L20: 2924 | M20: 2583 | N20: 44.3
A21: Note Specfications | F21: Highlands Town | G21: 12,894 | H21: 3,027 | I21: 3,203 | J21: 5,600 | K21: 1,064 | L21: 7,397 | M21: 5,497 | N21: 27.2
A22: Note | B22: Note: Town totals include Village totals. The Village of Harriman is split between the Towns of Monroe and Woodbury. | F22: Highland Falls Village | G22: 3,696 | H22: 773 | I22: 278 | J22: 2,198 | K22: 447 | L22: 2,000 | M22: 1,696 | N22: 40.7
F23: Middletown City | G23: 30,227 | H23: 7,796 | I23: 2,553 | J23: 15768 | K23: 4110 | L23: 15640 | M23: 14587 | N23: 35.7
F24: Minisink Town | G24: 4,648 | H24: 1,277 | I24: 476 | J24: 2371 | K24: 524 | L24: 2246 | M24: 2402 | N24: 36.5
F25: Unionville Village | G25: 684 | H25: 222 | I25: 79 | J25: 304 | K25: 79 | L25: 282 | M25: 402 | N25: 30.5
F26: Monroe Town | G26: 21,299 | H26: 5,787 | I26: 2,035 | J26: 10438 | K26: 3039 | L26: 9782 | M26: 11517 | N26: 36.8
F27: Harriman Village (portion) | G27: 2089 | H27: 598 | I27: 95 | J27: 1033 | K27: 363 | L27: 877 | M27: 1212 | N27: 37
F28: Monroe Village | G28: 9466 | H28: 2552 | I28: 1,118 | J28: 4846 | K28: 950 | L28: 4473 | M28: 4993 | N28: 32.8
F29: Montgomery Town | G29: 23235 | H29: 5597 | I29: 2,052 | J29: 12228 | K29: 3358 | L29: 11058 | M29: 12177 | N29: 39.4
F30: Maybrook Village | G30: 3147 | H30: 507 | I30: 208 | J30: 1772 | K30: 660 | L30: 1451 | M30: 1696 | N30: 46.5
F31: Montgomery Village | G31: 3800 | H31: 962 | I31: 325 | J31: 1960 | K31: 553 | L31: 1722 | M31: 2078 | N31: 39.8
F32: Walden Village | G32: 6871 | H32: 1664 | I32: 659 | J32: 3732 | K32: 816 | L32: 3498 | M32: 3373 | N32: 38.1
F33: Mount Hope Town | G33: 6,500 | H33: 1,080 | I33: 485 | J33: 3856 | K33: 1079 | L33: 3897 | M33: 2603 | N33: 44.3
F34: Otisville Village | G34: 1210 | H34: 353 | I34: 56 | J34: 564 | K34: 237 | L34: 623 | M34: 587 | N34: 35.6
F35: Newburgh City | G35: 28649 | H35: 7379 | I35: 3,337 | J35: 14393 | K35: 3540 | L35: 13424 | M35: 15225 | N35: 31.7
F36: Newburgh Town | G36: 31866 | H36: 6121 | I36: 2,988 | J36: 17297 | K36: 5460 | L36: 16112 | M36: 15754 | N36: 41.8
F37: New Windsor Town | G37: 27781 | H37: 5691 | I37: 2,448 | J37: 15049 | K37: 4593 | L37: 13475 | M37: 14306 | N37: 41.4
F38: Palm Tree Town | G38: 36572 | H38: 20811 | I38: 5,257 | J38: 9535 | K38: 969 | L38: 18558 | M38: 18014 | N38: 15.1
F39: Kiryas Joel Village | G39: 36,572 | H39: 20,811 | I39: 5,257 | J39: 9535 | K39: 969 | L39: 18558 | M39: 18014 | N39: 15.1
F40: Port Jervis City | G40: 8,709 | H40: 1,809 | I40: 1,076 | J40: 4209 | K40: 1615 | L40: 4267 | M40: 4442 | N40: 39.6
F41: Tuxedo Town | G41: 3,765 | H41: 702 | I41: 240 | J41: 1954 | K41: 869 | L41: 1975 | M41: 1790 | N41: 48.4
F42: Tuxedo Village | G42: 3083 | H42: 620 | I42: 228 | J42: 1543 | K42: 692 | L42: 1546 | M42: 1537 | N42: 45.1
F43: Tuxedo Park Village | G43: 682 | H43: 82 | I43: 12 | J43: 411 | K43: 177 | L43: 429 | M43: 253 | N43: 51.9
F44: Wallkill Town | G44: 30790 | H44: 5920 | I44: 3341 | J44: 16353 | K44: 5176 | L44: 15650 | M44: 15140 | N44: 41.3
F45: Warwick Town | G45: 31909 | H45: 6273 | I45: 2216 | J45: 17141 | K45: 6279 | L45: 15794 | M45: 16115 | N45: 44.1
F46: Florida Village | G46: 2915 | H46: 620 | I46: 278 | J46: 1575 | K46: 442 | L46: 1566 | M46: 1349 | N46: 36
F47: Greenwood Lake Village | G47: 3022 | H47: 529 | I47: 101 | J47: 1760 | K47: 632 | L47: 1471 | M47: 1551 | N47: 42.2
F48: Warwick Village | G48: 6625 | H48: 1274 | I48: 418 | J48: 3125 | K48: 1808 | L48: 2921 | M48: 3704 | N48: 48.4
F49: Wawayanda Town | G49: 7493 | H49: 1726 | I49: 882 | J49: 3842 | K49: 1043 | L49: 3585 | M49: 3908 | N49: 39.2
F50: Woodbury Town | G50: 12191 | H50: 3079 | I50: 1478 | J50: 6286 | K50: 1348 | L50: 6205 | M50: 5986 | N50: 40
F51: Harriman Village (portion) | G51: 754 | H51: 149 | I51: 39 | J51: 505 | K51: 61 | L51: 337 | M51: 417 | N51: 37
F52: Woodbury Village | G52: 11437 | H52: 2930 | I52: 1439 | J52: 5781 | K52: 1287 | L52: 5868 | M52: 5569 | N52: 39.7

Sheet Population by Municipality
A1: Name | B1: Population by Municipality, 1970–2020
A2: Table/Figure/Both | B2: Both
A3: Object ID | B3: =IF($B$1="","",_xlfn.XLOOKUP($B$1,Master!$F$2:$F$321,Master!$G$2:$G$321,"")) -> tbl-pop
A4: Figure ID | B4: =IF($B$1="","",_xlfn.XLOOKUP($B$1,Master!$F$2:$F$321,Master!$H$2:$H$321,"")) -> fig-pop | F4: text | G4: number | H4: number | I4: number | J4: number | K4: number | L4: number
A5: Table Rules | E5: Enter Data | F5: Geographic Area | G5: Population
A6: Multilevel Headers | G6: 1970 | H6: 1980 | I6: 1990 | J6: 2000 | K6: 2010 | L6: 2020
F7: Orange County | G7: 221657 | H7: 259603 | I7: 307647 | J7: 341367 | K7: 372813 | L7: 401310
F8: Blooming Grove Town | G8: 8813 | H8: 12339 | I8: 16673 | J8: 17351 | K8: 18028 | L8: 18811
A9: Figure Rules | F9: South Blooming Grove Village | G9: N/A | H9: N/A | I9: N/A | J9: N/A | K9: 3234 | L9: 3973
A10: Figure Type | F10: Washingtonville Village | G10: 1887 | H10: 2380 | I10: 4906 | J10: 5851 | K10: 5899 | L10: 5657
A11: X Column | F11: Chester Town | G11: 4767 | H11: 6850 | I11: 9138 | J11: 12140 | K11: 11981 | L11: 12646
A12: Y Column | F12: Chester Village | G12: 1627 | H12: 1910 | I12: 3270 | J12: 3445 | K12: 3969 | L12: 3993
A13: X Axis Title | F13: Cornwall Town | G13: 9672 | H13: 10774 | I13: 11270 | J13: 12307 | K13: 12646 | L13: 12884
A14: Y Axis Title | F14: Cornwall-on-Hudson Village | G14: 3131 | H14: 3164 | I14: 3093 | J14: 3058 | K14: 3018 | L14: 3075
A15: Start at Zero | F15: Crawford Town | G15: 3896 | H15: 4910 | I15: 6394 | J15: 7875 | K15: 9316 | L15: 9130
A16: Pivot For Chart | F16: Deerpark Town | G16: 4370 | H16: 5633 | I16: 7832 | J16: 7858 | K16: 7901 | L16: 7509
F17: Goshen Town | G17: 8393 | H17: 10463 | I17: 11500 | J17: 12913 | K17: 13687 | L17: 14571
A18: Source Specifications | F18: Goshen Village | G18: 4342 | H18: 4874 | I18: 5255 | J18: 5676 | K18: 5454 | L18: 5777
A19: Source | B19: Source: US Census Bureau, 2020 Decennial Redistricting Data (PL 94-171), Table P1-Total Population, November 2025 https://data.census.gov/table/DECENNIALPL2020.P1?q=PL+94-171&g=050XX00US36071 | F19: Greenville Town | G19: 1379 | H19: 2085 | I19: 3120 | J19: 3800 | K19: 4616 | L19: 4689
F20: Hamptonburgh Town | G20: 2204 | H20: 2945 | I20: 3910 | J20: 4686 | K20: 5561 | L20: 5489
A21: Note Specfications | F21: Highlands Town | G21: 14661 | H21: 14004 | I21: 13667 | J21: 12484 | K21: 12492 | L21: 12939
A22: Note | B22: Note: Town totals include Village totals; Village of Kiryas Joel was incorporated in 1977; Villages of South Blooming Grove and Woodbury were incorporated in 2006; Town of Palm Tree was incorporated in 2017 and made coterminous to the Village of Kiryas Joel thereafter. Prior to incorporation of Town of Palm Tree, the Village of Kiryas Joel was incorporated within the boundaries of the Town of Monroe | F22: Highland Falls Village | G22: 4638 | H22: 4187 | I22: 3937 | J22: 3678 | K22: 3900 | L22: 3684
F23: Middletown City | G23: 22607 | H23: 21454 | I23: 24160 | J23: 25388 | K23: 28086 | L23: 30345
F24: Minisink Town | G24: 1942 | H24: 2488 | I24: 2981 | J24: 3585 | K24: 4490 | L24: 4621
F25: Unionville Village | G25: 576 | H25: 574 | I25: 548 | J25: 536 | K25: 612 | L25: 592
F26: Monroe Town | G26: 9190 | H26: 14948 | I26: 23035 | J26: 31407 | K26: 39912 | L26: 21387
F27: Harriman Village (portion) | G27: 955 | H27: 796 | I27: 2288 | J27: 2252 | K27: 2424 | L27: 2714
F28: Monroe Village | G28: 4439 | H28: 5996 | I28: 6672 | J28: 7780 | K28: 8364 | L28: 9343
F29: Montgomery Town | G29: 13995 | H29: 16576 | I29: 18501 | J29: 20891 | K29: 22606 | L29: 23322
F30: Maybrook Village | G30: 1536 | H30: 2007 | I30: 2802 | J30: 3084 | K30: 2958 | L30: 3150
F31: Montgomery Village | G31: 1533 | H31: 2316 | I31: 2696 | J31: 3636 | K31: 3814 | L31: 3834
F32: Walden Village | G32: 5277 | H32: 5659 | I32: 5836 | J32: 6164 | K32: 6978 | L32: 6818
F33: Mount Hope Town | G33: 2966 | H33: 4398 | I33: 5971 | J33: 6639 | K33: 7018 | L33: 6537
F34: Otisville Village | G34: 933 | H34: 953 | I34: 1078 | J34: 989 | K34: 1068 | L34: 989
... F37: New Windsor Town | G37: 16650 | H37: 19534 | I37: 22937 | J37: 22866 | K37: 25244 | L37: 27805
F38: Palm Tree Town | G38: N/A | H38: N/A | I38: N/A | J38: N/A | K38: N/A | L38: 32954
F39: Kiryas Joel Village | G39: 0 | H39: 2088 | I39: 7437 | J39: 13138 | K39: 20175 | L39: 32954
F40: Port Jervis City | G40: 8852 | H40: 8699 | I40: 9060 | J40: 8860 | K40: 8828 | L40: 8775
F41: Tuxedo Town | G41: 2967 | H41: 3069 | I41: 3023 | J41: 3334 | K41: 3624 | L41: 3811
F42: Tuxedo Village | G42: 861 | H42: 809 | I42: 706 | J42: 731 | K42: 623 | L42: 645
F43: Tuxedo Park Village | G43: 11518 | H43: 20481 | I43: 23016 | J43: 24659 | K43: 27426 | L43: 30486
F44: Wallkill Town | G44: 16956 | H44: 20976 | I44: 27193 | J44: 30764 | K44: 32065 | L44: 32027
F45: Warwick Town | G45: 1674 | H45: 1947 | I45: 2497 | J45: 2571 | K45: 2833 | L45: 2888
F46: Florida Village | G46: 2262 | H46: 2809 | I46: 3208 | J46: 3411 | K46: 3154 | L46: 2994
F47: Greenwood Lake Village | G47: 3604 | H47: 4320 | I47: 5984 | J47: 6412 | K47: 6731 | L47: 6652
F48: Warwick Village | G48: 3408 | H48: 4298 | I48: 5518 | J48: 6273 | K48: 7266 | L48: 7534
F49: Wawayanda Town | G49: 4639 | H49: 6494 | I49: 8236 | J49: 9460 | K49: 11353 | L49: 12197
F50: Woodbury Town | G50: N/A | H50: N/A | I50: N/A | J50: N/A | K50: 10686 | L50: 11526
F51: Harriman Village (portion) | G51: N/A | H51: N/A | I51: N/A | J51: N/A | K51: N/A | L51: N/A
F52: Woodbury Village | G52: N/A | H52: N/A | I52: N/A | J52: N/A | K52: N/A | L52: N/A

Sheet Population Growth
A1: Name | B1: Population Growth by Municipality, 2000–2020
A2: Table/Figure/Both | B2: Both
A3: Object ID | B3: =IF($B$1="","",_xlfn.XLOOKUP($B$1,Master!$F$2:$F$321,Master!$G$2:$G$321,"")) -> tbl-pop-growth
A4: Figure ID | B4: =IF($B$1="","",_xlfn.XLOOKUP($B$1,Master!$F$2:$F$321,Master!$H$2:$H$321,"")) -> fig-pop-growth | F4: text | G4: number | H4: number | I4: number | J4: percent1 | K4: percent1 | L4: percent1
A5: Table Rules | E5: Enter Data | F5: Geographic Area | G5: Total Population | J5: Percent Change
A6: Multilevel Headers | B6: FALSE | G6: 2000 | H6: 2010 | I6: 2020 | J6: 2000-2010 | K6: 2010-2020 | L6: 2000-20
F7: Orange County | G7: 341367 | H7: 372813 | I7: 401310 | J7: 9.2 | K7: 7.6 | L7: 17.6
F8: Blooming Grove Town | G8: 17351 | H8: 18028 | I8: 18811 | J8: 3.9 | K8: 4.3 | L8: 8.4
A9: Figure Rules | F9: South Blooming Grove Village | G9: n/a | H9: 3234 | I9: 3973 | J9: N/A | K9: 22.9 | L9: N/A
A10: Figure Type | F10: Washingtonville Village | G10: 5851 | H10: 5899 | I10: 5657 | J10: 0.8 | K10: -4.1 | L10: -3.3
A11: X Column | F11: Chester Town | G11: 12140 | H11: 11981 | I11: 12646 | J11: -1.3 | K11: 5.6 | L11: 4.2
A12: Y Column | F12: Chester Village | G12: 3445 | H12: 3969 | I12: 3993 | J12: 15.2 | K12: 0.6 | L12: 15.9
A13: X Axis Title | F13: Cornwall Town | G13: 12307 | H13: 12646 | I13: 12884 | J13: 2.8 | K13: 1.9 | L13: 4.7
A14: Y Axis Title | F14: Cornwall-on-Hudson Village | G14: 3058 | H14: 3018 | I14: 3075 | J14: -1.3 | K14: 1.9 | L14: 0.6
A15: Start at Zero | F15: Crawford Town | G15: 7875 | H15: 9316 | I15: 9130 | J15: 18.3 | K15: -2 | L15: 15.9
A16: Pivot For Chart | F16: Deerpark Town | G16: 7858 | H16: 7901 | I16: 7509 | J16: 0.5 | K16: -5 | L16: -4.4
F17: Goshen Town | G17: 12913 | H17: 13687 | I17: 14571 | J17: 6 | K17: 6.5 | L17: 12.8
A18: Source Specifications | F18: Goshen Village | G18: 5676 | H18: 5454 | I18: 5777 | J18: -3.9 | K18: 5.9 | L18: 1.8
A19: Source | B19: Source: US Census Bureau, 2020 Decennial Redistricting Data (PL 94-171), Table P, November 2025 https://data.census.gov/table/DECENNIALPL2020.P1?q=PL+94-171&g=050XX00US36071 | F19: Greenville Town | G19: 3800 | H19: 4616 | I19: 4689 | J19: 21.5 | K19: 1.6 | L19: 23.4
F20: Hamptonburgh Town | G20: 4686 | H20: 5561 | I20: 5489 | J20: 18.7 | K20: -1.3 | L20: 17.1
A21: Note Specfications | F21: Highlands Town | G21: 12484 | H21: 12492 | I21: 12939 | J21: 0.1 | K21: 3.6 | L21: 3.6
A22: Note | B22: Note: Town totals include Village totals; Villages of South Blooming Grove and Woodbury were incorporated in 2006; Town of Palm Tree was incorporated in 2017 and made coterminous to the Village of Kiryas Joel thereafter. Prior to incorporation of Town of Palm Tree, the Village of Kiryas Joel was incorporated within the boundaries of the Town of Monroe. | F22: Highland Falls Village | G22: 3678 | H22: 3900 | I22: 3684 | J22: 6 | K22: -5.5 | L22: 0.2
F23: Middletown City | G23: 25388 | H23: 28086 | I23: 30345 | J23: 10.6 | K23: 8 | L23: 19.5
F24: Minisink Town | G24: 3585 | H24: 4490 | I24: 4621 | J24: 25.2 | K24: 2.9 | L24: 28.9
F25: Unionville Village | G25: 536 | H25: 612 | I25: 592 | J25: 14.2 | K25: -3.3 | L25: 10.4
F26: Monroe Town | G26: 31407 | H26: 39912 | I26: 21387 | J26: 27.1 | K26: -46.4 | L26: -31.9
F27: Harriman Village (portion) | G27: 2252 | H27: 2424 | I27: 2714 | J27: 7.6 | K27: 12 | L27: 20.5
F28: Monroe Village | G28: 7780 | H28: 8364 | I28: 9343 | J28: 7.5 | K28: 11.7 | L28: 20.1
F29: Montgomery Town | G29: 20891 | H29: 22606 | I29: 23322 | J29: 8.2 | K29: 3.2 | L29: 11.6
F30: Maybrook Village | G30: 3084 | H30: 2958 | I30: 3150 | J30: -4.1 | K30: 6.5 | L30: 2.1
F31: Montgomery Village | G31: 3636 | H31: 3814 | I31: 3834 | J31: 4.9 | K31: 0.5 | L31: 5.4
F32: Walden Village | G32: 6164 | H32: 6978 | I32: 6818 | J32: 13.2 | K32: -2.3 | L32: 10.6
F33: Mount Hope Town | G33: 6639 | H33: 7018 | I33: 6537 | J33: 5.7 | K33: -6.9 | L33: -1.5
F34: Otisville Village | G34: 989 | H34: 1068 | I34: 989 | J34: 8 | K34: -7.4 | L34: 0
... F37: New Windsor Town | G37: 22866 | H37: 25244 | I37: 27805 | J37: 10.4 | K37: 10.1 | L37: 21.6
F38: Palm Tree Town | G38: N/A | H38: N/A | I38: 32954 | J38: N/A | K38: N/A | L38: N/A
F39: Kiryas Joel Village | G39: 13138 | H39: 20175 | I39: 32954 | J39: 53.6 | K39: 63.3 | L39: 150.8
F40: Port Jervis City | G40: 8860 | H40: 8828 | I40: 8775 | J40: -0.4 | K40: -0.6 | L40: -1
F41: Tuxedo Town | G41: 3334 | H41: 3624 | I41: 3811 | J41: 8.7 | K41: 5.2 | L41: 14.3
F42: Tuxedo Village | G42: 731 | H42: 623 | I42: 645 | J42: -14.8 | K42: 3.5 | L42: -11.8
F43: Tuxedo Park Village | G43: 24659 | H43: 27426 | I43: 30486 | J43: 11.2 | K43: 11.2 | L43: 23.6
F44: Wallkill Town | G44: 30764 | H44: 32065 | I44: 32027 | J44: 4.2 | K44: -0.1 | L44: 4.1
F45: Warwick Town | G45: 2571 | H45: 2833 | I45: 2888 | J45: 10.2 | K45: 1.9 | L45: 12.3
F46: Florida Village | G46: 3411 | H46: 3154 | I46: 2994 | J46: -7.5 | K46: -5.1 | L46: -12.2
F47: Greenwood Lake Village | G47: 6412 | H47: 6731 | I47: 6652 | J47: 5 | K47: -1.2 | L47: 3.7
F48: Warwick Village | G48: 6273 | H48: 7266 | I48: 7534 | J48: 15.8 | K48: 3.7 | L48: 20.1
F49: Wawayanda Town | G49: 9460 | H49: 11353 | I49: 12197 | J49: 20 | K49: 7.4 | L49: 28.9
F50: Woodbury Town | G50: N/A | H50: 10686 | I50: 11526 | J50: N/A | K50: 7.9 | L50: N/A
F51: Harriman Village (portion) | G51: N/A | H51: N/A | I51: N/A | J51: N/A | K51: N/A | L51: N/A
F52: Woodbury Village | G52: N/A | H52: N/A | I52: N/A | J52: N/A | K52: N/A | L52: N/A

Sheet Population and Housing Unit Den
A1: Name | B1: Population and Housing Unit Density by Municipality, 2023
A2: Table/Figure/Both | B2: Both
A3: Object ID | B3: =IF($B$1="","",_xlfn.XLOOKUP($B$1,Master!$F$2:$F$321,Master!$G$2:$G$321,"")) -> tbl-pop-housing-density
A4: Figure ID | B4: =IF($B$1="","",_xlfn.XLOOKUP($B$1,Master!$F$2:$F$321,Master!$H$2:$H$321,"")) -> fig-pop-housing-density | F4: text | G4: percent1 | H4: percent1 | I4: percent1
A5: Table Rules | E5: Enter Data | F5: Geographic Area | G5: Land Area per Square Mile | H5: People per Square Mile | I5: Housing Units per Square Mile
A6: Multilevel Headers | B6: FALSE | F6: Orange County | G6: 812.3 | H6: 497.1 | I6: 182.8
F7: Blooming Grove Town | G7: 34.7 | H7: 537.6 | I7: 198.2
F8: South Blooming Grove Village | G8: 4.7 | H8: 829.1 | I8: 297
A9: Figure Rules | F9: Washingtonville Village | G9: 2.5 | H9: 2253.2 | I9: 860.6
A10: Figure Type | F10: Chester Town | G10: 25.1 | H10: 503.8 | I10: 190.1
A11: X Column | F11: Chester Village | G11: 2.2 | H11: 1884.7 | I11: 784.7
A12: Y Column | F12: Cornwall Town | G12: 26.7 | H12: 480.2 | I12: 201.3
A13: X Axis Title | F13: Cornwall-on-Hudson Village | G13: 2 | H13: 1530.7 | I13: 671.9
A14: Y Axis Title | F14: Crawford Town | G14: 40 | H14: 227.3 | I14: 77.3
A15: Start at Zero | F15: Deerpark Town | G15: 66.5 | H15: 112.4 | I15: 50.3
A16: Pivot For Chart | F16: Goshen Town | G16: 43.6 | H16: 331.4 | I16: 123.1
F17: Goshen Village | G17: 3.3 | H17: 1732.2 | I17: 778
A18: Source Specifications | F18: Greenville Town | G18: 38.9 | H18: 120.3 | I18: 45.6
A19: Source | B19: Source: US Census Bureau, Quick Facts, November 2025 https://www.census.gov/quickfacts/orangecountynewyork | F19: Hamptonburgh Town | G19: 26.8 | H19: 205.8 | I19: 68.8
F20: Highlands Town | G20: 30.4 | H20: 424.1 | I20: 139.5
A21: Note Specfications | F21: Highland Falls Village | G21: 1.1 | H21: 3390.8 | I21: 1649.5
A22: Note | B22: Note: Town totals include Village totals. Land area calculated as of 2020 Census. Population density and housing unit density calculated using 2019-2023 estimates divided by land area. | F22: Middletown City | G22: 5.3 | H22: 5692.5 | I22: 2075
F23: Minisink Town | G23: 23 | H23: 202.1 | I23: 70.8
F24: Unionville Village | G24: 0.3 | H24: 2206.5 | I24: 758.1
F25: Monroe Town | G25: 18.6 | H25: 1148.2 | I25: 398.7
F26: Harriman Village (portion) | G26: 0.5 | H26: 4352.1 | I26: 1829.2
F27: Monroe Village | G27: 3.5 | H27: 2712.3 | I27: 850.7
F28: Montgomery Town | G28: 50.3 | H28: 462.3 | I28: 178.5
F29: Maybrook Village | G29: 1.4 | H29: 2331.1 | I29: 1125.2
F30: Montgomery Village | G30: 1.4 | H30: 2695 | I30: 1134.8
F31: Walden Village | G31: 2 | H31: 3487.8 | I31: 1462.9 | K31: `
F32: Mount Hope Town | G32: 25.1 | H32: 258.7 | I32: 91.1
F33: Otisville Village | G33: 0.8 | H33: 1592.1 | I33: 615.8
F34: Newburgh City | G34: 3.8 | H34: 7519.4 | I34: 3050.9
F35: Newburgh Town | G35: 43.4 | H35: 734.9 | I35: 284.9
F36: New Windsor Town | G36: 34.1 | H36: 815.2 | I36: 332.6
F37: Palm Tree Town | G37: 1.5 | H37: 25049.3 | I37: 5056.9
F38: Kiryas Joel Village | G38: 1.5 | H38: 25049.3 | I38: 5056.9
F39: Port Jervis City | G39: 2.5 | H39: 3442.3 | I39: 1539.9
F40: Tuxedo Town | G40: 47.1 | H40: 80 | I40: 37.5
F41: Tuxedo Village | G41: 44.4 | H41: 69.5 | I41: 28.9
F42: Tuxedo Park Village | G42: 2.7 | H42: 256.4 | I42: 181.2
F43: Wallkill Town | G43: 61.9 | H43: 497.5 | I43: 198.5
... F51: Woodbury Village | G51: 35.6 | H51: 321.4 | I51: 110.6

Sheet Pop of Mun by Sex and Age
A1: Name | B1: Population of Municipalities by Sex and Age, 2023
A2: Table/Figure/Both | B2: Both
A3: Object ID | B3: =IF($B$1="","",_xlfn.XLOOKUP($B$1,Master!$F$2:$F$321,Master!$G$2:$G$321,"")) -> tbl-pop-sex-age
A4: Figure ID | B4: =IF($B$1="","",_xlfn.XLOOKUP($B$1,Master!$F$2:$F$321,Master!$H$2:$H$321,"")) -> fig-pop-sex-age | F4: text | G4: number | H4: number | I4: number | J4: number | K4: number | L4: number | M4: number | N4: number | O4: number | P4: number | Q4: number | R4: number
A5: Table Rules | E5: Enter Data | F5: Geographic Area | G5: Total Population | J5: Population >18 years | M5: Population Age 15-44 year | P5: Population 65+ years
A6: Multilevel Headers | B6: TRUE | G6: Total | H6: Male | I6: Female | J6: Total | K6: Male | L6: Female | M6: Total | N6: Male | O6: Female | P6: Total | Q6: Male | R6: Female
F7: Orange County | G7: 403840 | H7: 201512 | I7: 202328 | J7: 103740 | K7: 53161 | L7: 50579 | M7: 157903 | N7: 80408 | O7: 77495 | P7: 57945 | Q7: 26221 | R7: 31724
F8: Blooming Grove Town | G8: 18672 | H8: 9133 | I8: 9539 | J8: 5333 | K8: 2906 | L8: 2427 | M8: 7299 | N8: 3507 | O8: 3792 | P8: 2275 | Q8: 1093 | R8: 1182
A9: Figure Rules | F9: South Blooming Grove Village | G9: 3880 | H9: 1933 | I9: 1947 | J9: 1658 | K9: 774 | L9: 884 | M9: 1552 | N9: 738 | O9: 814 | P9: 337 | Q9: 188 | R9: 149
A10: Figure Type | F10: Washingtonville Village | G10: 5723 | H10: 2883 | I10: 2840 | J10: 1287 | K10: 740 | L10: 547 | M10: 2353 | N10: 1384 | O10: 969 | P10: 885 | Q10: 377 | R10: 508
A11: X Column | F11: Chester Town | G11: 12621 | H11: 5839 | I11: 6782 | J11: 2702 | K11: 1098 | L11: 1604 | M11: 5120 | N11: 2506 | O11: 2614 | P11: 1794 | Q11: 726 | R11: 1068
A12: Y Column | F12: Chester Village | G12: 4052 | H12: 1961 | I12: 2091 | J12: 738 | K12: 369 | L12: 369 | M12: 1797 | N12: 1018 | O12: 779 | P12: 550 | Q12: 221 | R12: 329
A13: X Axis Title | F13: Cornwall Town | G13: 12801 | H13: 6218 | I13: 6583 | J13: 2714 | K13: 1263 | L13: 1451 | M13: 4709 | N13: 2289 | O13: 2420 | P13: 2504 | Q13: 1207 | R13: 1297
A14: Y Axis Title | F14: Cornwall-on-Hudson Village | G14: 3046 | H14: 1460 | I14: 1586 | J14: 593 | K14: 228 | L14: 365 | M14: 1087 | N14: 484 | O14: 603 | P14: 552 | Q14: 233 | R14: 319
A15: Start at Zero | F15: Crawford Town | G15: 9097 | H15: 4732 | I15: 4365 | J15: 2086 | K15: 1380 | L15: 706 | M15: 3571 | N15: 1701 | O15: 1870 | P15: 1183 | Q15: 495 | R15: 688
A16: Pivot For Chart | F16: Deerpark Town | G16: 7471 | H16: 3753 | I16: 3718 | J16: 1512 | K16: 494 | L16: 1018 | M16: 2498 | N16: 1298 | O16: 1200 | P16: 1665 | Q16: 925 | R16: 740
F17: Goshen Town | G17: 14463 | H17: 7390 | I17: 7073 | J17: 2871 | K17: 1373 | L17: 1498 | M17: 4911 | N17: 2696 | O17: 2215 | P17: 3063 | Q17: 1307 | R17: 1756
A18: Source Specifications | F18: Goshen Village | G18: 5751 | H18: 2745 | I18: 3006 | J18: 1108 | K18: 594 | L18: 514 | M18: 1675 | N18: 812 | O18: 863 | P18: 1532 | Q18: 591 | R18: 941
A19: Source | B19: Source: US Census Bureau, American Community Survey 2019–2023 5-Year Population Estimates, Table S0101-Age and Sex, November 2025 https://data.census.gov/table?q=S0101+Orange+County,+NY&g=050XX00US36071 | F19: Greenville Town | G19: 4680 | H19: 2458 | I19: 2222 | J19: 1167 | K19: 659 | L19: 508 | M19: 1869 | N19: 1015 | O19: 854 | P19: 610 | Q19: 285 | R19: 325
F20: Hamptonburgh Town | G20: 5507 | H20: 2924 | I20: 2583 | J20: 1280 | K20: 818 | L20: 462 | M20: 1877 | N20: 1033 | O20: 844 | P20: 785 | Q20: 340 | R20: 445
A21: Note Specfications | F21: Highlands Town | G21: 12894 | H21: 7397 | I21: 5497 | J21: 3027 | K21: 1700 | L21: 1327 | M21: 6519 | N21: 3791 | O21: 2728 | P21: 1064 | Q21: 553 | R21: 511
A22: Note | B22: Note: Town totals include Village totals. | F22: Highland Falls Village | G22: 3696 | H22: 2000 | I22: 1696 | J22: 773 | K22: 439 | L22: 334 | M22: 1323 | N22: 694 | O22: 629 | P22: 447 | Q22: 176 | R22: 271
F23: Middletown City | G23: 30227 | H23: 15640 | I23: 14587 | J23: 7796 | K23: 4379 | L23: 3417 | M23: 12169 | N23: 6647 | O23: 5522 | P23: 4110 | Q23: 1855 | R23: 2255
F24: Minisink Town | G24: 4648 | H24: 2246 | I24: 2402 | J24: 1277 | K24: 496 | L24: 781 | M24: 1806 | N24: 841 | O24: 965 | P24: 524 | Q24: 332 | R24: 192
F25: Unionville Village | G25: 684 | H25: 282 | I25: 402 | J25: 222 | K25: 61 | L25: 161 | M25: 278 | N25: 114 | O25: 164 | P25: 79 | Q25: 38 | R25: 41
F26: Monroe Town | G26: 21299 | H26: 9782 | I26: 11517 | J26: 5787 | K26: 2800 | L26: 2987 | M26: 7992 | N26: 3423 | O26: 4569 | P26: 3039 | Q26: 1509 | R26: 1530
F27: Harriman Village (portion) | G27: 2089 | H27: 877 | I27: 1212 | J27: 598 | K27: 232 | L27: 366 | M27: 839 | N27: 399 | O27: 440 | P27: 363 | Q27: 117 | R27: 246
F28: Monroe Village | G28: 9466 | H28: 4473 | I28: 4993 | J28: 2552 | K28: 1325 | L28: 1227 | M28: 3867 | N28: 1767 | O28: 2100 | P28: 950 | Q28: 344 | R28: 606
F29: Montgomery Town | G29: 23235 | H29: 11058 | I29: 12177 | J29: 5597 | K29: 2566 | L29: 3031 | M29: 8825 | N29: 4262 | O29: 4563 | P29: 3358 | Q29: 1473 | R29: 1885
F30: Maybrook Village | G30: 3147 | H30: 1451 | I30: 1696 | J30: 507 | K30: 202 | L30: 305 | M30: 1094 | N30: 626 | O30: 468 | P30: 660 | Q30: 273 | R30: 387
F31: Montgomery Village | G31: 3800 | H31: 1722 | I31: 2078 | J31: 962 | K31: 434 | L31: 528 | M31: 1407 | N31: 679 | O31: 728 | P31: 553 | Q31: 186 | R31: 367
F32: Walden Village | G32: 6871 | H32: 3498 | I32: 3373 | J32: 1664 | K32: 868 | L32: 796 | M32: 2710 | N32: 1279 | O32: 1431 | P32: 816 | Q32: 337 | R32: 479
F33: Mount Hope Town | G33: 6500 | H33: 3897 | I33: 2603 | J33: 1080 | K33: 541 | L33: 539 | M33: 2476 | N33: 1540 | O33: 936 | P33: 1079 | Q33: 540 | R33: 539
F34: Otisville Village | G34: 1210 | H34: 623 | I34: 587 | J34: 353 | K34: 148 | L34: 205 | M34: 464 | N34: 267 | O34: 197 | P34: 237 | Q34: 102 | R34: 135
... F52: Woodbury Village | G52: 11437 | H52: 5868 | I52: 5569 | J52: 2930 | K52: 1721 | L52: 1209 | M52: 4484 | N52: 2456 | O52: 2028 | P52: 1287 | Q52: 620 | R52: 667

Sheet POP Mun Race-Eth
A1: Name | B1: Population of Municipalities by Race and Ethnicity, 2020
A2: Table/Figure/Both | B2: Both
A3: Object ID | B3: =IF($B$1="","",_xlfn.XLOOKUP($B$1,Master!$F$2:$F$321,Master!$G$2:$G$321,"")) -> tbl-pop-race-ethnicity
A4: Figure ID | B4: =IF($B$1="","",_xlfn.XLOOKUP($B$1,Master!$F$2:$F$321,Master!$H$2:$H$321,"")) -> fig-pop-race-ethnicity | F4: text | G4: number | H4: number | I4: number | J4: number | K4: number | L4: number | M4: number | N4: number | O4: number | P4: number
A5: Table Rules | E5: Enter Data | F5: Geographic Area | G5: Total Pop | H5: White Alone | I5: Black Alone | J5: American Indian/Alaska Native Alone | K5: Asian Alone | L5: Native Hawaiian/Pacific Islander Alone | M5: Some Other Race Alone | N5: Two or More Races | O5: Hispanic or Latino | P5: Not Hispanic or Latino
A6: Multilevel Headers | B6: FALSE | F6: Orange County | G6: 401310 | H6: 248085 | I6: 45543 | J6: 2949 | K6: 12025 | L6: 185 | M6: 52023 | N6: 40500 | O6: 89744 | P6: 311566
F7: Blooming Grove Town | G7: 18811 | H7: 12738 | I7: 1539 | J7: 121 | K7: 416 | L7: 7 | M7: 1784 | N7: 2206 | O7: 3913 | P7: 14898
F8: South Blooming Grove Village | G8: 3973 | H8: 2786 | I8: 311 | J8: 25 | K8: 52 | L8: 5 | M8: 484 | N8: 310 | O8: 555 | P8: 3418
A9: Figure Rules | F9: Washingtonville Village | G9: 5657 | H9: 3555 | I9: 630 | J9: 26 | K9: 131 | L9: 1 | M9: 590 | N9: 724 | O9: 1466 | P9: 4191
A10: Figure Type | F10: Chester Town | G10: 12646 | H10: 8574 | I10: 1188 | J10: 53 | K10: 513 | L10: 2 | M10: 984 | N10: 1332 | O10: 2446 | P10: 10200
A11: X Column | F11: Chester Village | G11: 3993 | H11: 2287 | I11: 611 | J11: 33 | K11: 212 | L11: 2 | M11: 417 | N11: 431 | O11: 912 | P11: 3081
A12: Y Column | F12: Cornwall Town | G12: 12884 | H12: 10225 | I12: 466 | J12: 37 | K12: 412 | L12: 5 | M12: 585 | N12: 1154 | O12: 1664 | P12: 11220
A13: X Axis Title | F13: Cornwall-on-Hudson Village | G13: 3075 | H13: 2598 | I13: 82 | J13: 9 | K13: 51 | L13: 3 | M13: 65 | N13: 267 | O13: 277 | P13: 2798
A14: Y Axis Title | F14: Crawford Town | G14: 9130 | H14: 7187 | I14: 390 | J14: 38 | K14: 152 | L14: 1 | M14: 439 | N14: 923 | O14: 1370 | P14: 7760
A15: Start at Zero | F15: Deerpark Town | G15: 7509 | H15: 6083 | I15: 240 | J15: 37 | K15: 334 | L15: 3 | M15: 188 | N15: 624 | O15: 657 | P15: 6852
A16: Pivot For Chart | F16: Goshen Town | G16: 14571 | H16: 10315 | I16: 1026 | J16: 68 | K16: 491 | L16: 3 | M16: 1196 | N16: 1472 | O16: 3133 | P16: 11438
F17: Goshen Village | G17: 5777 | H17: 4230 | I17: 303 | J17: 31 | K17: 185 | L17: 2 | M17: 509 | N17: 517 | O17: 1205 | P17: 4572
A18: Source Specifications | F18: Greenville Town | G18: 4689 | H18: 3828 | I18: 164 | J18: 17 | K18: 55 | L18: 0 | M18: 229 | N18: 396 | O18: 626 | P18: 4063
A19: Source | B19: Source: US Census Bureau, 2020 Decennial Redistricting Data (PL 94-171), Table P1-Total Population, November 2025 https://data.census.gov/table/DECENNIALPL2020.P1?q=PL+94-171&g=050XX00US36071 | F19: Hamptonburgh Town | G19: 5489 | H19: 4274 | I19: 189 | J19: 20 | K19: 204 | L19: 0 | M19: 227 | N19: 575 | O19: 797 | P19: 4692
F20: Highlands Town | G20: 12939 | H20: 8655 | I20: 1435 | J20: 137 | K20: 613 | L20: 31 | M20: 893 | N20: 1175 | O20: 2066 | P20: 10873
A21: Note Specfications | F21: Highland Falls Village | G21: 3684 | H21: 2100 | I21: 561 | J21: 54 | K21: 110 | L21: 3 | M21: 441 | N21: 415 | O21: 947 | P21: 2737
A22: Note | B22: Note: Town totals include Village totals | F22: Middletown City | G22: 30345 | H22: 9983 | I22: 7116 | J22: 424 | K22: 1165 | L22: 14 | M22: 7284 | N22: 4359 | O22: 13243 | P22: 17102
F23: Minisink Town | G23: 4621 | H23: 3829 | I23: 177 | J23: 8 | K23: 49 | L23: 0 | M23: 188 | N23: 370 | O23: 618 | P23: 4003
F24: Unionville Village | G24: 592 | H24: 505 | I24: 27 | J24: 0 | K24: 4 | L24: 0 | M24: 23 | N24: 33 | O24: 53 | P24: 539
F25: Monroe Town | G25: 21387 | H25: 13246 | I25: 1685 | J25: 137 | K25: 1221 | L25: 6 | M25: 2833 | N25: 2259 | O25: 5342 | P25: 16045
F26: Harriman Village (total)* | G26: 2714 | H26: 1247 | I26: 495 | J26: 9 | K26: 258 | L26: 5 | M26: 364 | N26: 336 | O26: 783 | P26: 1931
F27: Monroe Village | G27: 9343 | H27: 5528 | I27: 699 | J27: 64 | K27: 530 | L27: 0 | M27: 1544 | N27: 978 | O27: 2790 | P27: 6553
F28: Montgomery Town | G28: 23322 | H28: 16894 | I28: 1842 | J28: 117 | K28: 414 | L28: 6 | M28: 1562 | N28: 2487 | O28: 4320 | P28: 19002
F29: Maybrook Village | G29: 3150 | H29: 1930 | I29: 461 | J29: 11 | K29: 43 | L29: 0 | M29: 286 | N29: 419 | O29: 803 | P29: 2347
F30: Montgomery Village | G30: 3834 | H30: 2896 | I30: 275 | J30: 9 | K30: 61 | L30: 0 | M30: 181 | N30: 412 | O30: 620 | P30: 3214
F31: Walden Village | G31: 6818 | H31: 4533 | I31: 680 | J31: 55 | K31: 130 | L31: 5 | M31: 588 | N31: 827 | O31: 1596 | P31: 5222
F32: Mount Hope Town | G32: 6537 | H32: 4474 | I32: 824 | J32: 28 | K32: 312 | L32: 0 | M32: 387 | N32: 512 | O32: 1143 | P32: 5394
F33: Otisville Village | G33: 969 | H33: 719 | I33: 52 | J33: 3 | K33: 72 | L33: 0 | M33: 34 | N33: 89 | O33: 159 | P33: 810
F34: Newburgh City | G34: 28856 | H34: 6554 | I34: 8167 | J34: 656 | K34: 260 | L34: 24 | M34: 9737 | N34: 3458 | O34: 15085 | P34: 13771
... F49: Woodbury Village | G49: 11526 | H49: 7226 | I49: 942 | J49: 92 | K49: 720 | L49: 15 | M49: 1389 | N49: 1142 | O49: 2458 | P49: 9068

Sheet Employed Civilians by Industry
A1: Name | B1: Employed Civilians by Industry and Municipality, 2023
A2: Table/Figure/Both | B2: Both
A3: Object ID | B3: =IF($B$1="","",_xlfn.XLOOKUP($B$1,Master!$F$2:$F$321,Master!$G$2:$G$321,"")) -> tbl-employed-civilians-industry
A4: Figure ID | B4: =IF($B$1="","",_xlfn.XLOOKUP($B$1,Master!$F$2:$F$321,Master!$H$2:$H$321,"")) -> fig-employed-civilians-industry | F4: text | G4: number | H4: number | I4: number | J4: number | K4: number | L4: number | M4: number | N4: number | O4: number | P4: number | Q4: number | R4: number | S4: number | T4: number
A5: Table Rules | E5: Enter Data | F5: Geographic Area | G5: Civilian Employed Population Age 16+ | H5: Industry
A6: Multilevel Headers | B6: TRUE | H6: Agriculture, Forestry, Fishing, Hunting, Mining | I6: Construction | J6: Manufacturing | K6: Wholesale Trade | L6: Retail Trade | M6: Transportation, Warehousing, Utilities | N6: Information | O6: Finance, Insurance, Real Estate, Rental/Leasing | P6: Professional, Scientific, Management, Administrative, Waste Management | Q6: Educational Services, Health Care, Social Assistance | R6: Arts, Entertainment, Recreation, Accommodation, Food Services | S6: Public Administration | T6: Other Services
F7: Orange County | G7: 184167 | H7: 1278 | I7: 13492 | J7: 11754 | K7: 5470 | L7: 23207 | M7: 12393 | N7: 4268 | O7: 10817 | P7: 18700 | Q7: 50693 | R7: 12127 | S7: 10996 | T7: 8972
F8: Blooming Grove Town | G8: 8167 | H8: 85 | I8: 766 | J8: 369 | K8: 263 | L8: 891 | M8: 375 | N8: 255 | O8: 633 | P8: 692 | Q8: 2359 | R8: 628 | S8: 495 | T8: 356
A9: Figure Rules | F9: South Blooming Grove Village | G9: 1268 | H9: 0 | I9: 103 | J9: 102 | K9: 49 | L9: 169 | M9: 55 | N9: 29 | O9: 99 | P9: 71 | Q9: 355 | R9: 132 | S9: 5 | T9: 99
A10: Figure Type | F10: Washingtonville Village | G10: 2827 | H10: 0 | I10: 120 | J10: 103 | K10: 187 | L10: 251 | M10: 89 | N10: 155 | O10: 288 | P10: 203 | Q10: 800 | R10: 169 | S10: 298 | T10: 164
A11: X Column | F11: Chester Town | G11: 6888 | H11: 25 | I11: 346 | J11: 488 | K11: 283 | L11: 1099 | M11: 648 | N11: 244 | O11: 416 | P11: 790 | Q11: 1327 | R11: 533 | S11: 447 | T11: 242
A12: Y Column | F12: Chester Village | G12: 2488 | H12: 0 | I12: 89 | J12: 111 | K12: 96 | L12: 633 | M12: 263 | N12: 77 | O12: 175 | P12: 108 | Q12: 423 | R12: 260 | S12: 141 | T12: 112
A13: X Axis Title | F13: Cornwall Town | G13: 6425 | H13: 12 | I13: 357 | J13: 452 | K13: 155 | L13: 593 | M13: 207 | N13: 171 | O13: 406 | P13: 799 | Q13: 2023 | R13: 342 | S13: 725 | T13: 183
A14: Y Axis Title | F14: Cornwall-on-Hudson Village | G14: 1656 | H14: 0 | I14: 63 | J14: 156 | K14: 10 | L14: 189 | M14: 87 | N14: 30 | O14: 120 | P14: 148 | Q14: 534 | R14: 74 | S14: 202 | T14: 43
A15: Start at Zero | F15: Crawford Town | G15: 5000 | H15: 58 | I15: 426 | J15: 162 | K15: 180 | L15: 580 | M15: 230 | N15: 149 | O15: 293 | P15: 516 | Q15: 1632 | R15: 255 | S15: 315 | T15: 204
A16: Pivot For Chart | F16: Deerpark Town | G16: 3207 | H16: 76 | I16: 232 | J16: 250 | K16: 52 | L16: 463 | M16: 239 | N16: 74 | O16: 30 | P16: 309 | Q16: 810 | R16: 163 | S16: 192 | T16: 317
F17: Goshen Town | G17: 6373 | H17: 52 | I17: 372 | J17: 590 | K17: 214 | L17: 863 | M17: 270 | N17: 80 | O17: 328 | P17: 744 | Q17: 1875 | R17: 318 | S17: 439 | T17: 228
A18: Source Specifications | F18: Goshen Village | G18: 2703 | H18: 0 | I18: 175 | J18: 103 | K18: 61 | L18: 349 | M18: 127 | N18: 29 | O18: 178 | P18: 335 | Q18: 796 | R18: 232 | S18: 238 | T18: 80
A19: Source | B19: Source: US Census Bureau, American Community Survey 2019–2023 5-Year Population Estimates, S2403-Industry by Sex for the Civilian Employed Population 16 Years and Over, November 2025 https://data.census.gov/table/ACSST5Y2023.S2403?q=S2403+Orange+County,+NY&g=060XX00US3607134550,3607156185,3607148857,3607182755,3607147042,3607148153,3607178839,3607130631,3607 118300,3607175781,3607150045,3607147713,3607147999,3607150848,3607129553,3607107003,3607115308,3607131907,3607118916,3607178366,3607177992,3607119961,3607150034,3607159388_ 160XX00US3646162,3629542,3630752,3655673,3678355,3676210,3634495,3615297,3675803,3682750,3677849,3632325,3647988,3678465,3639853,3618333,3668610,3648142_050XX00US36071 | F19: Greenville Town | G19: 2563 | H19: 55 | I19: 206 | J19: 113 | K19: 36 | L19: 262 | M19: 250 | N19: 63 | O19: 115 | P19: 155 | Q19: 774 | R19: 49 | S19: 304 | T19: 181
F20: Hamptonburgh Town | G20: 2495 | H20: 9 | I20: 368 | J20: 74 | K20: 112 | L20: 249 | M20: 110 | N20: 55 | O20: 113 | P20: 355 | Q20: 598 | R20: 161 | S20: 52 | T20: 239
A21: Note Specfications | F21: Highlands Town | G21: 4373 | H21: 7 | I21: 234 | J21: 202 | K21: 14 | L21: 257 | M21: 568 | N21: 82 | O21: 61 | P21: 632 | Q21: 1291 | R21: 423 | S21: 420 | T21: 182
A22: Note | B22: Note: Town totals include Village totals. Industry titles and their 4-digit codes are based on the North American Industry Classification System (NAICS). The Census industry codes for 2023 and later years are based on the 2022 revision of the NAICS. To allow for the creation of multiyear tables, industry data in the multiyear files (prior to data year 2023) were recoded to the 2022 Census industry codes. We recommend using caution when comparing data coded using 2022 Census industry codes with data coded using Census industry codes prior to data year 2023. | F22: Highland Falls Village | G22: 1770 | H22: 0 | I22: 109 | J22: 85 | K22: 14 | L22: 100 | M22: 135 | N22: 7 | O22: 15 | P22: 312 | Q22: 539 | R22: 207 | S22: 183 | T22: 64
F23: Middletown City | G23: 13664 | H23: 139 | I23: 1041 | J23: 834 | K23: 214 | L23: 1951 | M23: 1113 | N23: 308 | O23: 679 | P23: 1311 | Q23: 3597 | R23: 1028 | S23: 601 | T23: 848
F24: Minisink Town | G24: 2456 | H24: 26 | I24: 101 | J24: 79 | K24: 71 | L24: 189 | M24: 270 | N24: 41 | O24: 134 | P24: 305 | Q24: 837 | R24: 127 | S24: 132 | T24: 144
F25: Unionville Village | G25: 368 | H25: 0 | I25: 19 | J25: 0 | K25: 0 | L25: 43 | M25: 83 | N25: 0 | O25: 35 | P25: 76 | Q25: 80 | R25: 5 | S25: 0 | T25: 27
F26: Monroe Town | G26: 10354 | H26: 7 | I26: 615 | J26: 554 | K26: 200 | L26: 1305 | M26: 544 | N26: 375 | O26: 715 | P26: 1187 | Q26: 2809 | R26: 643 | S26: 714 | T26: 686
F27: Harriman Village (portion) | G27: 1052 | H27: 0 | I27: 82 | J27: 71 | K27: 8 | L27: 140 | M27: 38 | N27: 9 | O27: 18 | P27: 27 | Q27: 333 | R27: 73 | S27: 40 | T27: 113
F28: Monroe Village | G28: 4852 | H28: 7 | I28: 299 | J28: 294 | K28: 45 | L28: 606 | M28: 276 | N28: 75 | O28: 317 | P28: 526 | Q28: 1482 | R28: 440 | S28: 310 | T28: 175
F29: Montgomery Town | G29: 11292 | H29: 127 | I29: 922 | J29: 819 | K29: 262 | L29: 1205 | M29: 1071 | N29: 214 | O29: 579 | P29: 859 | Q29: 2911 | R29: 865 | S29: 933 | T29: 525
F30: Maybrook Village | G30: 1807 | H30: 0 | I30: 88 | J30: 126 | K30: 32 | L30: 193 | M30: 367 | N30: 13 | O30: 119 | P30: 70 | Q30: 359 | R30: 187 | S30: 168 | T30: 85
F31: Montgomery Village | G31: 1871 | H31: 0 | I31: 155 | J31: 130 | K31: 76 | L31: 190 | M31: 101 | N31: 29 | O31: 110 | P31: 146 | Q31: 462 | R31: 180 | S31: 263 | T31: 29
F32: Walden Village | G32: 3220 | H32: 15 | I32: 208 | J32: 202 | K32: 84 | L32: 228 | M32: 422 | N32: 73 | O32: 152 | P32: 365 | Q32: 1031 | R32: 216 | S32: 99 | T32: 125
F33: Mount Hope Town | G33: 2690 | H33: 3 | I33: 292 | J33: 123 | K33: 63 | L33: 350 | M33: 212 | N33: 35 | O33: 88 | P33: 235 | Q33: 823 | R33: 178 | S33: 162 | T33: 126
F34: Otisville Village | G34: 500 | H34: 0 | I34: 97 | J34: 25 | K34: 6 | L34: 35 | M34: 45 | N34: 0 | O34: 17 | P34: 36 | Q34: 142 | R34: 52 | S34: 27 | T34: 18
... F52: Woodbury Village | G52: 5288 | H52: 0 | I52: 393 | J52: 170 | K52: 98 | L52: 627 | M52: 444 | N52: 182 | O52: 349 | P52: 829 | Q52: 1464 | R52: 289 | S52: 269 | T52: 174

Sheet Employed Civilian Occupations b
A1: Name | B1: Employed Civilian Occupations by Municipality, 2023
A2: Table/Figure/Both | B2: Both
A3: Object ID | B3: =IF($B$1="","",_xlfn.XLOOKUP($B$1,Master!$F$2:$F$321,Master!$G$2:$G$321,"")) -> tbl-employed-civilian-occupations
A4: Figure ID | B4: =IF($B$1="","",_xlfn.XLOOKUP($B$1,Master!$F$2:$F$321,Master!$H$2:$H$321,"")) -> fig-employed-civilian-occupations | F4: text | G4: number | H4: number | I4: number | J4: number | K4: number | L4: number
A5: Table Rules | E5: Enter Data | F5: Geographic Area | G5: Civilian Employed Population Age 16+ | H5: Occupations
A6: Multilevel Headers | B6: TRUE | H6: Management, Business, Science and Arts | I6: Service | J6: Sales and Office | K6: Natural Resources, Construction, Maintenance | L6: Production, Transportation, Material Moving
F7: Orange County | G7: 184167 | H7: 74036 | I7: 32806 | J7: 40121 | K7: 16708 | L7: 20496
F8: Blooming Grove Town | G8: 8167 | H8: 3370 | I8: 1503 | J8: 1872 | K8: 950 | L8: 472
A9: Figure Rules | F9: South Blooming Grove Village | G9: 1268 | H9: 550 | I9: 194 | J9: 339 | K9: 118 | L9: 67
A10: Figure Type | F10: Washingtonville Village | G10: 2827 | H10: 1117 | I10: 695 | J10: 695 | K10: 195 | L10: 125
A11: X Column | F11: Chester Town | G11: 6888 | H11: 3206 | I11: 741 | J11: 1792 | K11: 447 | L11: 702
A12: Y Column | F12: Chester Village | G12: 2488 | H12: 927 | I12: 295 | J12: 824 | K12: 125 | L12: 317
A13: X Axis Title | F13: Cornwall Town | G13: 6425 | H13: 3459 | I13: 930 | J13: 1116 | K13: 522 | L13: 398
A14: Y Axis Title | F14: Cornwall-on-Hudson Village | G14: 1656 | H14: 885 | I14: 259 | J14: 276 | K14: 83 | L14: 153
A15: Start at Zero | F15: Crawford Town | G15: 5000 | H15: 2041 | I15: 842 | J15: 1090 | K15: 588 | L15: 439
A16: Pivot For Chart | F16: Deerpark Town | G16: 3207 | H16: 915 | I16: 505 | J16: 1094 | K16: 267 | L16: 426
F17: Goshen Town | G17: 6373 | H17: 3107 | I17: 948 | J17: 1322 | K17: 558 | L17: 438
A18: Source Specifications | F18: Goshen Village | G18: 2703 | H18: 1151 | I18: 600 | J18: 486 | K18: 199 | L18: 267
A19: Source | B19: Source: US Census Bureau, American Community Survey 2019–2023 5-Year Population Estimates, S2401-Occupation by Sex for the Civilian Employed Population 16 Years and Over, November 2025 https://data.census.gov/table/ACSST5Y2023.S2401?q=S2401+Orange+County,+NY&g=060XX00US3607134550,3607156185,3 607148857,3607182755,3607147042,3607148153,3607178839,3607130631,3607118300,3607175781,3607150045,3607 147713,3607147999,3607150848,3607129553,3607107003,3607115308,3607131907,3607118916,3607178366,3607177 992,3607119961,3607150034,3607159388_160XX00US3646162,3629542,3630752,3655673,3678355,3676210,3634495,3 615297,3675803,3682750,3677849,3632325,3647988,3678465,3639853,3618333,3668610,3648142_050XX00US36071 | F19: Greenville Town | G19: 2563 | H19: 1131 | I19: 450 | J19: 410 | K19: 182 | L19: 390
F20: Hamptonburgh Town | G20: 2495 | H20: 998 | I20: 421 | J20: 408 | K20: 450 | L20: 218
A21: Note Specfications | F21: Highlands Town | G21: 4373 | H21: 1906 | I21: 661 | J21: 934 | K21: 325 | L21: 547
A22: Note | B22: Note: Town totals include Village totals. Occupation titles and their 4-digit codes are based on the 2018 Standard Occupational Classification. | F22: Highland Falls Village | G22: 1770 | H22: 809 | I22: 321 | J22: 245 | K22: 146 | L22: 249
F23: Middletown City | G23: 13664 | H23: 4662 | I23: 2868 | J23: 3059 | K23: 1397 | L23: 1678
F24: Minisink Town | G24: 2456 | H24: 1153 | I24: 384 | J24: 617 | K24: 110 | L24: 192
F25: Unionville Village | G25: 368 | H25: 180 | I25: 15 | J25: 84 | K25: 38 | L25: 51
F26: Monroe Town | G26: 10354 | H26: 4355 | I26: 2184 | J26: 1856 | K26: 932 | L26: 1027
F27: Harriman Village (partial) | G27: 1052 | H27: 517 | I27: 198 | J27: 154 | K27: 103 | L27: 80
F28: Monroe Village | G28: 4852 | H28: 1998 | I28: 1004 | J28: 862 | K28: 421 | L28: 567
F29: Montgomery Town | G29: 11292 | H29: 4115 | I29: 1900 | J29: 2529 | K29: 1318 | L29: 1430
F30: Maybrook Village | G30: 1807 | H30: 474 | I30: 342 | J30: 527 | K30: 144 | L30: 320
F31: Montgomery Village | G31: 1871 | H31: 759 | I31: 309 | J31: 423 | K31: 163 | L31: 217
F32: Walden Village | G32: 3220 | H32: 1261 | I32: 513 | J32: 676 | K32: 460 | L32: 310
F33: Mount Hope Town | G33: 2690 | H33: 1109 | I33: 454 | J33: 467 | K33: 264 | L33: 396
F34: Otisville Village | G34: 500 | H34: 183 | I34: 69 | J34: 78 | K34: 114 | L34: 56
... F52: Woodbury Village | G52: 5288 | H52: 2851 | I52: 692 | J52: 748 | K52: 393 | L52: 604

Sheet All-Cause Mortality, Rate Zip
A1: Name | B1: All-Cause Mortality, Rate per 100,000 Population by Age, ZIP Code, Race and Ethnicity, 2020–2023
A2: Table/Figure/Both | B2: Both
A3: Object ID | B3: =IF($B$1="","",_xlfn.XLOOKUP($B$1,Master!$F$2:$F$321,Master!$G$2:$G$321,"")) -> tbl-all-cause-mortal-rate-age-zip-code-rande
A4: Figure ID | B4: =IF($B$1="","",_xlfn.XLOOKUP($B$1,Master!$F$2:$F$321,Master!$H$2:$H$321,"")) -> fig-all-cause-mortal-rate-age-zip-code-rande | F4: text | G4: number | H4: percent1 | I4: number | J4: percent1 | K4: number | L4: percent1 | M4: number | N4: percent1 | O4: number | P4: percent1
A5: Table Rules | E5: Enter Data | G5: 2020 | I5: 2021 | K5: 2022 | M5: 2023 | O5: Total 2020-2023
A6: Multilevel Headers | B6: TRUE | G6: # | H6: Rate | I6: # | J6: Rate | K6: # | L6: Rate | M6: # | N6: Rate | O6: Total # | P6: Average Rate
F7: Total | G7: 3392 | H7: 887.8 | I7: 3020 | J7: 758.3 | K7: 3077 | L7: 766.9 | M7: 2860 | N7: 708.2 | O7: 12349 | P7: 780.3
F8: Age Intervals
A9: Figure Rules | F9: <1 | G9: 16 | H9: 332.8 | I9: 18 | J9: 351.2 | K9: 15 | L9: 302.1 | M9: 17 | N9: 323.6 | O9: 66 | P9: 327.4
A10: Figure Type | F10: 1–9 | G10: 9 | H10: 19.2 | I10: 8 | J10: 16.3 | K10: 7 | L10: 14.5 | M10: 13 | N10: 26.2 | O10: 37 | P10: 19.1
A11: X Column | F11: 10–19 | G11: 13 | H11: 22.7 | I11: 8 | J11: 13.3 | K11: 9 | L11: 14.5 | M11: 6 | N11: 9.7 | O11: 36 | P11: 15.1
A12: Y Column | F12: 20–24 | G12: 28 | H12: 98.2 | I12: 21 | J12: 72 | K12: 26 | L12: 87.7 | M12: 11 | N12: 38.4 | O12: 86 | P12: 74.1
A13: X Axis Title | F13: 25–34 | G13: 73 | H13: 162.6 | I13: 57 | J13: 122.3 | K13: 56 | L13: 118.2 | M13: 48 | N13: 100.2 | O13: 234 | P13: 125.8
A14: Y Axis Title | F14: 35–44 | G14: 98 | H14: 216.7 | I14: 101 | J14: 211.6 | K14: 87 | L14: 178.6 | M14: 87 | N14: 174.9 | O14: 373 | P14: 195.5
A15: Start at Zero | F15: 45–54 | G15: 174 | H15: 332.3 | I15: 192 | J15: 359.8 | K15: 159 | L15: 303.7 | M15: 150 | N15: 291.2 | O15: 675 | P15: 321.7
A16: Pivot For Chart | F16: 55–64 | G16: 395 | H16: 811.1 | I16: 392 | J16: 762.7 | K16: 392 | L16: 765.9 | M16: 344 | N16: 667.8 | O16: 1523 | P16: 751.9
F17: 65–74 | G17: 663 | H17: 2102.6 | I17: 599 | J17: 1789.7 | K17: 620 | L17: 1831.6 | M17: 546 | N17: 1567.2 | O17: 2428 | P17: 1822.7
A18: Source Specifications | F18: 75–84 | G18: 788 | H18: 5344.2 | I18: 728 | J18: 4770.6 | K18: 790 | L18: 4986.1 | M18: 752 | N18: 4586.2 | O18: 3058 | P18: 4921.8
A19: Source | B19: Source: Special request from NYSDOH Bureau of Vital Records, July 2025 | F19: 85+ | G19: 1135 | H19: 15876.3 | I19: 896 | J19: 13151.3 | K19: 916 | L19: 13048.4 | M19: 886 | N19: 13206.1 | O19: 3833 | P19: 13820.6
F20: Race and Ethnicity
A21: Note Specfications | F21: Non-Hispanic White | G21: 2626 | H21: 1088.8 | I21: 2347 | J21: 946.8 | K21: 2393 | L21: 986.2 | M21: 2255 | N21: 2249 | O21: 9621 | P21: 1317.7
A22: Note | B22: Note: See Data Note section for more information regarding this request. Birth and death data for Orange County excludes events recorded in NYC. All rates use ACS 5-year population estimates, except for the ages under 1 year and 1-9 years, which are based on crude live births in Orange County. | F22: Non-Hispanic Black | G22: 310 | H22: 806.2 | I22: 277 | J22: 697.2 | K22: 290 | L22: 691.4 | M22: 265 | N22: 259 | O22: 1142 | P22: 613.4
F23: Hispanic | G23: 376 | H23: 468.5 | I23: 310 | J23: 363.2 | K23: 305 | L23: 340.8 | M23: 267 | N23: 267 | O23: 1258 | P23: 359.9
F24: Other | G24: 80 | H24: 360.6 | I24: 86 | J24: 339.7 | K24: 89 | L24: 327.7 | M24: 73 | N24: 85 | O24: 328 | P24: 278.3
F25: ZIP Code
F26: 10940 | G26: 512 | H26: 1035.8 | I26: 496 | J26: 973.8 | K26: 480 | L26: 925.7 | M26: 430 | N26: 809.8 | O26: 1918 | P26: 936.3
F27: 10950 | G27: 226 | H27: 1688.6 | I27: 167 | J27: 1158.5 | K27: 194 | L27: 1337.7 | M27: 163 | N27: 1104.3 | O27: 750 | P27: 1322.3
F28: 12550 | G28: 561 | H28: 2103.9 | I28: 459 | J28: 1712.3 | K28: 468 | L28: 1707.5 | M28: 406 | N28: 1487.2 | O28: 1894 | P28: 1752.7
F29: 12771 | G29: 139 | H29: 964.7 | I29: 169 | J29: 1138.8 | K29: 166 | L29: 1148.5 | M29: 157 | N29: 1094.5 | O29: 631 | P29: 1086

Sheet All-Cause Mort AAR RE
A1: Name | B1: All-Cause Mortality, Age-Adjusted Rate per 100,000 Population by Race and Ethnicity, 2020–2022
A2: Table/Figure/Both | B2: Both
A3: Object ID | B3: =IF($B$1="","",_xlfn.XLOOKUP($B$1,Master!$F$2:$F$321,Master!$G$2:$G$321,"")) -> tbl-all-cause-mortal-aar-rande
A4: Figure ID | B4: =IF($B$1="","",_xlfn.XLOOKUP($B$1,Master!$F$2:$F$321,Master!$H$2:$H$321,"")) -> fig-all-cause-mortal-aar-rande | F4: text | G4: percent1 | H4: percent1 | I4: percent1 | J4: percent1 | K4: percent1
A5: Table Rules | E5: Enter Data | F5: Region | G5: Total | H5: Non-Hispanic White | I5: Non-Hispanic Black | J5: Non-Hispanic Asian/Pacific Islander | K5: Hispanic
A6: Multilevel Headers | B6: FALSE | F6: Orange | G6: 781 | H6: 790.7 | I6: 820.7 | J6: 487.8 | K6: 654.7
F7: NYS excl NYC | G7: 773 | H7: 772.2 | I7: 945 | J7: 413.7 | K7: 594.1
F8: NYS | G8: 735 | H8: 728.3 | I8: 871.2 | J8: 436.7 | K8: 649.3
A9: Figure Rules
A10: Figure Type | B10: Clustered Bar
A11: X Column | B11: Region/County
A12: Y Column
A13: X Axis Title | B13: Region/County
A14: Y Axis Title | B14: Rate per 100,000
A15: Start at Zero | B15: TRUE
A16: Pivot For Chart | B16: TRUE
A18: Source Specifications
A19: Source | B19: Source: NYS County Health Indicators by Race and Ethnicity, August 2025 sourced from Vital Statistics of NYS https://www.health.ny.gov/community/health_equity/reports/county/
A21: Note Specfications
A22: Note | B22: Note: The 2018 population estimates are also used to calculate rates for 2019, 2020, and 2021.
K31: `

Sheet All-Cause Mort Rate Zip
A1: Name | B1: All-Cause Mortality, Rate per 100,000 Population by ZIP Code, 2020–2023
A2: Table/Figure/Both | B2: Both
A3: Object ID | B3: =IF($B$1="","",_xlfn.XLOOKUP($B$1,Master!$F$2:$F$321,Master!$G$2:$G$321,"")) -> tbl-all-cause-mortal-rate-ZIP
A4: Figure ID | B4: =IF($B$1="","",_xlfn.XLOOKUP($B$1,Master!$F$2:$F$321,Master!$H$2:$H$321,"")) -> fig-all-cause-mortal-rate-ZIP | F4: text | G4: percent1 | H4: percent1 | I4: percent1 | J4: percent1
A5: Table Rules | E5: Enter Data | F5: Year | G5: 10940 | H5: 10950 | I5: 12550 | J5: 12771
A6: Multilevel Headers | B6: FALSE | F6: 2020 | G6: 1035.8 | H6: 1688.6 | I6: 2103.9 | J6: 964.7
F7: 2021 | G7: 973.8 | H7: 1158.5 | I7: 1712.3 | J7: 1138.8
F8: 2022 | G8: 925.7 | H8: 1337.7 | I8: 1707.5 | J8: 1148.5
A9: Figure Rules | F9: 2023 | G9: 809.8 | H9: 1104.3 | I9: 1487.2 | J9: 1094.5
A10: Figure Type | B10: Line
A11: X Column | B11: Year
A12: Y Column
A13: X Axis Title | B13: Year
A14: Y Axis Title | B14: Rate per 100,000
A15: Start at Zero | B15: TRUE
A16: Pivot For Chart | B16: TRUE
A18: Source Specifications
A19: Source | B19: Source: Special request from NYSDOH Bureau of Vital Records, July 2025
A21: Note Specfications
A22: Note | B22: Note: See Data Note section for more information regarding this request. Birth and death data for Orange County excludes events recorded in NYC. All rates use ACS 5-year population estimates, except for the ages under 1 year and 1-9 years, which are based on crude live births in Orange County.

Sheet All-Cause Mort Rate Sex
A1: Name | B1: All-Cause Mortality, Age-Adjusted Rate per 100,000 Population by Sex, 2020–2023
A2: Table/Figure/Both | B2: Both
A3: Object ID | B3: =IF($B$1="","",_xlfn.XLOOKUP($B$1,Master!$F$2:$F$321,Master!$G$2:$G$321,"")) -> tbl-all-cause-mortal-aar-sex
A4: Figure ID | B4: =IF($B$1="","",_xlfn.XLOOKUP($B$1,Master!$F$2:$F$321,Master!$H$2:$H$321,"")) -> fig-all-cause-mortal-aar-sex | F4: integer | G4: percent1 | H4: percent1 | I4: percent1 | J4: percent1
A5: Table Rules | E5: Enter Data | F5: Sex | G5: 2020 | H5: 2021 | I5: 2022 | J5: 2023
A6: Multilevel Headers | B6: FALSE | F6: Males | G6: 982.2 | H6: 842.9 | I6: 827.9 | J6: 767.5
F7: Females | G7: 680.7 | H7: 609.2 | I7: 616.3 | J7: 582.8
A9: Figure Rules
A10: Figure Type | B10: Line
A11: X Column | B11: Sex
A12: Y Column
A13: X Axis Title | B13: Sex
A14: Y Axis Title | B14: Rate per 100,000
A15: Start at Zero | B15: TRUE
A16: Pivot For Chart | B16: TRUE
A18: Source Specifications
A19: Source | B19: Source: Vital Statistics of NYS, July 2025
A21: Note Specfications
A22: Note | B22: Note: See Data Note section for more information regarding this request. Birth and death data for Orange County excludes events recorded in NYC. All rates use ACS 5-year population estimates, except for the ages under 1 year and 1-9 years, which are based on crude live births in Orange County.

Sheet Top 5 Leading Death AAR
A1: Name | B1: Top Five Leading Causes of Death, by Count and Age-Adjusted Rate per 100,000 Population, 2022
A2: Table/Figure/Both | B2: Both
A3: Object ID | B3: =IF($B$1="","",_xlfn.XLOOKUP($B$1,Master!$F$2:$F$321,Master!$G$2:$G$321,"")) -> tbl-top-five-leading-death-count-aar
A4: Figure ID | B4: =IF($B$1="","",_xlfn.XLOOKUP($B$1,Master!$F$2:$F$321,Master!$H$2:$H$321,"")) -> fig-top-five-leading-death-count-aar | F4: integer | G4: percent1 | H4: percent1 | J4: percent1 | L4: percent1 | N4: percent1 | P4: percent1
A5: Table Rules | E5: Enter Data | F5: All Deaths | H5: #1 Cause of Death | J5: #2 Cause of Death | L5: #3 Cause of Death | N5: #4 Cause of Death | P5: #5 Cause of Death
A6: Multilevel Headers | B6: TRUE | F6: Orange County | H6: Heart Disease | J6: Cancer | L6: Unintentional Injury | N6: COVID-19 | P6: CLRD
F7: Count | G7: 3222 | H7: 653 | J7: 609 | L7: 253 | N7: 231 | P7: 125
F8: Rate | G8: 745.2 | H8: 150.6 | J8: 132.4 | L8: 62.2 | N8: 53.4 | P8: 29.6
A9: Figure Rules | F9: NYS Excl NYC | H9: Heart Disease | J9: Cancer | L9: COVID-19 | N9: Unintentional Injury | P9: CLRD
A10: Figure Type | F10: Count | G10: 113465 | H10: 26215 | J10: 21762 | L10: 6666 | N10: 6666 | P10: 4602
A11: X Column | F11: Rate | G11: 744 | H11: 166.4 | J11: 137.3 | L11: 54.8 | N11: 42.3 | P11: 28.8
A12: Y Column | F12: NYS | H12: Heart Disease | J12: Cancer | L12: COVID-19 | N12: Unintentional Injury | P12: Cerebrovascular Disease
A13: X Axis Title | F13: Count | G13: 173986 | H13: 43166 | J13: 32584 | L13: 11174 | N13: 10820 | P13: 6574
A14: Y Axis Title | F14: Rate | G14: 679.6 | H14: 163.7 | J14: 123.7 | L14: 42.7 | N14: 50.6 | P14: 25.1
A15: Start at Zero
A16: Pivot For Chart
A18: Source Specifications
A19: Source | B19: Source: Vital Statistics of NYS, November 2025 https://apps.health.ny.gov/public/tabvis/PHIG_Public/lcd
A21: Note Specfications
A22: Note | B22: Note: Premature death includes deaths occurring before the age of 75.

Sheet Number fo Deaths by Sex
A1: Name | B1: Number of Deaths from Leading Causes by Sex, 2020–2022
A2: Table/Figure/Both | B2: Both
A3: Object ID | B3: =IF($B$1="","",_xlfn.XLOOKUP($B$1,Master!$F$2:$F$321,Master!$G$2:$G$321,"")) -> tbl-number-deaths-leading-sex
A4: Figure ID | B4: =IF($B$1="","",_xlfn.XLOOKUP($B$1,Master!$F$2:$F$321,Master!$H$2:$H$321,"")) -> fig-number-deaths-leading-sex | F4: integer | G4: number | H4: number | I4: number
A5: Table Rules | E5: Enter Data | F5: Cause of Death | G5: Number of Deaths
A6: Multilevel Headers | B6: TRUE | G6: Male | H6: Female | I6: Total
F7: All Causes | G7: 6235 | H7: 6114 | I7: 12349
F8: Disease of the Heart | G8: 1409 | H8: 1214 | I8: 2623
A9: Figure Rules | F9: Malignant Neoplasms | G9: 1165 | H9: 1217 | I9: 2382
A10: Figure Type | F10: Unintentional Injury | G10: 793 | H10: 366 | I10: 1159
A11: X Column | F11: COPD/CLRD | G11: 222 | H11: 271 | I11: 493
A12: Y Column | F12: Cerebrovascular Disease | G12: 176 | H12: 236 | I12: 412
A13: X Axis Title | F13: Alzheimer's Disease | G13: 106 | H13: 292 | I13: 398
A14: Y Axis Title | F14: Diabetes | G14: 155 | H14: 146 | I14: 301
A15: Start at Zero | F15: Pneumonia | G15: 136 | H15: 109 | I15: 245
A16: Pivot For Chart | F16: Septicemia | G16: 128 | H16: 135 | I16: 263
F17: Suicide | G17: 185 | H17: 42 | I17: 227
A18: Source Specifications | F18: Cirrhosis of Liver | G18: 84 | H18: 39 | I18: 123
A19: Source | B19: Source: Special request from NYSDOH Bureau of Vital Records, July 2025
A21: Note Specfications
A22: Note | B22: Note: See Data Note section for more information regarding this request. Birth and death data for Orange County excludes events recorded in NYC. All rates use ACS 5-year population estimates, except for the ages under 1 year and 1-9 years, which are based on crude live births in Orange County.

Sheet Premature Deaths RE
A1: Name | B1: Percentage of Deaths that are Premature, by Race and Ethnicity, 2018–2020
A2: Table/Figure/Both | B2: Both
A3: Object ID | B3: =IF($B$1="","",_xlfn.XLOOKUP($B$1,Master!$F$2:$F$321,Master!$G$2:$G$321,"")) -> tbl-premature-deaths-rande
A4: Figure ID | B4: =IF($B$1="","",_xlfn.XLOOKUP($B$1,Master!$F$2:$F$321,Master!$H$2:$H$321,"")) -> fig-premature-deaths-rande | F4: integer | G4: percent1 | H4: percent1 | I4: percent1 | J4: percent1 | K4: percent1
A5: Table Rules | E5: Enter Data | F5: Region | G5: Total | H5: Non-Hispanic White | I5: Non-Hispanic Black | J5: Non-Hispanic Asian/Pacific Islander | K5: Hispanic
A6: Multilevel Headers | B6: FALSE | F6: Orange | G6: 45.8 | H6: 41.3 | I6: 63.4 | J6: 61.3 | K6: 57.9
F7: NYS excl NYC | G7: 40.8 | H7: 37.3 | I7: 61.6 | J7: 46.5 | K7: 60.8
F8: NYS | G8: 42.9 | H8: 36.6 | I8: 58.6 | J8: 42.9 | K8: 55
A9: Figure Rules
A10: Figure Type | B10: Line
A11: X Column | B11: Region/County
A12: Y Column
A13: X Axis Title | B13: Region/County
A14: Y Axis Title
A15: Start at Zero | B15: TRUE
A16: Pivot For Chart | B16: TRUE
A18: Source Specifications
A19: Source | B19: Source: NYS County Health Indicators by Race and Ethnicity, November 2025 sourced from Vital Statistics of NYS https://www.health.ny.gov/community/health_equity/reports/county/orange.htm
A21: Note Specfications
A22: Note | B22: Note: Premature death includes deaths occurring before the age of 75. The 2018 population estimates are also used to calculate rates for 2019 and 2020. Later years are from the most recent Vintage estimates.

Sheet HMI Pov GINI
A1: Name | B1: Household Median Income, Poverty Status, and GINI Index by Municipality, 2023
A2: Table/Figure/Both | B2: Both
A3: Object ID | B3: =IF($B$1="","",_xlfn.XLOOKUP($B$1,Master!$F$2:$F$321,Master!$G$2:$G$321,"")) -> tbl-income-poverty-gini
A4: Figure ID | B4: =IF($B$1="","",_xlfn.XLOOKUP($B$1,Master!$F$2:$F$321,Master!$H$2:$H$321,"")) -> fig-income-poverty-gini | F4: integer | G4: number | H4: currency | I4: number | J4: percent1 | K4: number | L4: percent1 | M4: number | N4: percent1 | O4: percent2
A5: Table Rules | E5: Enter Data | F5: Geographic Area | G5: Total Households | H5: Median Household Income | I5: Households Below Federal Poverty Level | K5: Households Below Local Poverty Level | M5: Households with Income Over $150,000 | O5: GINI Index
A6: Multilevel Headers | B6: TRUE | I6: # | J6: % | K6: # | L6: % | M6: # | N6: %
F7: Orange County | G7: 137311 | H7: 96497 | I7: 21753 | J7: 15.8 | K7: 35627 | L7: 25.9 | M7: 39482 | N7: 28.8 | O7: 0.44
F8: Blooming Grove Town | G8: 6149 | H8: 100763 | I8: 805 | J8: 13.1 | K8: 1399 | L8: 22.8 | M8: 1825 | N8: 29.7 | O8: 0.41
A9: Figure Rules | F9: South Blooming Grove Village | G9: 1173 | H9: 68958 | I9: 158 | J9: 13.5 | K9: 374 | L9: 31.9 | M9: 142 | N9: 12.1 | O9: 0.39
A10: Figure Type | F10: Washingtonville Village | G10: 2106 | H10: 101080 | I10: 370 | J10: 17.6 | K10: 553 | L10: 26.3 | M10: 590 | N10: 28 | O10: 0.47
A11: X Column | F11: Chester Town | G11: 4458 | H11: 146893 | I11: 357 | J11: 8 | K11: 692 | L11: 15.5 | M11: 2183 | N11: 48.9 | O11: 0.38
A12: Y Column | F12: Chester Village | G12: 1560 | H12: 97250 | I12: 260 | J12: 16.7 | K12: 377 | L12: 24.2 | M12: 563 | N12: 36.1 | O12: 0.38
A13: X Axis Title | F13: Cornwall Town | G13: 5023 | H13: 118639 | I13: 459 | J13: 9.1 | K13: 773 | L13: 15.4 | M13: 1879 | N13: 37.4 | O13: 0.38
A14: Y Axis Title | F14: Cornwall-on-Hudson Village | G14: 1230 | H14: 150288 | I14: 79 | J14: 6.4 | K14: 143 | L14: 11.6 | M14: 627 | N14: 51 | O14: 0.36
A15: Start at Zero | F15: Crawford Town | G15: 3001 | H15: 130656 | I15: 277 | J15: 9.2 | K15: 448 | L15: 14.9 | M15: 1246 | N15: 41.5 | O15: 0.43
A16: Pivot For Chart | F16: Deerpark Town | G16: 2993 | H16: 72164 | I16: 421 | J16: 14.1 | K16: 834 | L16: 27.9 | M16: 448 | N16: 14.9 | O16: 0.4
F17: Goshen Town | G17: 4861 | H17: 117817 | I17: 626 | J17: 12.9 | K17: 1031 | L17: 21.2 | M17: 1895 | N17: 38.9 | O17: 0.47
A18: Source Specifications | F18: Goshen Village | G18: 2350 | H18: 99464 | I18: 436 | J18: 18.6 | K18: 653 | L18: 27.8 | M18: 730 | N18: 31.1 | O18: 0.49
A19: Source | B19: Source: US Census Bureau, American Community Survey 2019–2023 5-Year Population Estimates, Table DP03-Selected Economic Characteristics, Table B11001-Household Type (Including Living Alone), Table B17001-Poverty Status in the Past 12 Months by Sex by Age, Table B19001-Household Income in the Past 12 Months (in 2023 Inflation-Adjusted Dollars), and Table B19083-GINI Index of Income Inequality, November 2025 https://data.census.gov/table/ACSDP5Y2023.DP03?q=DP03+Orange+County,+NY&g=050XX00US36071, https://data.census.gov/table/ACSDT5Y2022.B11001?q=B11001+Orange+County,+NY&g=060XX00US3607134550,360715618 5,3607148857,3607182755,3607147042,3607148153,3607178839,3607130631,3607118300,3607175781,3607150045,36 07147713,3607147999,3607150848,3607129553,3607107003,3607115308,3607131907,3607118916,3607178366,360717 7992,3607119961,3607150034,3607159388_160XX00US3646162,3629542,3630752,3655673,3678355,3676210,3634495, 3615297,3675803,3682750,3677849,3632325,3647988,3678465,3639853,3618333,3668610,3648142_050XX00US36071; https://data.census.gov/table/ACSDT5Y2022.B17001?q=B17001+Orange+County,+NY&g=060XX00US3607134550,360715618 5,3607148857,3607182755,3607147042,3607148153,3607178839,3607130631,3607118300,3607175781,3607150045,36 07147713,3607147999,3607150848,3607129553,3607107003,3607115308,3607131907,3607118916,3607178366,360717 7992,3607119961,3607150034,3607159388_160XX00US3646162,3629542,3630752,3655673,3678355,3676210,3634495, 3615297,3675803,3682750,3677849,3632325,3647988,3678465,3639853,3618333,3668610,3648142_050XX00US36071; https://data.census.gov/table/ACSDT5Y2023.B19001?q=B19001+Orange+County,+NY&g=060XX00US3607134550,360715618 5,3607148857,3607182755,3607147042,3607148153,3607178839,3607130631,3607118300,3607175781,3607150045,36 07147713,3607147999,3607150848,3607129553,3607107003,3607115308,3607131907,3607118916,3607178366,360717 7992,3607119961,3607150034,3607159388_160XX00US3646162,3629542,3630752,3655673,3678355,3676210,3634495, 3615297,3675803,3682750,3677849,3632325,3647988,3678465,3639853,3618333,3668610,3648142_050XX00US36071; and https://data.census.gov/table/ACSDT5Y2023.B19083?q=B19083+Orange+County,+NY&g=060XX00US3607134550,3607156185 ,3607148857,3607182755,3607147042,3607148153,3607178839,3607130631,3607118300,3607175781,3607150045,36 07147713,3607147999,3607150848,3607129553,3607107003,3607115308,3607131907,3607118916,3607178366,36071 77992,3607119961,3607150034,3607159388_160XX00US3646162,3629542,3630752,3655673,3678355,3676210,363449 5,3615297,3675803,3682750,3677849,3632325,3647988,3678465,3639853,3618333,3668610,3648142_050XX00US3607 1 | F19: Greenville Town | G19: 1645 | H19: 130938 | I19: 66 | J19: 4 | K19: 196 | L19: 11.9 | M19: 594 | N19: 36.1 | O19: 0.33
F20: Hamptonburgh Town | G20: 1745 | H20: 113267 | I20: 171 | J20: 9.8 | K20: 310 | L20: 17.8 | M20: 632 | N20: 36.2 | O20: 0.42
A21: Note Specfications | F21: Highlands Town | G21: 3938 | H21: 111786 | I21: 367 | J21: 9.3 | K21: 833 | L21: 21.2 | M21: 1218 | N21: 30.9 | O21: 0.37
A22: Note | B22: Note: Town totals include Village totals. The "local poverty level" standard was initially developed by RECAP and is defined as 50% of the County median household income; in 2023, this was $48,249. The federal poverty level for 2023 is assumed to be a four-person household and is set at $30,000 for 2023. The GINI Index of Income Inequality is a statistical measure of how wealth is concentrated in a location or group. It measures how far a municipalities wealth or income distribution deviated from a perfectly equal distribution. The scale ranges from 0 to 1. A GINI of 0 represents prefect equality or every household has the same income. A GINI of 1 represents perfect inequality or when one household has all the income and everyone else has none. All dollar amounts are indexed to 2023 dollars. | F22: Highland Falls Village | G22: 1648 | H22: 107500 | I22: 221 | J22: 13.4 | K22: 500 | L22: 30.3 | M22: 393 | N22: 23.8 | O22: 0.39
F23: Middletown City | G23: 10182 | H23: 77174 | I23: 2209 | J23: 21.7 | K23: 3329 | L23: 32.7 | M23: 2002 | N23: 19.6 | O23: 0.44
F24: Minisink Town | G24: 1526 | H24: 114048 | I24: 105 | J24: 6.9 | K24: 217 | L24: 14.2 | M24: 464 | N24: 30.4 | O24: 0.37
F25: Unionville Village | G25: 222 | H25: 104615 | I25: 3 | J25: 1.4 | K25: 29 | L25: 13.1 | M25: 59 | N25: 26.6 | O25: 0.42
F26: Monroe Town | G26: 6855 | H26: 116019 | I26: 625 | J26: 9.1 | K26: 1105 | L26: 16.1 | M26: 2522 | N26: 36.8 | O26: 0.39
F27: Harriman Village (portion) | G27: 792 | H27: 95324 | I27: 93 | J27: 11.7 | K27: 209 | L27: 26.4 | M27: 186 | N27: 23.5 | O27: 0.38
F28: Monroe Village | G28: 2886 | H28: 110806 | I28: 283 | J28: 9.8 | K28: 487 | L28: 16.9 | M28: 1000 | N28: 34.7 | O28: 0.36
F29: Montgomery Town | G29: 8306 | H29: 98360 | I29: 1411 | J29: 17 | K29: 2113 | L29: 25.4 | M29: 2318 | N29: 27.9 | O29: 0.42
F30: Maybrook Village | G30: 1401 | H30: 89293 | I30: 279 | J30: 19.9 | K30: 417 | L30: 29.8 | M30: 225 | N30: 16.1 | O30: 0.39
F31: Montgomery Village | G31: 1535 | H31: 88348 | I31: 286 | J31: 18.6 | K31: 414 | L31: 27 | M31: 404 | N31: 26.3 | O31: 0.44
F32: Walden Village | G32: 2621 | H32: 89652 | I32: 650 | J32: 24.8 | K32: 860 | L32: 32.8 | M32: 578 | N32: 22.1 | O32: 0.44
F33: Mount Hope Town | G33: 2094 | H33: 95833 | I33: 336 | J33: 16 | K33: 581 | L33: 27.7 | M33: 626 | N33: 29.9 | O33: 0.45
F34: Otisville Village | G34: 439 | H34: 80625 | I34: 46 | J34: 10.5 | K34: 95 | L34: 21.6 | M34: 66 | N34: 15 | O34: 0.42
... F42: Tuxedo Village | G42: 1151 | H42: 118317 | I42: 130 | J42: 11.3 | K42: 255 | L42: 22.2 | M42: 461 | N42: 40.1 | O42: 0.47
F43: Tuxedo Park Village | G43: 388 | H43: $250,000+ | I43: 15 | J43: 3.9 | K43: 24 | L43: 6.2 | M43: 290 | N43: 74.7 | O43: 0.44
F44: Wallkill Town | G44: 11910 | H44: 94002 | I44: 1746 | J44: 14.7 | K44: 2669 | L44: 22.4 | M44: 2560 | N44: 21.5 | O44: 0.39
F45: Warwick Town | G45: 11743 | H45: 117680 | I45: 1362 | J45: 11.6 | K45: 2244 | L45: 19.1 | M45: 4501 | N45: 38.3 | O45: 0.42
F46: Florida Village | G46: 936 | H46: 117083 | I46: 88 | J46: 9.4 | K46: 127 | L46: 13.6 | M46: 247 | N46: 26.4 | O46: 0.34
F47: Greenwood Lake Village | G47: 1181 | H47: 80240 | I47: 169 | J47: 14.3 | K47: 275 | L47: 23.3 | M47: 223 | N47: 18.9 | O47: 0.4
F48: Warwick Village | G48: 2998 | H48: 81250 | I48: 792 | J48: 26.4 | K48: 1170 | L48: 39 | M48: 800 | N48: 26.7 | O48: 0.48
F49: Wawayanda Town | G49: 2468 | H49: 150000 | I49: 196 | J49: 7.9 | K49: 429 | L49: 17.4 | M49: 1234 | N49: 50 | O49: 0.38
F50: Woodbury Town | G50: 3822 | H50: 133953 | I50: 279 | J50: 7.3 | K50: 498 | L50: 13 | M50: 1746 | N50: 45.6 | O50: 0.38
F51: Harriman Village (portion) | G51: 259 | H51: 95324 | I51: 39 | J51: 15.1 | K51: 43 | L51: 16.6 | M51: 40 | N51: 15.4 | O51: 0.38
F52: Woodbury Village | G52: 3563 | H52: 141607 | I52: 240 | J52: 6.7 | K52: 455 | L52: 12.8 | M52: 1706 | N52: 47.9 | O52: 0.37

Sheet POV Thresh Size Fam #
A1: Name | B1: Poverty Threshold by Size of Family and Number of Related Children Under 18 Years, 2024
A2: Table/Figure/Both | B2: Both
A3: Object ID | B3: =IF($B$1="","",_xlfn.XLOOKUP($B$1,Master!$F$2:$F$321,Master!$G$2:$G$321,"")) -> tbl-poverty-threshold
A4: Figure ID | B4: =IF($B$1="","",_xlfn.XLOOKUP($B$1,Master!$F$2:$F$321,Master!$H$2:$H$321,"")) -> fig-poverty-threshold | F4: integer | G4: currency | H4: currency | I4: currency | J4: currency | K4: currency | L4: currency | M4: currency | N4: currency | O4: currency
A5: Table Rules | E5: Enter Data | F5: Size of family unit | G5: Related children under 18 years
A6: Multilevel Headers | B6: TRUE | G6: None | H6: One | I6: Two | J6: Three | K6: Four | L6: Five | M6: Six | N6: Seven | O6: Eight or more
F7: One person (unrelated individual)
F8: Under age 65 | G8: 16320
A9: Figure Rules | F9: Aged 65 and older | G9: 15045
A10: Figure Type | F10: Two people
A11: X Column | F11: Householder under age 65 | G11: 21006 | H11: 21621
A12: Y Column | F12: Householder aged 65 and older | G12: 18961 | H12: 21540
A13: X Axis Title | F13: Three people | G13: 24537 | H13: 25249 | I13: 25273
A14: Y Axis Title | F14: Four people | G14: 32355 | H14: 32884 | I14: 31812 | J14: 31922
A15: Start at Zero | F15: Five people | G15: 39019 | H15: 39586 | I15: 38374 | J15: 37436 | K15: 36863
A16: Pivot For Chart | F16: Six people | G16: 44879 | H16: 45057 | I16: 44128 | J16: 43238 | K16: 41915 | L16: 41131
F17: Seven people | G17: 51638 | H17: 51961 | I17: 50849 | J17: 50075 | K17: 48631 | L17: 46948 | M17: 45100
A18: Source Specifications | F18: Eight people | G18: 57753 | H18: 58263 | I18: 57215 | J18: 56296 | K18: 54992 | L18: 53337 | M18: 51614 | N18: 51177
A19: Source | B19: Source: US Census Bureau, Poverty Thresholds by Size of Family and Number of Children, 2024, November 2025 https://www.census.gov/data/tables/time-series/demo/income-poverty/historical-poverty-thresholds.html | F19: Nine people or more | G19: 69473 | H19: 69810 | I19: 68882 | J19: 68102 | K19: 66822 | L19: 65062 | M19: 63469 | N19: 63075 | O19: 60640
A21: Note Specfications
A22: Note | B22: Note: The source of the weighted average thresholds is the 2025 Current Population Survey Annual Social and Economic Supplement (CPS ASEC). The official poverty measure compares a family's total before-tax money income to the specific dollar threshold that matches their family size, number of related children under 18, and age of the householder.
K30: `

Sheet Pop Living in POV Age RE
A1: Name | B1: Population Living in Poverty by Age Group, Race and Ethnicity, 2023
A2: Table/Figure/Both | B2: Both
A3: Object ID | B3: =IF($B$1="","",_xlfn.XLOOKUP($B$1,Master!$F$2:$F$321,Master!$G$2:$G$321,"")) -> tbl-poverty-age-rande
A4: Figure ID | B4: =IF($B$1="","",_xlfn.XLOOKUP($B$1,Master!$F$2:$F$321,Master!$H$2:$H$321,"")) -> fig-poverty-age-rande | F4: integer | G4: number | H4: number | I4: number | J4: number | K4: number | L4: number | M4: number | N4: number | O4: number | P4: number
A5: Table Rules | E5: Enter Data | F5: Geographic Area | G5: Population with Known Poverty Status | H5: Population Living in Poverty | I5: Poverty by Age Group | L5: Poverty by Race and Ethnicity
A6: Multilevel Headers | B6: TRUE | I6: Under Age 18 years | J6: Age 18–64 years | K6: Age 65+ years | L6: White | M6: Black | N6: Asian | O6: Multiracial | P6: Hispanic/Latino
F7: Orange County | G7: 395402 | H7: 51238 | I7: 19619 | J7: 25992 | K7: 5697 | L7: 32525 | M7: 6471 | N7: 1134 | O7: 4573 | P7: 11485
F8: Blooming Grove Town | G8: 18639 | H8: 2428 | I8: 1155 | J8: 1025 | K8: 248 | L8: 1796 | M8: 106 | N8: 51 | O8: 107 | P8: 468
A9: Figure Rules | F9: South Blooming Grove Village | G9: 3880 | H9: 1524 | I9: 954 | J9: 564 | K9: 6 | L9: 1323 | M9: 33 | N9: 0 | O9: 7 | P9: 161
A10: Figure Type | F10: Washingtonville Village | G10: 5718 | H10: 422 | I10: 54 | J10: 189 | K10: 179 | L10: 233 | M10: 51 | N10: 30 | O10: 69 | P10: 129
A11: X Column | F11: Chester Town | G11: 12333 | H11: 907 | I11: 53 | J11: 660 | K11: 194 | L11: 771 | M11: 4 | N11: 0 | O11: 132 | P11: 64
A12: Y Column | F12: Chester Village | G12: 4050 | H12: 262 | I12: 0 | J12: 203 | K12: 59 | L12: 130 | M12: 0 | N12: 0 | O12: 132 | P12: 64
A13: X Axis Title | F13: Cornwall Town | G13: 12758 | H13: 622 | I13: 108 | J13: 304 | K13: 210 | L13: 480 | M13: 14 | N13: 72 | O13: 47 | P13: 67
A14: Y Axis Title | F14: Cornwall-on-Hudson Village | G14: 3009 | H14: 72 | I14: 0 | J14: 26 | K14: 46 | L14: 72 | M14: 0 | N14: 0 | O14: 0 | P14: 0
A15: Start at Zero | F15: Crawford Town | G15: 9077 | H15: 320 | I15: 50 | J15: 231 | K15: 39 | L15: 185 | M15: 86 | N15: 0 | O15: 38 | P15: 72
A16: Pivot For Chart | F16: Deerpark Town | G16: 7359 | H16: 627 | I16: 77 | J16: 426 | K16: 124 | L16: 495 | M16: 0 | N16: 0 | O16: 120 | P16: 92
F17: Goshen Town | G17: 13210 | H17: 555 | I17: 135 | J17: 337 | K17: 83 | L17: 327 | M17: 4 | N17: 25 | O17: 192 | P17: 209
A18: Source Specifications | F18: Goshen Village | G18: 5598 | H18: 101 | I18: 9 | J18: 64 | K18: 28 | L18: 101 | M18: 0 | N18: 0 | O18: 0 | P18: 0
A19: Source | B19: Source: US Census Bureau, American Community Survey 2019–2023 5-Year Population Estimates, Table S1701-Poverty Status in the Last 12 Months, November 2025 https://data.census.gov/table/ACSST5Y2023.S1701?q=S1701+Orange+County,+NY&g=050XX00US36071 | F19: Greenville Town | G19: 4652 | H19: 162 | I19: 16 | J19: 108 | K19: 38 | L19: 145 | M19: 0 | N19: 0 | O19: 0 | P19: 17
F20: Hamptonburgh Town | G20: 5407 | H20: 316 | I20: 96 | J20: 206 | K20: 14 | L20: 158 | M20: 0 | N20: 148 | O20: 10 | P20: 10
A21: Note Specfications | F21: Highlands Town | G21: 10450 | H21: 633 | I21: 165 | J21: 369 | K21: 99 | L21: 295 | M21: 61 | N21: 0 | O21: 42 | P21: 289
A22: Note | B22: Note: Town totals include Village totals. | F22: Highland Falls Village | G22: 3696 | H22: 384 | I22: 144 | J22: 215 | K22: 25 | L22: 104 | M22: 61 | N22: 0 | O22: 27 | P22: 219
F23: Middletown City | G23: 29921 | H23: 4641 | I23: 1480 | J23: 2631 | K23: 530 | L23: 1108 | M23: 679 | N23: 60 | O23: 712 | P23: 2983
F24: Minisink Town | G24: 4645 | H24: 476 | I24: 241 | J24: 226 | K24: 9 | L24: 456 | M24: 0 | N24: 0 | O24: 20 | P24: 38
F25: Unionville Village | G25: 684 | H25: 61 | I25: 35 | J25: 26 | K25: 0 | L25: 41 | M25: 0 | N25: 0 | O25: 20 | P25: 38
F26: Monroe Town | G26: 21255 | H26: 1802 | I26: 772 | J26: 909 | K26: 121 | L26: 1191 | M26: 106 | N26: 11 | O26: 138 | P26: 418
F27: Harriman Village (portion) | G27: 2081 | H27: 79 | I27: 16 | J27: 34 | K27: 2 | L27: 43 | M27: 0 | N27: 0 | O27: 21 | P27: 36
F28: Monroe Village | G28: 9466 | H28: 883 | I28: 304 | J28: 520 | K28: 59 | L28: 343 | M28: 90 | N28: 11 | O28: 83 | P28: 382
F29: Montgomery Town | G29: 22899 | H29: 2399 | I29: 474 | J29: 1417 | K29: 508 | L29: 1669 | M29: 240 | N29: 0 | O29: 305 | P29: 479
F30: Maybrook Village | G30: 3147 | H30: 231 | I30: 0 | J30: 61 | K30: 170 | L30: 216 | M30: 5 | N30: 0 | O30: 0 | P30: 27
F31: Montgomery Village | G31: 3800 | H31: 506 | I31: 142 | J31: 243 | K31: 121 | L31: 208 | M31: 158 | N31: 0 | O31: 13 | P31: 328
F32: Walden Village | G32: 6871 | H32: 884 | I32: 193 | J32: 560 | K32: 131 | L32: 535 | M32: 77 | N32: 0 | O32: 224 | P32: 76
F33: Mount Hope Town | G33: 5366 | H33: 300 | I33: 106 | J33: 121 | K33: 73 | L33: 160 | M33: 80 | N33: 48 | O33: 0 | P33: 38
F34: Otisville Village | G34: 1210 | H34: 118 | I34: 64 | J34: 45 | K34: 9 | L34: 50 | M34: 44 | N34: 12 | O34: 0 | P34: 38
... F52: Woodbury Village | G52: 11426 | H52: 573 | I52: 164 | J52: 380 | K52: 29 | L52: 417 | M52: 141 | N52: 0 | O52: 15 | P52: 223

Sheet Pop in Poverty
A1: Name | B1: Population in Poverty, 2019–2022
A2: Table/Figure/Both | B2: Both
A3: Object ID | B3: tbl-poverty-pop
A4: Figure ID | B4: fig-poverty-pop | F4: integer | G4: percent1 | H4: percent1 | I4: percent1 | J4: percent1
A5: Table Rules | E5: Enter Data | F5: Region | G5: 2019 | H5: 2020 | I5: 2021 | J5: 2022
A6: Multilevel Headers | B6: FALSE | F6: Orange | G6: 12.3 | H6: 10.6 | I6: 12.2 | J6: 14.4
F7: NYS | G7: 13.1 | H7: 12.7 | I7: 14 | J7: 14.2
A9: Figure Rules
A10: Figure Type | B10: Line
A11: X Column | B11: Year
A12: Y Column
A13: X Axis Title
A14: Y Axis Title | B14: Percent
A15: Start at Zero | B15: TRUE
A16: Pivot For Chart | B16: TRUE
A18: Source Specifications
A19: Source | B19: Source: NYS Community Health Indicator Reports Dashboard, August 2025 sourced from US Census Bureau, Small Area Income and Poverty Estimates https://webbi1.health.ny.gov/SASStoredProcess/guest?_program=%2FEBI%2FPHIG%2Fapps%2Fchir_dashboard%2Fchir_dashboard& p=ch&cos=33
A21: Note Specfications
A22: Note | B22: Note: This includes the population who live below the federally determined guidelines for poverty.
K31: `

Sheet Pov Status 12M RE
A1: Name | B1: Percentage of Individual Poverty Status in the Past 12 Months, by Race and Ethnicity, 2023
A2: Table/Figure/Both | B2: Both
A3: Object ID | B3: tbl-poverty-individual-rande
A4: Figure ID | B4: fig-poverty-individual-rande | F4: integer | G4: percent1 | H4: percent1 | I4: percent1 | J4: percent1 | K4: percent1 | L4: percent1 | M4: percent1 | N4: percent1 | O4: percent1 | P4: percent1
A5: Table Rules | E5: Enter Data | F5: Region | G5: Total | H5: White Alone | I5: Black or African American Alone | J5: American Indian and Alaska Native Alone | K5: Asian Alone | L5: Native Hawaiian and Other Pacific Islander Alone | M5: Some Other Race Alone | N5: Two or More Races | O5: Hispanic or Latino Origin (Any Race) | P5: White Alone, Not Hispanic or Latino
A6: Multilevel Headers | B6: FALSE | F6: Orange | G6: 13 | H6: 12.8 | I6: 14.6 | J6: 20.3 | K6: 10.2 | L6: 23.1 | M6: 14.9 | N6: 10.5 | O6: 12.4 | P6: 13.1
F7: NYS | G7: 13.7 | H7: 10 | I7: 20.6 | J7: 22.7 | K7: 13.9 | L7: 22.2 | M7: 21.9 | N7: 16 | O7: 20.1 | P7: 9.5
F8: US | G8: 12.4 | H8: 9.9 | I8: 21.3 | J8: 21.8 | K8: 9.9 | L8: 17.2 | M8: 18.2 | N8: 14.7 | O8: 16.9 | P8: 9.2
A9: Figure Rules
A10: Figure Type | B10: Clustered Bar
A11: X Column | B11: Race/Ethnicity
A12: Y Column
A13: X Axis Title | B13: County/State/Country
A14: Y Axis Title | B14: Percent
A15: Start at Zero | B15: TRUE
A16: Pivot For Chart | B16: TRUE
A18: Source Specifications
A19: Source | B19: Source: US Census Bureau; American Community Survey, 2019–2023 5-Year Population Estimates, Table S1701-Poverty Status in the Past 12 Months, August 2025 https://data.census.gov/table/ACSST5Y2023.S1701?q=s1701&g=050XX00US36071_010XX00US_040XX00US36
A21: Note Specfications
A22: Note | B22: Note: The American Community Survey asks respondents their income in the past 12 months. This is for income that is received on a regular basis before payments for taxes, social security, etc. and only includes those above 15 years old.

Sheet Fam Pov Status 12M RE
A1: Name | B1: Percentage of Poverty Status of Families in the Past 12 Months, by Race and Ethnicity, 2023
A2: Table/Figure/Both | B2: Both
A3: Object ID | B3: tbl-poverty-family-rande
A4: Figure ID | B4: fig-poverty-family-rande | F4: integer | G4: percent1 | H4: percent1 | I4: percent1 | J4: percent1 | K4: percent1 | L4: percent1 | M4: percent1 | N4: percent1 | O4: percent1 | P4: percent1
A5: Table Rules | E5: Enter Data | F5: Region | G5: Total | H5: White Alone | I5: Black or African American Alone | J5: American Indian and Alaska Native Alone | K5: Asian Alone | L5: Native Hawaiian and Other Pacific Islander Alone | M5: Some Other Race Alone | N5: Two or More Races | O5: Hispanic or Latino Origin (Any Race) | P5: White Alone, Not Hispanic or Latino
A6: Multilevel Headers | B6: FALSE | F6: Orange | G6: 9.1 | H6: 8.1 | I6: 12.3 | J6: 14.9 | K6: 10.3 | L6: 0 | M6: 10.7 | N6: 9.6 | O6: 10.2 | P6: 8
F7: NYS | G7: 9.8 | H7: 6.2 | I7: 16.4 | J7: 19.2 | K7: 11.3 | L7: 11.4 | M7: 18.8 | N7: 12.8 | O7: 16.9 | P7: 5.7
F8: US | G8: 8.7 | H8: 6.3 | I8: 17.4 | J8: 18.1 | K8: 7.1 | L8: 12.9 | M8: 15.9 | N8: 12.1 | O8: 14.4 | P8: 5.7
A9: Figure Rules
A10: Figure Type | B10: Clustered Bar
A11: X Column | B11: Race/Ethnicity
A12: Y Column
A13: X Axis Title | B13: Region/County
A14: Y Axis Title | B14: Percent
A15: Start at Zero | B15: TRUE
A16: Pivot For Chart | B16: TRUE
A18: Source Specifications
A19: Source | B19: Source: US Census Bureau; American Community Survey, 2017–2021 American Community Survey 5-Year Estimates, Table S1702-Poverty Status in the Past 12 Months of Families, August 2025 https://data.census.gov/table/ACSST5Y2023.S1702?q=S1702:+POVERTY+STATUS+IN+THE+PAST+12+MONTHS+OF+FAMILIES& g=010XX00US_040XX00US36_050XX00US36071
A21: Note Specfications
A22: Note | B22: Note: The American Community Survey asks respondents their income in the past 12 months for all related members of the family living in the household. This is for income that is received on a regular basis before payments for taxes, social security, etc. and only includes those above 15 years old.

Sheet Children Below POV Thresh
A1: Name | B1: Percentage of Children Living Below the Poverty Threshold, 2019–2022
A2: Table/Figure/Both | B2: Both
A3: Object ID | B3: tbl-children-poverty-threshold
A4: Figure ID | B4: fig-children-poverty-threshold | F4: integer | G4: percent1 | H4: percent1 | I4: percent1 | J4: percent1
A5: Table Rules | E5: Enter Data | F5: Region | G5: 2019 | H5: 2020 | I5: 2021 | J5: 2022
A6: Multilevel Headers | B6: FALSE | F6: Orange | G6: 18 | H6: 15.7 | I6: 18 | J6: 21
F7: NYS | G7: 18.2 | H7: 16.7 | I7: 18.8 | J7: 18.6
A9: Figure Rules
A10: Figure Type | B10: Line
A11: X Column | B11: Year
A12: Y Column
A13: X Axis Title | B13: Year
A14: Y Axis Title | B14: Percent
A15: Start at Zero | B15: TRUE
A16: Pivot For Chart | B16: TRUE
A18: Source Specifications
A19: Source | B19: Source: NYS Community Health Indicator Reports Dashboard, August 2025 sourced from US Census Bureau, Small Area Income and Poverty Estimates https://webbi1.health.ny.gov/SASStoredProcess/guest?_program=%2FEBI%2FPHIG%2Fapps%2Fchir_dashboard%2Fchir_dashboard &p=ch&cos=33
A21: Note Specfications
A22: Note | B22: Note: This includes children less than 18 years old who live below the federally determined guidelines for poverty.

Sheet Employment Status Municipali
A1: Name | B1: Employment Status by Municipality, 2023
A2: Table/Figure/Both | B2: Both
A3: Object ID | B3: =IF($B$1="","",_xlfn.XLOOKUP($B$1,Master!$F$2:$F$321,Master!$G$2:$G$321,"")) -> tbl-employment
A4: Figure ID | B4: =IF($B$1="","",_xlfn.XLOOKUP($B$1,Master!$F$2:$F$321,Master!$H$2:$H$321,"")) -> fig-employment | F4: integer | G4: number | H4: number | I4: number | J4: number | K4: number | L4: number
A5: Table Rules | E5: Enter Data | F5: Geographic Area | G5: Total Population Age 16+ | H5: Population Age 16+ in Labor Force | I5: Civilian Labor Force | K5: Armed Forces | L5: Population Age 16+ Not In Labor Force
A6: Multilevel Headers | B6: TRUE | I6: Employed | J6: Unemployed
F7: Orange County | G7: 312794 | H7: 198515 | I7: 184167 | J7: 10556 | K7: 3792 | L7: 114279
F8: Blooming Grove Town | G8: 13963 | H8: 8841 | I8: 8167 | J8: 645 | K8: 29 | L8: 5122
A9: Figure Rules | F9: South Blooming Grove Village | G9: 2303 | H9: 1442 | I9: 1268 | J9: 174 | K9: 0 | L9: 861
A10: Figure Type | F10: Washingtonville Village | G10: 4687 | H10: 3056 | I10: 2827 | J10: 200 | K10: 29 | L10: 1631
A11: X Column | F11: Chester Town | G11: 10311 | H11: 7161 | I11: 6888 | J11: 222 | K11: 51 | L11: 3150
A12: Y Column | F12: Chester Village | G12: 3497 | H12: 2552 | I12: 2488 | J12: 44 | K12: 20 | L12: 945
A13: X Axis Title | F13: Cornwall Town | G13: 10454 | H13: 6811 | I13: 6425 | J13: 262 | K13: 124 | L13: 3643
A14: Y Axis Title | F14: Cornwall-on-Hudson Village | G14: 2569 | H14: 1757 | I14: 1656 | J14: 7 | K14: 94 | L14: 812
A15: Start at Zero | F15: Crawford Town | G15: 7403 | H15: 5259 | I15: 5000 | J15: 259 | K15: 0 | L15: 2144
A16: Pivot For Chart | F16: Deerpark Town | G16: 6229 | H16: 3512 | I16: 3207 | J16: 305 | K16: 0 | L16: 2717
F17: Goshen Town | G17: 11905 | H17: 6893 | I17: 6373 | J17: 505 | K17: 15 | L17: 5012
A18: Source Specifications | F18: Goshen Village | G18: 4743 | H18: 2842 | I18: 2703 | J18: 139 | K18: 0 | L18: 1901
A19: Source | B19: Source: US Census Bureau, American Community Survey 2019–2023 5-Year Population Estimates, Table DP03-Selected Economic Characteristics, November 2025 https://data.census.gov/table/ACSDP5Y2023.DP03?q=DP03+Orange+County,+NY&g=060XX00US3607134550,3607156185,36 07148857,3607182755,3607147042,3607148153,3607178839,3607130631,3607118300,3607175781,3607150045,360714 7713,3607147999,3607150848,3607129553,3607107003,3607115308,3607131907,3607118916,3607178366,3607177992 ,3607119961,3607150034,3607159388_160XX00US3646162,3629542,3630752,3655673,3678355,3676210,3634495,3615 297,3675803,3682750,3677849,3632325,3647988,3678465,3639853,3618333,3668610,3648142_050XX00US36071 | F19: Greenville Town | G19: 3682 | H19: 2623 | I19: 2563 | J19: 60 | K19: 0 | L19: 1059
F20: Hamptonburgh Town | G20: 4418 | H20: 2583 | I20: 2495 | J20: 88 | K20: 0 | L20: 1835
A21: Note Specfications | F21: Highlands Town | G21: 10077 | H21: 7452 | I21: 4373 | J21: 198 | K21: 2881 | L21: 2625
A22: Note | B22: Note: Town totals include Village totals. Armed Forces includes active-duty members of the US Air Force, Army, Coast Guard, Marines, or Navy. They are counted as part of the total labor force but are categorized separately from civilians. | F22: Highland Falls Village | G22: 3007 | H22: 2121 | I22: 1770 | J22: 137 | K22: 214 | L22: 886
F23: Middletown City | G23: 23291 | H23: 14570 | I23: 13664 | J23: 890 | K23: 16 | L23: 8721
F24: Minisink Town | G24: 3499 | H24: 2509 | I24: 2456 | J24: 53 | K24: 0 | L24: 990
F25: Unionville Village | G25: 493 | H25: 368 | I25: 368 | J25: 0 | K25: 0 | L25: 125
F26: Monroe Town | G26: 16348 | H26: 11088 | I26: 10354 | J26: 734 | K26: 0 | L26: 5260
F27: Harriman Village (portion) | G27: 1553 | H27: 1085 | I27: 1052 | J27: 33 | K27: 0 | L27: 468
F28: Monroe Village | G28: 7194 | H28: 5047 | I28: 4852 | J28: 195 | K28: 0 | L28: 2147
F29: Montgomery Town | G29: 18507 | H29: 11935 | I29: 11292 | J29: 495 | K29: 148 | L29: 6572
F30: Maybrook Village | G30: 2698 | H30: 1836 | I30: 1807 | J30: 29 | K30: 0 | L30: 862
F31: Montgomery Village | G31: 3071 | H31: 1910 | I31: 1871 | J31: 19 | K31: 20 | L31: 1161
F32: Walden Village | G32: 5411 | H32: 3402 | I32: 3220 | J32: 182 | K32: 0 | L32: 2009
F33: Mount Hope Town | G33: 5594 | H33: 2717 | I33: 2690 | J33: 27 | K33: 0 | L33: 2877
F34: Otisville Village | G34: 923 | H34: 511 | I34: 500 | J34: 11 | K34: 0 | L34: 412
... F52: Woodbury Village | G52: 8871 | H52: 5826 | I52: 5288 | J52: 516 | K52: 22 | L52: 3045

Sheet Percentage of Labor Force Unemp
A1: Name | B1: Percentage of Labor Force Unemployed, 2020–2023
A2: Table/Figure/Both | B2: Both
A3: Object ID | B3: =IF($B$1="","",_xlfn.XLOOKUP($B$1,Master!$F$2:$F$321,Master!$G$2:$G$321,"")) -> tbl-labor-force-unemployed
A4: Figure ID | B4: =IF($B$1="","",_xlfn.XLOOKUP($B$1,Master!$F$2:$F$321,Master!$H$2:$H$321,"")) -> fig-labor-force-unemployed | F4: integer | G4: percent1 | H4: percent1 | I4: percent1 | J4: percent1
A5: Table Rules | E5: Enter Data | F5: Region | G5: 2020 | H5: 2021 | I5: 2022 | J5: 2023
A6: Multilevel Headers | B6: FALSE | F6: Orange | G6: 8.4 | H6: 4.7 | I6: 3.2 | J6: 3.4
F7: NYS excl NYC | G7: 8.3 | H7: 4.8 | I7: 3.2 | J7: 3.5
A9: Figure Rules
A10: Figure Type | B10: Line
A11: X Column | B11: Year
A12: Y Column
A13: X Axis Title | B13: Year
A14: Y Axis Title | B14: Percent
A15: Start at Zero | B15: TRUE
A16: Pivot For Chart | B16: TRUE
A18: Source Specifications
A19: Source | B19: Source: NYS Community Health Indicator Reports Dashboard, September 2024 sourced from US Department of Labor https://webbi1.health.ny.gov/SASStoredProcess/guest?_program=%2FEBI%2FPHIG%2Fapps%2Fchir_dashboard%2Fchir_dashboard &p=ch&cos=33
A21: Note Specfications
A22: Note | B22: Note: Unemployed is defined as a person actively seeking employment and available for work. Part-time workers are considered employed. The annual average "Percentage Unemployed" aged 16 years and older was calculated by dividing the number unemployed by the total labor force (employed and unemployed) times 100.

Sheet Demo Prof Grad Rate
A1: Name | B1: Demographic Profile and Graduation Rates by Public School District, 2023–2024
A2: Table/Figure/Both | B2: Both
A3: Object ID | B3: =IF($B$1="","",_xlfn.XLOOKUP($B$1,Master!$F$2:$F$321,Master!$G$2:$G$321,"")) -> tbl-graudation-rate-demographic
A4: Figure ID | B4: =IF($B$1="","",_xlfn.XLOOKUP($B$1,Master!$F$2:$F$321,Master!$H$2:$H$321,"")) -> fig-graudation-rate-demographic | F4: integer | G4: integer | H4: number | I4: number | J4: number | K4: number | L4: number | M4: number | N4: number
A5: Table Rules | E5: Enter Data | F5: School District | G5: Racial and Ethnic Origins of Students Enrolled | M5: Drop-Out and Four-Year Graduation Rate
A6: Multilevel Headers | B6: TRUE | G6: American Indian or Alaska Native # (%) | H6: Asian or Native Hawaiian/Other Pacific Islander # (%) | I6: Black or African American # (%) | J6: Hispanic or Latino # (%) | K6: White # (%) | L6: Multiracial # (%) | M6: Drop-Out Rate # (%) | N6: Four-Year Graduation Rate (%)
F7: Chester Union Free | G7: 1 (0) | H7: 32 (4) | I7: 118 (13) | J7: 367 (41) | K7: 362 (40) | L7: 25 (3) | M7: 2 (2) | N7: 94 (91)
F8: Cornwall Central | G8: 3 (0) | H8: 187 (6) | I8: 197 (7) | J8: 733 (25) | K8: 1,730 (58) | L8: 139 (5) | M8: 3 (1) | N8: 263 (97)
A9: Figure Rules | F9: Florida Union Free | G9: 3 (0) | H9: 17 (2) | I9: 50 (7) | J9: 201 (29) | K9: 408 (58) | L9: 22 (3) | M9: 1 (2) | N9: 46 (92)
A10: Figure Type | F10: Goshen Central | G10: 3 (0) | H10: 119 (4) | I10: 162 (6) | J10: 607 (22) | K10: 1,812 (66) | L10: 60 (2) | M10: 6 (2) | N10: 232 (94)
A11: X Column | F11: Greenwood Lake Union Free* | G11: 2 (0) | H11: 10 (2) | I11: 11 (3) | J11: 110 (26) | K11: 280 (66) | L11: 13 (3) | M11: N/A | N11: N/A
A12: Y Column | F12: Highland Falls Central | G12: 3 (0) | H12: 44 (3) | I12: 119 (8) | J12: 240 (16) | K12: 1,034 (69) | L12: 68 (5) | M12: 0 (0) | N12: 92 (88)
A13: X Axis Title | F13: Kiryas Joel Village Union Free* | G13: N/A | H13: N/A | I13: N/A | J13: N/A | K13: 176 (100) | L13: N/A | M13: N/A | N13: N/A
A14: Y Axis Title | F14: Middletown Enlarged City | G14: 13 (0) | H14: 191 (3) | I14: 1,537 (21) | J14: 4,520 (63) | K14: 687 (10) | L14: 268 (4) | M14: 32 (5) | N14: 615 (91)
A15: Start at Zero | F15: Minisink Valley Central | G15: 5 (0) | H15: 71 (2) | I15: 226 (7) | J15: 804 (23) | K15: 2,311 (67) | L15: 34 (1) | M15: 9 (3) | N15: 261 (92)
A16: Pivot For Chart | F16: Monroe-Woodbury Central | G16: 11 (0) | H16: 411 (7) | I16: 725 (11) | J16: 2,911 (46) | K16: 2,051 (32) | L16: 211 (3) | M16: 18 (3) | N16: 555 (90)
F17: Newburgh Enlarged City | G17: 31 (0) | H17: 216 (2) | I17: 2,019 (19) | J17: 6,410 (61) | K17: 1,364 (13) | L17: 476 (5) | M17: 140 (15) | N17: 665 (71)
A18: Source Specifications | F18: Pine Bush Central | G18: 12 (0) | H18: 127 (3) | I18: 549 (12) | J18: 1,213 (27) | K18: 2,489 (55) | L18: 161 (4) | M18: 17 (4) | N18: 419 (92)
A19: Source | B19: Source: NYS Education Department, November 2025 https://data.nysed.gov/enrollment.php?county=44&year=2024&ethnicity5B5D=I&ethnicity5B5D=B&ethnicity5B5D=H&ethnicity5B5D=AP&ethnicity5B5D=W&ethnicity5B5D=M | F19: Port Jervis City | G19: 9 (0) | H19: 36 (2) | I19: 191 (8) | J19: 520 (23) | K19: 1,359 (59) | L19: 185 (8) | M19: 25 (13) | N19: 157 (80)
F20: Tuxedo Union Free* | G20: N/A | H20: 6 (3) | I20: 26 (14) | J20: 59 (31) | K20: 101 (53) | L20: N/A | M20: N/A | N20: N/A
A21: Note Specfications | F21: Valley Central | G21: 6 (0) | H21: 61 (1) | I21: 316 (8) | J21: 1,352 (33) | K21: 2,155 (52) | L21: 234 (6) | M21: 26 (7) | N21: 301 (86)
A22: Note | B22: *: These school districts do not have high schools. Note: Race or races with which the student primarily identifies are indicated by the student or the parent/guardian. Multiracial includes Non-Hispanic students who reported more than one race. Dropout refers to students who were exited as a dropout on or before June 30th of the selected school year. Graduation rate is the percentage of students within a cohort earning a Regents, Regents with Advanced Designation, or a Local Diploma. Students earning a Non Diploma Credential are not counted as graduates. | F22: Warwick Valley Central | G22: 4 (0) | H22: 90 (2) | I22: 162 (4) | J22: 664 (18) | K22: 2,608 (71) | L22: 161 (4) | M22: 4 (1) | N22: 331 (95)
F23: Washingtonville Central | G23: 8 (0) | H23: 72 (2) | I23: 415 (11) | J23: 1,278 (34) | K23: 1,912 (50) | L23: 121 (3) | M23: 9 (2) | N23: 358 (95)
K31: `

Sheet Educ Person 25+
A1: Name | B1: Educational Attainment of Persons 25 years and Over, 2023
A2: Table/Figure/Both | B2: Both
A3: Object ID | B3: =IF($B$1="","",_xlfn.XLOOKUP($B$1,Master!$F$2:$F$321,Master!$G$2:$G$321,"")) -> tbl-educational-attain
A4: Figure ID | B4: =IF($B$1="","",_xlfn.XLOOKUP($B$1,Master!$F$2:$F$321,Master!$H$2:$H$321,"")) -> fig-educational-attain | F4: integer | G4: number | H4: number | I4: percent1 | J4: number | K4: percent1 | L4: number | M4: percent1 | N4: number | O4: percent1 | P4: number | Q4: percent1 | R4: number | S4: percent1 | T4: number | U4: percent1
A5: Table Rules | E5: Enter Data | F5: Geographic Area | G5: Total Population Age 25 and Over | H5: Highest Level of Schooling Achieved
A6: Multilevel Headers | B6: TRUE | H6: < 9th Grade | J6: 9–12th Grade, No Diploma | L6: High School Graduate | N6: Some College, No Degree | P6: Associate's Degree | R6: Bachelor's Degree | T6: Graduate/Professional Degree
H7: # | I7: % | J7: # | K7: % | L7: # | M7: % | N7: # | O7: % | P7: # | Q7: % | R7: # | S7: % | T7: # | U7: %
F8: Orange County | G8: 258632 | H8: 10091 | I8: 390 | J8: 16609 | K8: 640 | L8: 72466 | M8: 2800 | N8: 49355 | O8: 1910 | P8: 26722 | Q8: 1030 | R8: 46977 | S8: 1820 | T8: 36412 | U8: 14.1
A9: Figure Rules | F9: Blooming Grove Town | G9: 11597 | H9: 260 | I9: 2.2 | J9: 591 | K9: 5.1 | L9: 3025 | M9: 26.1 | N9: 2303 | O9: 19.9 | P9: 1728 | Q9: 14.9 | R9: 2143 | S9: 18.5 | T9: 1547 | U9: 13.3
A10: Figure Type | F10: South Blooming Grove Village | G10: 1959 | H10: 7 | I10: 0.4 | J10: 141 | K10: 7.2 | L10: 516 | M10: 26.3 | N10: 629 | O10: 32.1 | P10: 91 | Q10: 4.6 | R10: 303 | S10: 15.5 | T10: 272 | U10: 13.9
A11: X Column | F11: Washingtonville Village | G11: 4006 | H11: 82 | I11: 2 | J11: 253 | K11: 6.3 | L11: 1111 | M11: 27.7 | N11: 822 | O11: 20.5 | P11: 391 | Q11: 9.8 | R11: 914 | S11: 22.8 | T11: 433 | U11: 10.8
A12: Y Column | F12: Chester Town | G12: 8721 | H12: 79 | I12: 0.9 | J12: 238 | K12: 2.7 | L12: 2147 | M12: 24.8 | N12: 1812 | O12: 20.8 | P12: 885 | Q12: 10.1 | R12: 2042 | S12: 23.4 | T12: 1518 | U12: 17.4
A13: X Axis Title | F13: Chester Village | G13: 3001 | H13: 59 | I13: 2 | J13: 125 | K13: 4.2 | L13: 803 | M13: 26.8 | N13: 811 | O13: 27 | P13: 233 | Q13: 7.8 | R13: 683 | S13: 22.8 | T13: 287 | U13: 9.6
A14: Y Axis Title | F14: Cornwall Town | G14: 8939 | H14: 190 | I14: 2.1 | J14: 215 | K14: 2.4 | L14: 1426 | M14: 16 | N14: 1195 | O14: 13.4 | P14: 1132 | Q14: 12.7 | R14: 2275 | S14: 25.5 | T14: 2506 | U14: 28
A15: Start at Zero | F15: Cornwall-on-Hudson Village | G15: 2132 | H15: 11 | I15: 0.5 | J15: 47 | K15: 2.2 | L15: 217 | M15: 10.2 | N15: 225 | O15: 10.6 | P15: 408 | Q15: 19.1 | R15: 520 | S15: 24.4 | T15: 704 | U15: 33
A16: Pivot For Chart | F16: Crawford Town | G16: 6197 | H16: 113 | I16: 1.8 | J16: 186 | K16: 3 | L16: 2009 | M16: 32.4 | N16: 1255 | O16: 20.3 | P16: 715 | Q16: 11.5 | R16: 1147 | S16: 18.5 | T16: 772 | U16: 12.5
F17: Deerpark Town | G17: 5451 | H17: 49 | I17: 0.9 | J17: 266 | K17: 4.9 | L17: 2054 | M17: 37.7 | N17: 1183 | O17: 21.7 | P17: 723 | Q17: 13.3 | R17: 738 | S17: 13.5 | T17: 438 | U17: 8
A18: Source Specifications | F18: Goshen Town | G18: 10366 | H18: 313 | I18: 3 | J18: 876 | K18: 8.5 | L18: 2411 | M18: 23.3 | N18: 1600 | O18: 15.4 | P18: 1008 | Q18: 9.7 | R18: 2216 | S18: 21.4 | T18: 1942 | U18: 18.7
A19: Source | B19: Source: US Census Bureau, American Community Survey, 2019–2023 5-Year Population Estimates, Table S1501-Educational Attainment, November 2025 https://data.census.gov/table/ACSST5Y2023.S1501?q=S1501+Orange+County,+NY&g=050XX00US36071 | F19: Goshen Village | G19: 4276 | H19: 180 | I19: 4.2 | J19: 403 | K19: 9.4 | L19: 866 | M19: 20.3 | N19: 706 | O19: 16.5 | P19: 452 | Q19: 10.6 | R19: 947 | S19: 22.1 | T19: 722 | U19: 16.9
F20: Greenville Town | G20: 3247 | H20: 11 | I20: 0.3 | J20: 81 | K20: 2.5 | L20: 1060 | M20: 32.6 | N20: 679 | O20: 20.9 | P20: 471 | Q20: 14.5 | R20: 463 | S20: 14.3 | T20: 482 | U20: 14.8
A21: Note Specfications | F21: Hamptonburgh Town | G21: 3728 | H21: 118 | I21: 3.2 | J21: 86 | K21: 2.3 | L21: 850 | M21: 22.8 | N21: 744 | O21: 20 | P21: 332 | Q21: 8.9 | R21: 679 | S21: 18.2 | T21: 919 | U21: 24.7
A22: Note | B22: Note: Town totals include Village totals. The category "High School Diploma" includes those who have received a GED or other equivalent document. | F22: Highlands Town | G22: 6664 | H22: 173 | I22: 2.6 | J22: 368 | K22: 5.5 | L22: 1494 | M22: 22.4 | N22: 1069 | O22: 16 | P22: 458 | Q22: 6.9 | R22: 1220 | S22: 18.3 | T22: 1882 | U22: 28.2
F23: Highland Falls Village | G23: 2645 | H23: 94 | I23: 3.6 | J23: 190 | K23: 7.2 | L23: 752 | M23: 28.4 | N23: 430 | O23: 16.3 | P23: 200 | Q23: 7.6 | R23: 484 | S23: 18.3 | T23: 495 | U23: 18.7
F24: Middletown City | G24: 19878 | H24: 1747 | I24: 8.8 | J24: 1801 | K24: 9.1 | L24: 6235 | M24: 31.4 | N24: 3799 | O24: 19.1 | P24: 2374 | Q24: 11.9 | R24: 2084 | S24: 10.5 | T24: 1844 | U24: 9.3
F25: Minisink Town | G25: 2895 | H25: 65 | I25: 2.2 | J25: 168 | K25: 5.8 | L25: 764 | M25: 26.4 | N25: 515 | O25: 17.8 | P25: 247 | Q25: 8.5 | R25: 550 | S25: 19 | T25: 586 | U25: 20.2
F26: Unionville Village | G26: 383 | H26: 16 | I26: 4.2 | J26: 2 | K26: 0.5 | L26: 92 | M26: 24 | N26: 49 | O26: 12.8 | P26: 54 | Q26: 14.1 | R26: 34 | S26: 8.9 | T26: 136 | U26: 35.5
F27: Monroe Town | G27: 13477 | H27: 581 | I27: 4.3 | J27: 628 | K27: 4.7 | L27: 2942 | M27: 21.8 | N27: 2448 | O27: 18.2 | P27: 1041 | Q27: 7.7 | R27: 3659 | S27: 27.1 | T27: 2178 | U27: 16.2
F28: Harriman Village (total)* | G28: 1396 | H28: 51 | I28: 3.6 | J28: 88 | K28: 6.3 | L28: 425 | M28: 30.4 | N28: 146 | O28: 10.5 | P28: 171 | Q28: 12.2 | R28: 292 | S28: 20.9 | T28: 223 | U28: 15.9
F29: Monroe Village | G29: 5796 | H29: 441 | I29: 7.6 | J29: 212 | K29: 3.7 | L29: 1251 | M29: 21.6 | N29: 989 | O29: 17.1 | P29: 604 | Q29: 10.4 | R29: 1541 | S29: 26.6 | T29: 758 | U29: 13.1
F30: Montgomery Town | G30: 15586 | H30: 653 | I30: 4.2 | J30: 971 | K30: 6.2 | L30: 4339 | M30: 27.8 | N30: 3254 | O30: 20.9 | P30: 1979 | Q30: 12.7 | R30: 2712 | S30: 17.4 | T30: 1678 | U30: 10.8
F31: Maybrook Village | G31: 2432 | H31: 80 | I31: 3.3 | J31: 129 | K31: 5.3 | L31: 853 | M31: 35.1 | N31: 571 | O31: 23.5 | P31: 282 | Q31: 11.6 | R31: 394 | S31: 16.2 | T31: 123 | U31: 5.1
F32: Montgomery Village | G32: 2513 | H32: 139 | I32: 5.5 | J32: 128 | K32: 5.1 | L32: 548 | M32: 21.8 | N32: 609 | O32: 24.2 | P32: 290 | Q32: 11.5 | R32: 390 | S32: 15.5 | T32: 409 | U32: 16.3
F33: Walden Village | G33: 4548 | H33: 241 | I33: 5.3 | J33: 309 | K33: 6.8 | L33: 1383 | M33: 30.4 | N33: 1001 | O33: 22 | P33: 511 | Q33: 11.2 | R33: 619 | S33: 13.6 | T33: 484 | U33: 10.6
F34: Mount Hope Town | G34: 4935 | H34: 280 | I34: 5.7 | J34: 713 | K34: 14.4 | L34: 1288 | M34: 26.1 | N34: 738 | O34: 15 | P34: 766 | Q34: 15.5 | R34: 584 | S34: 11.8 | T34: 566 | U34: 11.5
... F53: Woodbury Village | G53: 7068 | H53: 68 | I53: 1 | J53: 250 | K53: 3.5 | L53: 1249 | M53: 17.7 | N53: 1417 | O53: 20 | P53: 822 | Q53: 11.6 | R53: 1672 | S53: 23.7 | T53: 1590 | U53: 22.5

Sheet High School Grad RE
A1: Name | B1: High School Graduation Rate, by Race and Ethnicity, 2023
A2: Table/Figure/Both | B2: Both
A3: Object ID | B3: =IF($B$1="","",_xlfn.XLOOKUP($B$1,Master!$F$2:$F$321,Master!$G$2:$G$321,"")) -> tbl-hs-graduation-rande
A4: Figure ID | B4: =IF($B$1="","",_xlfn.XLOOKUP($B$1,Master!$F$2:$F$321,Master!$H$2:$H$321,"")) -> fig-hs-graduation-rande | F4: integer | G4: percent1 | H4: percent1 | I4: percent1 | J4: percent1 | K4: percent1 | L4: percent1 | M4: percent1
A5: Table Rules | E5: Enter Data | F5: Region | G5: Total | H5: American Indian or Alaska Native | I5: Asian or Native Hawaiian/Other Pacific Islander | J5: Black or African American | K5: Hispanic or Latino | L5: White | M5: Multiracial
A6: Multilevel Headers | B6: FALSE | F6: Orange | G6: 88 | H6: 83 | I6: 96 | J6: 85 | K6: 83 | L6: 93 | M6: 88
F7: NYS | G7: 86 | H7: 81 | I7: 93 | J7: 81 | K7: 81 | L7: 91 | M7: 84
A9: Figure Rules
A10: Figure Type | B10: Clustered Bar
A11: X Column | B11: Race and Ethnicity
A12: Y Column
A13: X Axis Title | B13: Region/County
A14: Y Axis Title | B14: Percent
A15: Start at Zero | B15: TRUE
A16: Pivot For Chart | B16: FALSE
A18: Source Specifications
A19: Source | B19: Source: NYS Education Department, August 2025 https://data.nysed.gov/gradrate.php?year=2022&county=44
A21: Note Specfications
A22: Note | B22: Note: Graduation rate is the percentage of students within a cohort earning a Regents, Regents with Advanced Designation, or a Local Diploma. Students earning a Non Diploma Credential are not counted as graduates.

Sheet Lang Spoken Home
A1: Name | B1: Language Spoken at Home by Municipality, 2023
A2: Table/Figure/Both | B2: Both
A3: Object ID | B3: =IF($B$1="","",_xlfn.XLOOKUP($B$1,Master!$F$2:$F$321,Master!$G$2:$G$321,"")) -> tbl-language-spoken-home
A4: Figure ID | B4: =IF($B$1="","",_xlfn.XLOOKUP($B$1,Master!$F$2:$F$321,Master!$H$2:$H$321,"")) -> fig-language-spoken-home | F4: integer | G4: number | H4: number | I4: number | J4: number | K4: number | L4: number
A5: Table Rules | E5: Enter Data | F5: Geographic Area | G5: Total Population Age 5+ | H5: Language Spoken At Home
A6: Multilevel Headers | B6: TRUE | H6: English Only | I6: Spanish | J6: Other Indo-European | K6: Asian/Pacific Island | L6: Other
F7: Orange County | G7: 376697 | H7: 266545 | I7: 55418 | J7: 45346 | K7: 6298 | L7: 3090
F8: Blooming Grove Town | G8: 17139 | H8: 11552 | I8: 2838 | J8: 2518 | K8: 150 | L8: 81
A9: Figure Rules | F9: South Blooming Grove Village | G9: 3444 | H9: 1326 | I9: 268 | J9: 1786 | K9: 0 | L9: 64
A10: Figure Type | F10: Washingtonville Village | G10: 5521 | H10: 4268 | I10: 957 | J10: 171 | K10: 117 | L10: 8
A11: X Column | F11: Chester Town | G11: 11930 | H11: 9762 | I11: 1728 | J11: 246 | K11: 87 | L11: 107
A12: Y Column | F12: Chester Village | G12: 3965 | H12: 2873 | I12: 872 | J12: 146 | K12: 17 | L12: 57
A13: X Axis Title | F13: Cornwall Town | G13: 12136 | H13: 10815 | I13: 754 | J13: 299 | K13: 247 | L13: 21
A14: Y Axis Title | F14: Cornwall-on-Hudson Village | G14: 2928 | H14: 2545 | I14: 194 | J14: 133 | K14: 51 | L14: 5
A15: Start at Zero | F15: Crawford Town | G15: 8705 | H15: 7399 | I15: 777 | J15: 407 | K15: 109 | L15: 13
A16: Pivot For Chart | F16: Deerpark Town | G16: 7216 | H16: 6587 | I16: 233 | J16: 171 | K16: 225 | L16: 0
F17: Goshen Town | G17: 13829 | H17: 11216 | I17: 1780 | J17: 572 | K17: 192 | L17: 69
A18: Source Specifications | F18: Goshen Village | G18: 5504 | H18: 4437 | I18: 839 | J18: 151 | K18: 47 | L18: 30
A19: Source | B19: Source: US Census Bureau, American Community Survey 2019–2023 5-Year Population Estimates, Table S1601-Language Spoken at Home, November 2025 https://data.census.gov/table/ACSST5Y2023.S1601?q=S1601+Orange+County,+NY&g=060XX00US3607134550,3607156185,3607148857,3607182755,3607147042,360 7148153,3607178839,3607130631,3607118300,3607175781,3607150045,3607147713,3607147999,3607150848,3607129553,3607107003,3607115308,3607131 907,3607118916,3607178366,3607177992,3607119961,3607150034,3607159388_160XX00US3646162,3629542,3630752,3655673,3678355,3676210,3634495,36 15297,3675803,3682750,3677849,3632325,3647988,3678465,3639853,3618333,3668610,3648142_050XX00US36071 | F19: Greenville Town | G19: 4447 | H19: 3862 | I19: 316 | J19: 79 | K19: 175 | L19: 15
F20: Hamptonburgh Town | G20: 5366 | H20: 4439 | I20: 463 | J20: 145 | K20: 239 | L20: 80
A21: Note Specfications | F21: Highlands Town | G21: 12086 | H21: 9659 | I21: 1187 | J21: 765 | K21: 374 | L21: 101
A22: Note | B22: Note: Town totals include Village totals. | F22: Highland Falls Village | G22: 3514 | H22: 2478 | I22: 562 | J22: 408 | K22: 24 | L22: 42
F23: Middletown City | G23: 27829 | H23: 18076 | I23: 8278 | J23: 647 | K23: 712 | L23: 116
F24: Minisink Town | G24: 4359 | H24: 4011 | I24: 241 | J24: 107 | K24: 0 | L24: 0
F25: Unionville Village | G25: 643 | H25: 557 | I25: 47 | J25: 39 | K25: 0 | L25: 0
F26: Monroe Town | G26: 19775 | H26: 13174 | I26: 2927 | J26: 2711 | K26: 387 | L26: 576
F27: Harriman Village (portion) | G27: 1932 | H27: 1332 | I27: 362 | J27: 123 | K27: 13 | L27: 102
F28: Monroe Village | G28: 8514 | H28: 5144 | I28: 1621 | J28: 1325 | K28: 124 | L28: 300
F29: Montgomery Town | G29: 21772 | H29: 18320 | I29: 2280 | J29: 945 | K29: 139 | L29: 88
F30: Maybrook Village | G30: 3017 | H30: 2364 | I30: 441 | J30: 207 | K30: 0 | L30: 0
F31: Montgomery Village | G31: 3470 | H31: 2777 | I31: 6111 | J31: 74 | K31: 8 | L31: 0
F32: Walden Village | G32: 6457 | H32: 5424 | I32: 625 | J32: 342 | K32: 41 | L32: 25
F33: Mount Hope Town | G33: 6326 | H33: 5313 | I33: 755 | J33: 127 | K33: 126 | L33: 5
F34: Otisville Village | G34: 1165 | H34: 921 | I34: 176 | J34: 18 | K34: 50 | L34: 0
... F52: Woodbury Village | G52: 10930 | H52: 8477 | I52: 1183 | J52: 1083 | K52: 139 | L52: 48

Sheet Eng Learners Disav Disab
A1: Name | B1: English Language Learners, Economically Disadvantaged, and Students with Disabilities by Public School District, 2023–2024
A2: Table/Figure/Both | B2: Table
A3: Object ID | B3: =IF($B$1="","",_xlfn.XLOOKUP($B$1,Master!$F$2:$F$321,Master!$G$2:$G$321,"")) -> tbl-english-language-eco-disad-disability
A4: Figure ID | B4: =IF($B$1="","",_xlfn.XLOOKUP($B$1,Master!$F$2:$F$321,Master!$H$2:$H$321,"")) -> fig-english-language-eco-disad-disability | F4: integer | G4: number | H4: number | I4: percent1 | J4: number | K4: percent1 | L4: number | M4: percent1
A5: Table Rules | E5: Enter Data | F5: School District | G5: Total Students | H5: English Language Learners | J5: Economically Disadvantaged | L5: Students with Disabilities
A6: Multilevel Headers | B6: FALSE | G6: # | H6: # | I6: % | J6: # | K6: % | L6: # | M6: %
F7: Chester Union Free | G7: 905 | H7: 44 | I7: 5 | J7: 425 | K7: 47 | L7: 158 | M7: 17
F8: Cornwall Central | G8: 2989 | H8: 73 | I8: 2 | J8: 724 | K8: 24 | L8: 404 | M8: 14
A9: Figure Rules | F9: Florida Union Free | G9: 701 | H9: 35 | I9: 5 | J9: 266 | K9: 38 | L9: 112 | M9: 16
A10: Figure Type | F10: Goshen Central | G10: 2763 | H10: 98 | I10: 4 | J10: 871 | K10: 32 | L10: 405 | M10: 15
A11: X Column | F11: Greenwood Lake Union Free* | G11: 426 | H11: 7 | I11: 2 | J11: 147 | K11: 35 | L11: 72 | M11: 17
A12: Y Column | F12: Highland Falls Central | G12: 914 | H12: 68 | I12: 7 | J12: 447 | K12: 49 | L12: 189 | M12: 21
A13: X Axis Title | F13: Kiryas Joel Village Union Free* | G13: 176 | H13: 149 | I13: 85 | J13: 153 | K13: 87 | L13: 175 | M13: 99
A14: Y Axis Title | F14: Middletown Enlarged City | G14: 7216 | H14: 1065 | I14: 15 | J14: 5370 | K14: 74 | L14: 1220 | M14: 17
A15: Start at Zero | F15: Minisink Valley Central | G15: 3451 | H15: 85 | I15: 2 | J15: 1162 | K15: 34 | L15: 582 | M15: 17
A16: Pivot For Chart | F16: Monroe-Woodbury Central | G16: 6320 | H16: 668 | I16: 11 | J16: 3051 | K16: 48 | L16: 1122 | M16: 18
F17: Newburgh Enlarged City | G17: 10516 | H17: 1910 | I17: 18 | J17: 6408 | K17: 61 | L17: 1765 | M17: 17
A18: Source Specifications | F18: Pine Bush Central | G18: 4551 | H18: 119 | I18: 3 | J18: 2575 | K18: 57 | L18: 775 | M18: 17
A19: Source | B19: Source: NYS Education Department, November 2025 https://data.nysed.gov/enrollment.php?county=44&year=2024&ethnicity%5B%5D=I&ethnicity%5B%5D=B&ethnicity%5B%5D=H&et hnicity%5B%5D=AP&ethnicity%5B%5D=W&ethnicity%5B%5D=M | F19: Port Jervis City | G19: 2300 | H19: 53 | I19: 2 | J19: 1403 | K19: 61 | L19: 489 | M19: 21
F20: Tuxedo Union Free* | G20: 192 | H20: 15 | I20: 8 | J20: 80 | K20: 42 | L20: 34 | M20: 18
A21: Note Specfications | F21: Valley Central | G21: 4124 | H21: 70 | I21: 2 | J21: 1797 | K21: 44 | L21: 799 | M21: 19
A22: Note | B22: *: These school districts do not have high schools. Note: English Language Learners (ELLs) are those who by reason of foreign birth or ancestry, speak or understand a language other than English or understand little or no English, and require support in order to become proficient in English and are identified pursuant to Section 154.3 of Commissioner's Regulations. Student who participates in, or whose family participates in, economic assistance programs, such as the Free or Reduced-Price Lunch Programs; Social Security Insurance (SSI); Supplemental Nutrition Assistance Program (SNAP); Foster Care; Refugee Assistance (cash or medical assistance); Earned Income Tax Credit (EITC); Home Energy Assistance Program (HEAP); Safety Net Assistance (SNA); Bureau of Indian Affairs (BIA); or Family Assistance: Temporary Assistance for Needy Families (TANF). If one student in a family is identified as low income, all students from that household (economic unit) may be identified as low income. Students with disabilities are those who have been identified as such by the Committee on Special Education and are receiving services under the Individuals with Disabilities Education Act (IDEA). Students with disabilities include those having an intellectual disability; hearing impairment, including deafness; speech or language impairment; visual impairment, including blindness; emotional disability; orthopedic impairment; autism; traumatic brain injury; developmental delay; other health impairment; specific learning disability; deaf-blindness; or multiple disabilities and who, by reason thereof, receive special education and related services under the IDEA according to an Individualized Education Program (IEP), Individualized Family Service Plan (IFSP), or a services plan. | F22: Warwick Valley Central | G22: 3689 | H22: 43 | I22: 1 | J22: 798 | K22: 22 | L22: 574 | M22: 16
F23: Washingtonville Central | G23: 3806 | H23: 174 | I23: 5 | J23: 1567 | K23: 41 | L23: 581 | M23: 15
K31: `

Sheet Uninsured Civ Pop RE
A1: Name | B1: Percentage of Uninsured Civilian Noninstitutionalized Population, by Race and Ethnicity, 2023
A2: Table/Figure/Both | B2: Both
A3: Object ID | B3: =IF($B$1="","",_xlfn.XLOOKUP($B$1,Master!$F$2:$F$321,Master!$G$2:$G$321,"")) -> tbl-uninsured-rande
A4: Figure ID | B4: =IF($B$1="","",_xlfn.XLOOKUP($B$1,Master!$F$2:$F$321,Master!$H$2:$H$321,"")) -> fig-uninsured-rande | F4: integer | G4: percent1 | H4: percent1 | I4: percent1 | J4: percent1 | K4: percent1 | L4: percent1 | M4: percent1 | N4: percent1 | O4: percent1 | P4: percent1
A5: Table Rules | E5: Enter Data | F5: Region | G5: Total | H5: White Alone | I5: Black or African American Alone | J5: American Indian and Alaska Native Alone | K5: Asian Alone | L5: Native Hawaiian and Other Pacific Islander Alone | M5: Some Other Race Alone | N5: Two or More Races | O5: Hispanic or Latino Origin (Any Race) | P5: White Alone, Not Hispanic or Latino
A6: Multilevel Headers | B6: FALSE | F6: Orange | G6: 4.8 | H6: 3.4 | I6: 5.2 | J6: 18.8 | K6: 10.6 | L6: 78.1 | M6: 10.4 | N6: 4.7 | O6: 8.4 | P6: 3
F7: NYS | G7: 5.1 | H7: 3.3 | I7: 5.6 | J7: 13.6 | K7: 6 | L7: 12.8 | M7: 11.7 | N7: 6.8 | O7: 9.7 | P7: 3.1
F8: US | G8: 8.6 | H8: 6.6 | I8: 9.5 | J8: 19.2 | K8: 5.9 | L8: 11.6 | M8: 19.7 | N8: 13 | O8: 17.5 | P8: 5.7
A9: Figure Rules
A10: Figure Type | B10: Clustered Bar
A11: X Column | B11: Region/County
A12: Y Column
A13: X Axis Title
A14: Y Axis Title | B14: Percent
A15: Start at Zero | B15: TRUE
A16: Pivot For Chart | B16: TRUE
A18: Source Specifications
A19: Source | B19: Source: US Census Bureau, American Community Survey, 2017–2021 American Community Survey 5-Year Estimates, Table S2701- Selected Characteristics of Health Insurance Coverage in the United States, August 2025 https://data.census.gov/table/ACSST5Y2023.S2701?q=uninsured&g=010XX00US_040XX00US36_050XX00US36071
A21: Note Specfications
A22: Note | B22: Note: The American Community Survey asks respondents about health insurance coverage for each person in the household. A person is considered insured if they have marked "Yes" for at least one of the comprehensive coverage types (insurance through a current or former employer; insurance purchased directly from an insurance company; TRICARE or military health care; Medicare; Medicaid or government assistance plans; or VA healthcare).

Sheet Cars Avail per Household
A1: Name | B1: Vehicles Available per Household by Municipality, 2023
A2: Table/Figure/Both | B2: Table
A3: Object ID | B3: =IF($B$1="","",_xlfn.XLOOKUP($B$1,Master!$F$2:$F$321,Master!$G$2:$G$321,"")) -> tbl-cars-household
A4: Figure ID | B4: =IF($B$1="","",_xlfn.XLOOKUP($B$1,Master!$F$2:$F$321,Master!$H$2:$H$321,"")) -> fig-cars-household | F4: integer | G4: number | H4: number | I4: number | J4: number | K4: number | L4: number
A5: Table Rules | E5: Enter Data | F5: Geographic Area | G5: Total Households | H5: Vehicles Available by Household
A6: Multilevel Headers | B6: TRUE | H6: 0 | I6: 1 | J6: 2 | K6: 3 | L6: 4+
F7: Orange County | G7: 137311 | H7: 11823 | I7: 44006 | J7: 50961 | K7: 19803 | L7: 10718
F8: Blooming Grove Town | G8: 6149 | H8: 259 | I8: 2189 | J8: 2236 | K8: 958 | L8: 507
A9: Figure Rules | F9: South Blooming Grove Village | G9: 1173 | H9: 64 | I9: 598 | J9: 392 | K9: 30 | L9: 89
A10: Figure Type | F10: Washingtonville Village | G10: 2106 | H10: 78 | I10: 647 | J10: 950 | K10: 236 | L10: 195
A11: X Column | F11: Chester Town | G11: 4458 | H11: 139 | I11: 943 | J11: 2154 | K11: 806 | L11: 416
A12: Y Column | F12: Chester Village | G12: 1560 | H12: 124 | I12: 406 | J12: 685 | K12: 305 | L12: 40
A13: X Axis Title | F13: Cornwall Town | G13: 5023 | H13: 102 | I13: 1605 | J13: 2274 | K13: 690 | L13: 352
A14: Y Axis Title | F14: Cornwall-on-Hudson Village | G14: 1230 | H14: 29 | I14: 283 | J14: 713 | K14: 124 | L14: 81
A15: Start at Zero | F15: Crawford Town | G15: 3001 | H15: 23 | I15: 627 | J15: 1059 | K15: 747 | L15: 545
A16: Pivot For Chart | F16: Deerpark Town | G16: 2993 | H16: 92 | I16: 1031 | J16: 1443 | K16: 297 | L16: 130
F17: Goshen Town | G17: 4861 | H17: 357 | I17: 1400 | J17: 1879 | K17: 923 | L17: 302
A18: Source Specifications | F18: Goshen Village | G18: 2350 | H18: 227 | I18: 936 | J18: 774 | K18: 357 | L18: 56
A19: Source | B19: Source: US Census Bureau, American Community Survey 2019–2023 5-Year Population Estimates, Table B08201-Household Size by Vehicles Available, November 2025 https://data.census.gov/table/ACSDT5Y2023.B08201?q=B08201+Orange+County,+NY&g=060XX00US3607134550,360715618 5,3607148857,3607182755,3607147042,3607148153,3607178839,3607130631,3607118300,3607175781,3607150045,36 07147713,3607147999,3607150848,3607129553,3607107003,3607115308,3607131907,3607118916,3607178366,360717 7992,3607119961,3607150034,3607159388_160XX00US3646162,3629542,3630752,3655673,3678355,3676210,3634495, 3615297,3675803,3682750,3677849,3632325,3647988,3678465,3639853,3618333,3668610,3648142_050XX00US36071 | F19: Greenville Town | G19: 1645 | H19: 87 | I19: 271 | J19: 703 | K19: 328 | L19: 256
F20: Hamptonburgh Town | G20: 1745 | H20: 0 | I20: 416 | J20: 648 | K20: 394 | L20: 287
A21: Note Specfications | F21: Highlands Town | G21: 3938 | H21: 105 | I21: 1410 | J21: 1806 | K21: 400 | L21: 217
A22: Note | B22: Note: Town totals include Village totals. | F22: Highland Falls Village | G22: 1648 | H22: 56 | I22: 770 | J22: 588 | K22: 188 | L22: 46
F23: Middletown City | G23: 10182 | H23: 1391 | I23: 3867 | J23: 3270 | K23: 1017 | L23: 637
F24: Minisink Town | G24: 1526 | H24: 43 | I24: 309 | J24: 652 | K24: 207 | L24: 315
F25: Unionville Village | G25: 222 | H25: 0 | I25: 44 | J25: 141 | K25: 23 | L25: 14
F26: Monroe Town | G26: 6855 | H26: 301 | I26: 2096 | J26: 2539 | K26: 1532 | L26: 387
F27: Harriman Village (portion) | G27: 792 | H27: 57 | I27: 346 | J27: 264 | K27: 97 | L27: 28
F28: Monroe Village | G28: 2886 | H28: 137 | I28: 1025 | J28: 966 | K28: 536 | L28: 222
F29: Montgomery Town | G29: 8306 | H29: 421 | I29: 2443 | J29: 3356 | K29: 1258 | L29: 828
F30: Maybrook Village | G30: 1401 | H30: 96 | I30: 706 | J30: 424 | K30: 122 | L30: 53
F31: Montgomery Village | G31: 1535 | H31: 119 | I31: 510 | J31: 711 | K31: 174 | L31: 21
F32: Walden Village | G32: 2621 | H32: 167 | I32: 638 | J32: 1124 | K32: 451 | L32: 241
F33: Mount Hope Town | G33: 2094 | H33: 76 | I33: 723 | J33: 846 | K33: 252 | L33: 197
F34: Otisville Village | G34: 439 | H34: 31 | I34: 143 | J34: 202 | K34: 30 | L34: 33
... F52: Woodbury Village | G52: 3563 | H52: 206 | I52: 686 | J52: 1687 | K52: 551 | L52: 433

Sheet Commuting to Work
A1: Name | B1: Commuting to Work by Municipality, 2023
A2: Table/Figure/Both | B2: Table
A3: Object ID | B3: =IF($B$1="","",_xlfn.XLOOKUP($B$1,Master!$F$2:$F$321,Master!$G$2:$G$321,"")) -> tbl-commute-work
A4: Figure ID | B4: =IF($B$1="","",_xlfn.XLOOKUP($B$1,Master!$F$2:$F$321,Master!$H$2:$H$321,"")) -> fig-commute-work | F4: integer | G4: number | H4: number | I4: number | J4: number | K4: number | L4: number | M4: number | N4: percent1
A5: Table Rules | E5: Enter Data | F5: Geographic Area | G5: Total Workers Age 16+ | H5: Journey to Work | N5: Mean Travel Time in Minutes
A6: Multilevel Headers | B6: TRUE | H6: Drove Alone (Car, Truck, Van) | I6: Carpooled (Car, Truck, Van) | J6: Public Transit (Not Taxicab) | K6: Walked | L6: Other Means | M6: Worked From Home
F7: Orange County | G7: 183509 | H7: 126559 | I7: 17469 | J7: 8069 | K7: 6707 | L7: 3611 | M7: 21094 | N7: 34.2
F8: Blooming Grove Town | G8: 7934 | H8: 5434 | I8: 707 | J8: 778 | K8: 50 | L8: 14 | M8: 951 | N8: 43.8
A9: Figure Rules | F9: South Blooming Grove Village | G9: 1268 | H9: 845 | I9: 111 | J9: 59 | K9: 2 | L9: 8 | M9: 243 | N9: 43.3
A10: Figure Type | F10: Washingtonville Village | G10: 2748 | H10: 2067 | I10: 170 | J10: 145 | K10: 9 | L10: 6 | M10: 351 | N10: 36.3
A11: X Column | F11: Chester Town | G11: 6816 | H11: 5003 | I11: 357 | J11: 440 | K11: 70 | L11: 12 | M11: 934 | N11: 41
A12: Y Column | F12: Chester Village | G12: 2406 | H12: 1866 | I12: 93 | J12: 336 | K12: 20 | L12: 0 | M12: 91 | N12: 37.4
A13: X Axis Title | F13: Cornwall Town | G13: 6448 | H13: 4762 | I13: 443 | J13: 227 | K13: 73 | L13: 98 | M13: 845 | N13: 32.2
A14: Y Axis Title | F14: Cornwall-on-Hudson Village | G14: 1741 | H14: 1330 | I14: 54 | J14: 72 | K14: 18 | L14: 9 | M14: 258 | N14: 38.7
A15: Start at Zero | F15: Crawford Town | G15: 4997 | H15: 3987 | I15: 267 | J15: 0 | K15: 91 | L15: 3 | M15: 649 | N15: 34.1
A16: Pivot For Chart | F16: Deerpark Town | G16: 3119 | H16: 2356 | I16: 559 | J16: 73 | K16: 6 | L16: 37 | M16: 88 | N16: 32.3
F17: Goshen Town | G17: 6256 | H17: 4260 | I17: 433 | J17: 334 | K17: 138 | L17: 94 | M17: 997 | N17: 39.3
A18: Source Specifications | F18: Goshen Village | G18: 2663 | H18: 1777 | I18: 259 | J18: 167 | K18: 42 | L18: 58 | M18: 360 | N18: 27.6
A19: Source | B19: Source: US Census Bureau, American Community Survey 2019–2023 5-Year Population Estimates, Table DP03-Selected Economic Characteristics, November 2025 https://data.census.gov/table/ACSDP5Y2023.DP03?q=DP03+Orange+County,+NY&g=060XX00US3607134550,3607156185,3607148857,3607182755,3607147042,3607148153,3607178839,3607130631,36071 18300,3607175781,3607150045,3607147713,3607147999,3607150848,3607129553,3607107003,3607115308,3607131907,3607118916,3607178366,3607177992,3607119961,3607150034,3607159388_1 60XX00US3646162,3629542,3630752,3655673,3678355,3676210,3634495,3615297,3675803,3682750,3677849,3632325,3647988,3678465,3639853,3618333,3668610,3648142_050XX00US36071 | F19: Greenville Town | G19: 2459 | H19: 2100 | I19: 186 | J19: 24 | K19: 0 | L19: 4 | M19: 145 | N19: 41.2
F20: Hamptonburgh Town | G20: 2428 | H20: 1864 | I20: 93 | J20: 106 | K20: 0 | L20: 0 | M20: 365 | N20: 41.2
A21: Note Specfications | F21: Highlands Town | G21: 6699 | H21: 4078 | I21: 342 | J21: 17 | K21: 1241 | L21: 144 | M21: 1177 | N21: 19
A22: Note | B22: Note: Town totals include Village totals. | F22: Highland Falls Village | G22: 1915 | H22: 1457 | I22: 187 | J22: 0 | K22: 75 | L22: 31 | M22: 165 | N22: 24.2
F23: Middletown City | G23: 13184 | H23: 8506 | I23: 2446 | J23: 593 | K23: 355 | L23: 522 | M23: 762 | N23: 35.4
F24: Minisink Town | G24: 2438 | H24: 1837 | I24: 213 | J24: 15 | K24: 14 | L24: 76 | M24: 283 | N24: 39.6
F25: Unionville Village | G25: 368 | H25: 269 | I25: 49 | J25: 0 | K25: 14 | L25: 0 | M25: 36 | N25: 33.2
F26: Monroe Town | G26: 10178 | H26: 6377 | I26: 1229 | J26: 729 | K26: 86 | L26: 370 | M26: 1387 | N26: 37.3
F27: Harriman Village (portion) | G27: 1033 | H27: 630 | I27: 131 | J27: 52 | K27: 21 | L27: 49 | M27: 150 | N27: 36.8
F28: Monroe Village | G28: 4780 | H28: 3427 | I28: 584 | J28: 183 | K28: 30 | L28: 178 | M28: 378 | N28: 33.2
F29: Montgomery Town | G29: 11313 | H29: 9030 | I29: 794 | J29: 243 | K29: 97 | L29: 205 | M29: 944 | N29: 32.1
F30: Maybrook Village | G30: 1785 | H30: 1315 | I30: 191 | J30: 15 | K30: 0 | L30: 106 | M30: 158 | N30: 33.9
F31: Montgomery Village | G31: 1867 | H31: 1475 | I31: 202 | J31: 45 | K31: 8 | L31: 8 | M31: 129 | N31: 32.4
F32: Walden Village | G32: 3173 | H32: 2620 | I32: 118 | J32: 12 | K32: 46 | L32: 0 | M32: 377 | N32: 30.6
F33: Mount Hope Town | G33: 2624 | H33: 2138 | I33: 144 | J33: 30 | K33: 9 | L33: 5 | M33: 298 | N33: 37
F34: Otisville Village | G34: 495 | H34: 416 | I34: 17 | J34: 0 | K34: 9 | L34: 5 | M34: 48 | N34: 34.9
... F52: Woodbury Village | G52: 5151 | H52: 3899 | I52: 486 | J52: 284 | K52: 0 | L52: 59 | M52: 423 | N52: 45.7

Sheet Housing Tenure and Vacancy
A1: Name | B1: Housing Tenure and Vacancy Status by Municipality, 2023
A2: Table/Figure/Both | B2: Both
A3: Object ID | B3: =IF($B$1="","",_xlfn.XLOOKUP($B$1,Master!$F$2:$F$321,Master!$G$2:$G$321,"")) -> tbl-house-tenure-vacancy
A4: Figure ID | B4: =IF($B$1="","",_xlfn.XLOOKUP($B$1,Master!$F$2:$F$321,Master!$H$2:$H$321,"")) -> fig-house-tenure-vacancy | F4: integer | G4: number | H4: number | I4: number | J4: number | K4: number | L4: number | M4: number | N4: number | O4: number | P4: number | Q4: number | R4: number
A5: Table Rules | E5: Enter Data | F5: Geographic Area | G5: Total Housing Units | H5: Occupied Housing Units | N5: Vacant Housing Units
A6: Multilevel Headers | B6: TRUE | H6: Total Number | I6: Owner-Occupied | J6: Renter-Occupied | K6: Total Number | L6: For Rent | M6: Rented, Not Occupied | N6: For Sale | O6: Sold, Not Occupied | P6: Seasonal/Recreational | Q6: Migrant Labor Housing | R6: Other
F7: Orange County | G7: 148460 | H7: 137311 | I7: 93959 | J7: 43352 | K7: 11149 | L7: 1622 | M7: 255 | N7: 1005 | O7: 692 | P7: 2154 | Q7: 47 | R7: 5374
F8: Blooming Grove Town | G8: 6884 | H8: 6149 | I8: 5016 | J8: 1133 | K8: 695 | L8: 93 | M8: 0 | N8: 65 | O8: 68 | P8: 186 | Q8: 0 | R8: 283
A9: Figure Rules | F9: South Blooming Grove Village | G9: 1390 | H9: 1173 | I9: 714 | J9: 459 | K9: 217 | L9: 14 | M9: 0 | N9: 0 | O9: 39 | P9: 71 | Q9: 0 | R9: 93
A10: Figure Type | F10: Washingtonville Village | G10: 2186 | H10: 2106 | I10: 1670 | J10: 436 | K10: 80 | L10: 44 | M10: 0 | N10: 0 | O10: 0 | P10: 36 | Q10: 0 | R10: 0
A11: X Column | F11: Chester Town | G11: 4763 | H11: 4458 | I11: 3538 | J11: 920 | K11: 305 | L11: 0 | M11: 0 | N11: 45 | O11: 0 | P11: 56 | Q11: 0 | R11: 204
A12: Y Column | F12: Chester Village | G12: 1687 | H12: 1560 | I12: 828 | J12: 732 | K12: 127 | L12: 0 | M12: 0 | N12: 0 | O12: 0 | P12: 56 | Q12: 0 | R12: 71
A13: X Axis Title | F13: Cornwall Town | G13: 5366 | H13: 5023 | I13: 3815 | J13: 1208 | K13: 343 | L13: 28 | M13: 18 | N13: 93 | O13: 0 | P13: 73 | Q13: 0 | R13: 131
A14: Y Axis Title | F14: Cornwall-on-Hudson Village | G14: 1337 | H14: 1230 | I14: 920 | J14: 310 | K14: 107 | L14: 0 | M14: 9 | N14: 27 | O14: 0 | P14: 28 | Q14: 0 | R14: 43
A15: Start at Zero | F15: Crawford Town | G15: 3093 | H15: 3001 | I15: 2299 | J15: 702 | K15: 92 | L15: 0 | M15: 0 | N15: 0 | O15: 0 | P15: 60 | Q15: 0 | R15: 32
A16: Pivot For Chart | F16: Deerpark Town | G16: 3347 | H16: 2993 | I16: 2254 | J16: 739 | K16: 354 | L16: 21 | M16: 0 | N16: 19 | O16: 25 | P16: 83 | Q16: 0 | R16: 206
F17: Goshen Town | G17: 5371 | H17: 4861 | I17: 3868 | J17: 993 | K17: 510 | L17: 76 | M17: 11 | N17: 50 | O17: 26 | P17: 126 | Q17: 0 | R17: 221
A18: Source Specifications | F18: Goshen Village | G18: 2583 | H18: 2350 | I18: 1560 | J18: 790 | K18: 233 | L18: 76 | M18: 11 | N18: 0 | O18: 0 | P18: 74 | Q18: 0 | R18: 72
A19: Source | B19: Source: US Census Bureau, American Community Survey 2019–2023 5-Year Population Estimates, Table B25003-Tenure and Table B25004-Vacancy Status, November 2025 https://data.census.gov/table/ACSDT5Y2023.B25003?q=B25003+Orange+County,+NY&g=060XX00US3607134550,3607156185,3607148857,3607182755,3607147042,3607148153,3607178839,3607130631,3 607118300,3607175781,3607150045,3607147713,3607147999,3607150848,3607129553,3607107003,3607115308,3607131907,3607118916,3607178366,3607177992,3607119961,3607150034,36071593 88_160XX00US3646162,3629542,3630752,3655673,3678355,3676210,3634495,3615297,3675803,3682750,3677849,3632325,3647988,3678465,3639853,3618333,3668610,3648142_050XX00US36071 and https://data.census.gov/table/ACSDT5Y2023.B25004?q=B25004+Orange+County,+NY&g=060XX00US3607134550,3607156185,3607148857,3607182755,3607147042,3607148153,3607178839,3607130631,3 607118300,3607175781,3607150045,3607147713,3607147999,3607150848,3607129553,3607107003,3607115308,3607131907,3607118916,3607178366,3607177992,3607119961,3607150034,36071593 88_160XX00US3646162,3629542,3630752,3655673,3678355,3676210,3634495,3615297,3675803,3682750,3677849,3632325,3647988,3678465,3639853,3618333,3668610,3648142_050XX00US36071 | F19: Greenville Town | G19: 1775 | H19: 1645 | I19: 1379 | J19: 266 | K19: 130 | L19: 26 | M19: 0 | N19: 0 | O19: 0 | P19: 13 | Q19: 0 | R19: 91
F20: Hamptonburgh Town | G20: 1842 | H20: 1745 | I20: 1625 | J20: 120 | K20: 97 | L20: 0 | M20: 0 | N20: 9 | O20: 11 | P20: 0 | Q20: 0 | R20: 77
A21: Note Specfications | F21: Highlands Town | G21: 4240 | H21: 3938 | I21: 1639 | J21: 2299 | K21: 302 | L21: 127 | M21: 0 | N21: 0 | O21: 0 | P21: 36 | Q21: 0 | R21: 139
A22: Note | B22: Note: Town totals include Village totals. The Village of Harriman is split between the Towns of Monroe and Woodbury. | F22: Highland Falls Village | G22: 1798 | H22: 1648 | I22: 898 | J22: 750 | K22: 150 | L22: 21 | M22: 0 | N22: 0 | O22: 0 | P22: 22 | Q22: 0 | R22: 107
F23: Middletown City | G23: 11018 | H23: 10182 | I23: 5341 | J23: 4841 | K23: 836 | L23: 201 | M23: 0 | N23: 38 | O23: 0 | P23: 20 | Q23: 0 | R23: 577
F24: Minisink Town | G24: 1628 | H24: 1526 | I24: 1244 | J24: 282 | K24: 102 | L24: 51 | M24: 0 | N24: 6 | O24: 0 | P24: 7 | Q24: 0 | R24: 38
F25: Unionville Village | G25: 235 | H25: 222 | I25: 134 | J25: 88 | K25: 13 | L25: 0 | M25: 0 | N25: 6 | O25: 0 | P25: 7 | Q25: 0 | R25: 0
F26: Monroe Town | G26: 7395 | H26: 6855 | I26: 5552 | J26: 1303 | K26: 540 | L26: 65 | M26: 0 | N26: 145 | O26: 17 | P26: 135 | Q26: 0 | R26: 178
F27: Harriman Village (portion) | G27: 878 | H27: 792 | I27: 447 | J27: 345 | K27: 86 | L27: 38 | M27: 0 | N27: 0 | O27: 0 | P27: 0 | Q27: 0 | R27: 48
F28: Monroe Village | G28: 2969 | H28: 2886 | I28: 2372 | J28: 514 | K28: 83 | L28: 27 | M28: 0 | N28: 0 | O28: 0 | P28: 33 | Q28: 0 | R28: 23
F29: Montgomery Town | G29: 8972 | H29: 8306 | I29: 5721 | J29: 2585 | K29: 666 | L29: 78 | M29: 41 | N29: 42 | O29: 0 | P29: 59 | Q29: 0 | R29: 446
F30: Maybrook Village | G30: 1519 | H30: 1401 | I30: 758 | J30: 643 | K30: 118 | L30: 19 | M30: 0 | N30: 0 | O30: 0 | P30: 0 | Q30: 0 | R30: 99
F31: Montgomery Village | G31: 1600 | H31: 1535 | I31: 1047 | J31: 488 | K31: 65 | L31: 24 | M31: 41 | N31: 0 | O31: 0 | P31: 0 | Q31: 0 | R31: 0
F32: Walden Village | G32: 2882 | H32: 2621 | I32: 1648 | J32: 973 | K32: 261 | L32: 35 | M32: 0 | N32: 0 | O32: 0 | P32: 39 | Q32: 0 | R32: 187
F33: Mount Hope Town | G33: 2289 | H33: 2094 | I33: 1686 | J33: 408 | K33: 195 | L33: 5 | M33: 0 | N33: 29 | O33: 6 | P33: 70 | Q33: 0 | R33: 85
F34: Otisville Village | G34: 468 | H34: 439 | I34: 273 | J34: 166 | K34: 29 | L34: 0 | M34: 0 | N34: 0 | O34: 6 | P34: 6 | Q34: 0 | R34: 17
... F52: Woodbury Village | G52: 3934 | H52: 3563 | I52: 3322 | J52: 241 | K52: 371 | L52: 128 | M52: 0 | N52: 35 | O52: 0 | P52: 151 | Q52: 0 | R52: 57

Sheet Housing Unit Ages
A1: Name | B1: Housing Unit Ages by Municipality, 202
A2: Table/Figure/Both | B2: Both
A3: Object ID | B3: =IF($B$1="","",_xlfn.XLOOKUP($B$1,Master!$F$2:$F$321,Master!$G$2:$G$321,"")) -> tbl-house-unit-age
A4: Figure ID | B4: =IF($B$1="","",_xlfn.XLOOKUP($B$1,Master!$F$2:$F$321,Master!$H$2:$H$321,"")) -> fig-house-unit-age | F4: integer | G4: number | H4: number | I4: number | J4: number | K4: number | L4: number | M4: number | N4: number | O4: number
A5: Table Rules | E5: Enter Data | F5: Geographic Area | G5: Total # of Housing Units | H5: Year Structure Built
A6: Multilevel Headers | B6: TRUE | H6: 2020 or later | I6: 2010–2019 | J6: 2000–2009 | K6: 1990–1999 | L6: 1980–1989 | M6: 1970–1979 | N6: 1950–1969 | O6: 1949 or earlier
F7: Orange County | G7: 148460 | H7: 1109 | I7: 10815 | J7: 18207 | K7: 14286 | L7: 19738 | M7: 18626 | N7: 29807 | O7: 35872
F8: Blooming Grove Town | G8: 6884 | H8: 38 | I8: 175 | J8: 905 | K8: 681 | L8: 1265 | M8: 1099 | N8: 1650 | O8: 1031
A9: Figure Rules | F9: South Blooming Grove Village | G9: 1390 | H9: 0 | I9: 7 | J9: 19 | K9: 69 | L9: 142 | M9: 463 | N9: 626 | O9: 64
A10: Figure Type | F10: Washingtonville Village | G10: 2186 | H10: 13 | I10: 64 | J10: 294 | K10: 303 | L10: 688 | M10: 434 | N10: 301 | O10: 89
A11: X Column | F11: Chester Town | G11: 4763 | H11: 65 | I11: 243 | J11: 655 | K11: 485 | L11: 1065 | M11: 493 | N11: 996 | O11: 761
A12: Y Column | F12: Chester Village | G12: 1687 | H12: 0 | I12: 111 | J12: 54 | K12: 85 | L12: 531 | M12: 163 | N12: 292 | O12: 451
A13: X Axis Title | F13: Cornwall Town | G13: 5366 | H13: 0 | I13: 284 | J13: 393 | K13: 329 | L13: 808 | M13: 438 | N13: 1474 | O13: 1640
A14: Y Axis Title | F14: Cornwall-on-Hudson Village | G14: 1337 | H14: 0 | I14: 77 | J14: 38 | K14: 37 | L14: 205 | M14: 59 | N14: 333 | O14: 588
A15: Start at Zero | F15: Crawford Town | G15: 3093 | H15: 0 | I15: 107 | J15: 580 | K15: 487 | L15: 395 | M15: 437 | N15: 455 | O15: 629
A16: Pivot For Chart | F16: Deerpark Town | G16: 3347 | H16: 21 | I16: 142 | J16: 303 | K16: 462 | L16: 473 | M16: 565 | N16: 689 | O16: 692
F17: Goshen Town | G17: 5371 | H17: 56 | I17: 374 | J17: 510 | K17: 503 | L17: 795 | M17: 924 | N17: 998 | O17: 1211
A18: Source Specifications | F18: Goshen Village | G18: 2583 | H18: 25 | I18: 125 | J18: 197 | K18: 216 | L18: 388 | M18: 375 | N18: 455 | O18: 802
A19: Source | B19: Source: US Census Bureau, American Community Survey 2019–2023 5-Year Population Estimates, Table B25034-Year Structure Built, November 2025 https://data.census.gov/table/ACSDT5Y2023.B25034?q=B25034+Orange+County,+NY&g=050XX00US36071 | F19: Greenville Town | G19: 1775 | H19: 0 | I19: 172 | J19: 380 | K19: 260 | L19: 341 | M19: 188 | N19: 293 | O19: 141
F20: Hamptonburgh Town | G20: 1842 | H20: 0 | I20: 74 | J20: 300 | K20: 296 | L20: 320 | M20: 237 | N20: 270 | O20: 345
A21: Note Specfications | F21: Highlands Town | G21: 4240 | H21: 0 | I21: 140 | J21: 460 | K21: 327 | L21: 415 | M21: 554 | N21: 809 | O21: 1535
A22: Note | B22: Note: Town totals include Village totals. | F22: Highland Falls Village | G22: 1798 | H22: 0 | I22: 23 | J22: 18 | K22: 52 | L22: 123 | M22: 237 | N22: 625 | O22: 720
F23: Middletown City | G23: 11018 | H23: 241 | I23: 824 | J23: 924 | K23: 510 | L23: 1070 | M23: 1215 | N23: 2201 | O23: 4033
F24: Minisink Town | G24: 1628 | H24: 7 | I24: 95 | J24: 431 | K24: 206 | L24: 178 | M24: 162 | N24: 219 | O24: 330
F25: Unionville Village | G25: 235 | H25: 0 | I25: 17 | J25: 55 | K25: 6 | L25: 40 | M25: 0 | N25: 37 | O25: 80
F26: Monroe Town | G26: 7395 | H26: 20 | I26: 320 | J26: 1024 | K26: 952 | L26: 1367 | M26: 648 | N26: 1606 | O26: 1458
F27: Harriman Village (portion) | G27: 878 | H27: 0 | I27: 126 | J27: 63 | K27: 71 | L27: 372 | M27: 34 | N27: 39 | O27: 173
F28: Monroe Village | G28: 2969 | H28: 20 | I28: 138 | J28: 139 | K28: 655 | L28: 408 | M28: 370 | N28: 752 | O28: 487
F29: Montgomery Town | G29: 8972 | H29: 69 | I29: 458 | J29: 1070 | K29: 1034 | L29: 964 | M29: 1211 | N29: 1638 | O29: 2528
F30: Maybrook Village | G30: 1519 | H30: 0 | I30: 116 | J30: 98 | K30: 82 | L30: 287 | M30: 305 | N30: 190 | O30: 441
F31: Montgomery Village | G31: 1600 | H31: 0 | I31: 58 | J31: 312 | K31: 311 | L31: 145 | M31: 336 | N31: 144 | O31: 294
F32: Walden Village | G32: 2882 | H32: 13 | I32: 8 | J32: 394 | K32: 417 | L32: 163 | M32: 187 | N32: 463 | O32: 1237
F33: Mount Hope Town | G33: 2289 | H33: 15 | I33: 124 | J33: 394 | K33: 246 | L33: 161 | M33: 485 | N33: 306 | O33: 558
F34: Otisville Village | G34: 468 | H34: 8 | I34: 7 | J34: 39 | K34: 24 | L34: 37 | M34: 66 | N34: 71 | O34: 216
... F52: Woodbury Village | G52: 3934 | H52: 0 | I52: 260 | J52: 458 | K52: 468 | L52: 752 | M52: 435 | N52: 772 | O52: 789

Sheet Selected Housing Characteristic
A1: Name | B1: Selected Housing Characteristics for Homeowners by Municipality, 2023
A2: Table/Figure/Both | B2: Both
A3: Object ID | B3: =IF($B$1="","",_xlfn.XLOOKUP($B$1,Master!$F$2:$F$321,Master!$G$2:$G$321,"")) -> tbl-house-characteristics-homeowner
A4: Figure ID | B4: =IF($B$1="","",_xlfn.XLOOKUP($B$1,Master!$F$2:$F$321,Master!$H$2:$H$321,"")) -> fig-house-characteristics-homeowner | F4: integer | G4: number | H4: number | I4: number | J4: percent1 | K4: currency | L4: currency | M4: number
A5: Table Rules | E5: Enter Data | F5: Geographic Area | G5: Housing Costs, Home Values, Vacancy Rates and Cost-Stressed Households
A6: Multilevel Headers | B6: TRUE | G6: Total # of Housing Units | H6: # of Occupied Housing Units | I6: # of Owner-Occupied Housing Units | J6: % Homeowner Vacancy Rate | K6: Median Home Value $ | L6: Median Selected Monthly Owner Costs (Mortgage) $ | M6: # of Cost-Stressed Homeowner Households
F7: Orange County | G7: 148460 | H7: 137311 | I7: 93959 | J7: 1.1 | K7: 361100 | L7: 2653 | M7: 30065
F8: Blooming Grove Town | G8: 6844 | H8: 6149 | I8: 5016 | J8: 1.3 | K8: 372900 | L8: 2738 | M8: 2083
A9: Figure Rules | F9: South Blooming Grove Village | G9: 1483 | H9: 1261 | I9: 995 | J9: 2.4 | K9: 349800 | L9: 2536 | M9: 500
A10: Figure Type | F10: Washingtonville Village | G10: 2080 | H10: 2004 | I10: 1575 | J10: 1.9 | K10: 268100 | L10: 2464 | M10: 507
A11: X Column | F11: Chester Town | G11: 4763 | H11: 4458 | I11: 3538 | J11: 1.3 | K11: 399700 | L11: 3094 | M11: 1026
A12: Y Column | F12: Chester Village | G12: 1735 | H12: 1643 | I12: 922 | J12: 5.1 | K12: 219600 | L12: 2260 | M12: 409
A13: X Axis Title | F13: Cornwall Town | G13: 5366 | H13: 5023 | I13: 3815 | J13: 2.4 | K13: 416500 | L13: 2994 | M13: 1160
A14: Y Axis Title | F14: Cornwall-on-Hudson Village | G14: 1250 | H14: 1186 | I14: 818 | J14: 1.9 | K14: 349800 | L14: 2813 | M14: 321
A15: Start at Zero | F15: Crawford Town | G15: 3093 | H15: 3001 | I15: 2299 | J15: 0 | K15: 384700 | L15: 2490 | M15: 399
A16: Pivot For Chart | F16: Deerpark Town | G16: 3347 | H16: 2993 | I16: 2254 | J16: 0.8 | K16: 223000 | L16: 2023 | M16: 611
F17: Goshen Town | G17: 5371 | H17: 4861 | I17: 3868 | J17: 1.3 | K17: 437900 | L17: 3236 | M17: 1288
A18: Source Specifications | F18: Goshen Village | G18: 2548 | H18: 2307 | I18: 1379 | J18: 0 | K18: 357000 | L18: 2466 | M18: 337
A19: Source | B19: Source: US Census Bureau, American Community Survey 2019–2023 5-Year Population Estimates, DP04-Selected Housing Characteristics, November 2025 https://data.census.gov/table/ACSDP5Y2023.DP04?q=dp04+Orange+County,+NY&g=060XX00US3607134550,3607156185,3607148857,3607182755,3607147042,3607 148153,3607178839,3607130631,3607118300,3607175781,3607150045,3607147713,3607147999,3607150848,3607129553,3607107003,3607115308,360713190 7,3607118916,3607178366,3607177992,3607119961,3607150034,3607159388_160XX00US3646162,3629542,3630752,3655673,3678355,3676210,3634495,36152 97,3675803,3682750,3677849,3632325,3647988,3678465,3639853,3618333,3668610,3648142_050XX00US36071 | F19: Greenville Town | G19: 1775 | H19: 1645 | I19: 1343 | J19: 0 | K19: 357000 | L19: 2466 | M19: 337
F20: Hamptonburgh Town | G20: 1842 | H20: 1745 | I20: 1625 | J20: 0.5 | K20: 481700 | L20: 3084 | M20: 596
A21: Note Specfications | F21: Highlands Town | G21: 4240 | H21: 3938 | I21: 1639 | J21: 0 | K21: 324800 | L21: 2810 | M21: 666
A22: Note | B22: Note: Town totals include Village totals. Although the Village of Harriman is split between the Towns of Monroe and Woodbury, the total is included under the Town of Monroe for simplicity | F22: Highland Falls Village | G22: 1801 | H22: 1575 | I22: 853 | J22: 0 | K22: 266900 | L22: 2493 | M22: 319
F23: Middletown City | G23: 11018 | H23: 10182 | I23: 5341 | J23: 0.7 | K23: 271000 | L23: 2272 | M23: 1469
F24: Minisink Town | G24: 1697 | H24: 1491 | I24: 1172 | J24: 0.9 | K24: 357800 | L24: 2790 | M24: 398
F25: Unionville Village | G25: 265 | H25: 229 | I25: 138 | J25: 7.4 | K25: 261100 | L25: 1989 | M25: 30
F26: Monroe Town | G26: 7407 | H26: 6883 | I26: 5588 | J26: 2.2 | K26: 353300 | L26: 2834 | M26: 1857
F27: Harriman Village (total)* | G27: 1233 | H27: 1140 | I27: 557 | J27: 0 | K27: 232100 | L27: 2411 | M27: 214
F28: Monroe Village | G28: 3009 | H28: 2841 | I28: 2373 | J28: 0 | K28: 336800 | L28: 2942 | M28: 785
F29: Montgomery Town | G29: 9101 | H29: 8330 | I29: 5806 | J29: 0.9 | K29: 271700 | L29: 2299 | M29: 1884
F30: Maybrook Village | G30: 1446 | H30: 1286 | I30: 705 | J30: 7 | K30: 200200 | L30: 1747 | M30: 199
F31: Montgomery Village | G31: 1373 | H31: 1346 | I31: 859 | J31: 0 | K31: 291000 | L31: 2269 | M31: 195
F32: Walden Village | G32: 3003 | H32: 2790 | I32: 1717 | J32: 0 | K32: 257300 | L32: 2309 | M32: 699
F33: Mount Hope Town | G33: 2216 | H33: 1906 | I33: 1550 | J33: 3.4 | K33: 269900 | L33: 2109 | M33: 405
F34: Otisville Village | G34: 524 | H34: 491 | I34: 321 | J34: 1.5 | K34: 223100 | L34: 2169 | M34: 120
... F50: Woodbury Village | G50: 3999 | H50: 3498 | I50: 3206 | J50: 1.6 | K50: 355900 | L50: 2951 | M50: 1102

Sheet Selected Housing Renters 
A1: Name | B1: Selected Housing Characteristics for Renters by Municipality, 2023
A2: Table/Figure/Both | B2: Both
A3: Object ID | B3: =IF($B$1="","",_xlfn.XLOOKUP($B$1,Master!$F$2:$F$321,Master!$G$2:$G$321,"")) -> tbl-house-characteristics-renters
A4: Figure ID | B4: =IF($B$1="","",_xlfn.XLOOKUP($B$1,Master!$F$2:$F$321,Master!$H$2:$H$321,"")) -> fig-house-characteristics-renters | F4: integer | G4: number | H4: number | I4: number | J4: percent1 | K4: currency | L4: number
A5: Table Rules | E5: Enter Data | F5: Geographic Area | G5: Housing Costs, Home Values, Vacancy Rates and Cost-Stressed Households
A6: Multilevel Headers | B6: TRUE | G6: Total # of Housing Units | H6: # of Occupied Housing Units | I6: # of Renter-Occupied Housing Units | J6: % Rental Vacancy Rate | K6: Median Gross Rent $ | L6: # of Cost-Stressed Renter Households
F7: Orange County | G7: 145947 | H7: 132880 | I7: 41346 | J7: 4.2 | K7: 1379 | L7: 24456
F8: Blooming Grove Town | G8: 6749 | H8: 6005 | I8: 1117 | J8: 6.6 | K8: 1429 | L8: 558
A9: Figure Rules | F9: South Blooming Grove Village | G9: 1483 | H9: 1261 | I9: 266 | J9: 4.7 | K9: 1415 | L9: 139
A10: Figure Type | F10: Washingtonville Village | G10: 2080 | H10: 2004 | I10: 429 | J10: 6.9 | K10: 1088 | L10: 299
A11: X Column | F11: Chester Town | G11: 4712 | H11: 4364 | I11: 852 | J11: 0 | K11: 1539 | L11: 294
A12: Y Column | F12: Chester Village | G12: 1735 | H12: 1643 | I12: 721 | J12: 0 | K12: 1459 | L12: 247
A13: X Axis Title | F13: Cornwall Town | G13: 5250 | H13: 4890 | I13: 1303 | J13: 2.2 | K13: 1577 | L13: 570
A14: Y Axis Title | F14: Cornwall-on-Hudson Village | G14: 1250 | H14: 1186 | I14: 368 | J14: 0 | K14: 1277 | L14: 78
A15: Start at Zero | F15: Crawford Town | G15: 3103 | H15: 3029 | I15: 665 | J15: 4.6 | K15: 1421 | L15: 307
A16: Pivot For Chart | F16: Deerpark Town | G16: 3143 | H16: 2800 | I16: 536 | J16: 8.4 | K16: 1156 | L16: 256
F17: Goshen Town | G17: 4862 | H17: 4373 | I17: 1072 | J17: 9.2 | K17: 1367 | L17: 577
A18: Source Specifications | F18: Goshen Village | G18: 2548 | H18: 2307 | I18: 904 | J18: 10.8 | K18: 1339 | L18: 484
A19: Source | B19: Source: US Census Bureau, American Community Survey 2019–2023 5-Year Population Estimates, Table B25003-Tenure and Table B25004-Vacancy Status, November 2025 https://data.census.gov/table/ACSDT5Y2023.B25003?q=B25003+Orange+County,+NY&g=060XX00US3607134550,3607156185 ,3607148857,3607182755,3607147042,3607148153,3607178839,3607130631,3607118300,3607175781,3607150045,360 7147713,3607147999,3607150848,3607129553,3607107003,3607115308,3607131907,3607118916,3607178366,3607177 992,3607119961,3607150034,3607159388_160XX00US3646162,3629542,3630752,3655673,3678355,3676210,3634495,3 615297,3675803,3682750,3677849,3632325,3647988,3678465,3639853,3618333,3668610,3648142_050XX00US36071 and https://data.census.gov/table/ACSDT5Y2023.B25004?q=B25004+Orange+County,+NY&g=060XX00US3607134550,3607156185 ,3607148857,3607182755,3607147042,3607148153,3607178839,3607130631,3607118300,3607175781,3607150045,36 07147713,3607147999,3607150848,3607129553,3607107003,3607115308,3607131907,3607118916,3607178366,36071 77992,3607119961,3607150034,3607159388_160XX00US3646162,3629542,3630752,3655673,3678355,3676210,363449 5,3615297,3675803,3682750,3677849,3632325,3647988,3678465,3639853,3618333,3668610,3648142_050XX00US3607 1 | F19: Greenville Town | G19: 1678 | H19: 1581 | I19: 238 | J19: 10.2 | K19: 1377 | L19: 93
F20: Hamptonburgh Town | G20: 1844 | H20: 1735 | I20: 97 | J20: 0 | K20: 793 | L20: 0
A21: Note Specfications | F21: Highlands Town | G21: 3750 | H21: 3251 | I21: 1947 | J21: 7.2 | K21: 2095 | L21: 889
A22: Note | B22: Note: Town totals include Village totals. Although the Village of Harriman is split between the Towns of Monroe and Woodbury, the total is included under the Town of Monroe for simplicity. | F22: Highland Falls Village | G22: 1801 | H22: 1575 | I22: 722 | J22: 5.2 | K22: 1459 | L22: 340
F23: Middletown City | G23: 11872 | H23: 10604 | I23: 4741 | J23: 6.4 | K23: 1407 | L23: 3353
F24: Minisink Town | G24: 1697 | H24: 1491 | I24: 319 | J24: 20.1 | K24: 1304 | L24: 206
F25: Unionville Village | G25: 265 | H25: 229 | I25: 91 | J25: 0 | K25: 1223 | L25: 8
F26: Monroe Town | G26: 7407 | H26: 6883 | I26: 1295 | J26: 1.7 | K26: 1748 | L26: 572
F27: Harriman Village (total)* | G27: 1233 | H27: 1140 | I27: 583 | J27: 0 | K27: 1742 | L27: 279
F28: Monroe Village | G28: 3009 | H28: 2841 | I28: 468 | J28: 4.7 | K28: 1670 | L28: 275
F29: Montgomery Town | G29: 9101 | H29: 8330 | I29: 2524 | J29: 0.5 | K29: 1356 | L29: 1589
F30: Maybrook Village | G30: 1446 | H30: 1286 | I30: 581 | J30: 2.1 | K30: 1310 | L30: 239
F31: Montgomery Village | G31: 1373 | H31: 1346 | I31: 487 | J31: 0 | K31: 1425 | L31: 245
F32: Walden Village | G32: 3003 | H32: 2790 | I32: 1073 | J32: 0 | K32: 1268 | L32: 791
F33: Mount Hope Town | G33: 2216 | H33: 1906 | I33: 356 | J33: 2.7 | K33: 867 | L33: 123
F34: Otisville Village | G34: 524 | H34: 491 | I34: 170 | J34: 0 | K34: 1188 | L34: 73
... F50: Woodbury Village | G50: 3999 | H50: 3498 | I50: 292 | J50: 35 | K50: 1745 | L50: 149

Sheet Owner vs Renter Per Room
A1: Name | B1: Owner versus Renter Occupancy Per Room by Municipality, 2023
A2: Table/Figure/Both | B2: Both
A3: Object ID | B3: =IF($B$1="","",_xlfn.XLOOKUP($B$1,Master!$F$2:$F$321,Master!$G$2:$G$321,"")) -> tbl-own-vs-rent-per-room
A4: Figure ID | B4: =IF($B$1="","",_xlfn.XLOOKUP($B$1,Master!$F$2:$F$321,Master!$H$2:$H$321,"")) -> fig-own-vs-rent-per-room | F4: integer | G4: number | H4: number | I4: number
A5: Table Rules | E5: Enter Data | F5: Geographic Area | G5: Total # of Occupied Housing Units | H5: >1 Occupants Per Room
A6: Multilevel Headers | B6: TRUE | H6: Owner | I6: Renter
F7: Orange County | G7: 137311 | H7: 2240 | I7: 2859
F8: Blooming Grove Town | G8: 6149 | H8: 140 | I8: 39
A9: Figure Rules | F9: South Blooming Grove Village | G9: 1173 | H9: 48 | I9: 30
A10: Figure Type | F10: Washingtonville Village | G10: 2106 | H10: 12 | I10: 9
A11: X Column | F11: Chester Town | G11: 4458 | H11: 0 | I11: 0
A12: Y Column | F12: Chester Village | G12: 1560 | H12: 0 | I12: 0
A13: X Axis Title | F13: Cornwall Town | G13: 5023 | H13: 27 | I13: 12
A14: Y Axis Title | F14: Cornwall-on-Hudson Village | G14: 1230 | H14: 0 | I14: 0
A15: Start at Zero | F15: Crawford Town | G15: 3001 | H15: 0 | I15: 8
A16: Pivot For Chart | F16: Deerpark Town | G16: 2993 | H16: 55 | I16: 30
F17: Goshen Town | G17: 4861 | H17: 55 | I17: 23
A18: Source Specifications | F18: Goshen Village | G18: 2350 | H18: 7 | I18: 23
A19: Source | B19: Source: US Census Bureau, American Community Survey 2019–2023 5-Year Population Estimates, Table B25014-Tenure by Occupants per Room, November 2025 https://data.census.gov/table/ACSDT5Y2023.B25014?q=B25014+Orange+County,+NY&g=060XX00US3607134550,360715618 5,3607148857,3607182755,3607147042,3607148153,3607178839,3607130631,3607118300,3607175781,3607150045,36 07147713,3607147999,3607150848,3607129553,3607107003,3607115308,3607131907,3607118916,3607178366,360717 7992,3607119961,3607150034,3607159388_160XX00US3646162,3629542,3630752,3655673,3678355,3676210,3634495, 3615297,3675803,3682750,3677849,3632325,3647988,3678465,3639853,3618333,3668610,3648142_050XX00US36071 | F19: Greenville Town | G19: 1645 | H19: 40 | I19: 0
F20: Hamptonburgh Town | G20: 1745 | H20: 11 | I20: 0
A21: Note Specfications | F21: Highlands Town | G21: 3938 | H21: 29 | I21: 101
A22: Note | B22: Note: Town totals include Village totals | F22: Highland Falls Village | G22: 1648 | H22: 0 | I22: 44
F23: Middletown City | G23: 10182 | H23: 145 | I23: 184
F24: Minisink Town | G24: 1526 | H24: 15 | I24: 0
F25: Unionville Village | G25: 222 | H25: 0 | I25: 0
F26: Monroe Town | G26: 6855 | H26: 138 | I26: 196
F27: Harriman Village (portion) | G27: 792 | H27: 0 | I27: 37
F28: Monroe Village | G28: 2886 | H28: 78 | I28: 146
F29: Montgomery Town | G29: 8306 | H29: 203 | I29: 237
F30: Maybrook Village | G30: 1401 | H30: 46 | I30: 52
F31: Montgomery Village | G31: 1535 | H31: 32 | I31: 0 | K31: `
F32: Walden Village | G32: 2621 | H32: 36 | I32: 128
F33: Mount Hope Town | G33: 2094 | H33: 33 | I33: 0
F34: Otisville Village | G34: 439 | H34: 14 | I34: 0
F35: Newburgh City | G35: 10335 | H35: 99 | I35: 304
F36: Newburgh Town | G36: 11553 | H36: 82 | I36: 90
F37: New Windsor Town | G37: 10763 | H37: 56 | I37: 118
F38: Palm Tree Town | G38: 6869 | H38: 780 | I38: 1192
F39: Kiryas Joel Village | G39: 6869 | H39: 780 | I39: 1192
F40: Port Jervis City | G40: 3533 | H40: 31 | I40: 24
F41: Tuxedo Town | G41: 1539 | H41: 6 | I41: 6
F42: Tuxedo Village | G42: 1151 | H42: 6 | I42: 6
F43: Tuxedo Park Village | G43: 388 | H43: 0 | I43: 0
... F52: Woodbury Village | G52: 3563 | H52: 18 | I52: 0

Sheet High Blood Level <72Mon
A1: Name | B1: Incidence of Confirmed High Blood Lead Level, Rate per 1,000 Tested Children Aged < 72 Months, 2018–2021
A2: Table/Figure/Both | B2: Both
A3: Object ID | B3: =IF($B$1="","",_xlfn.XLOOKUP($B$1,Master!$F$2:$F$321,Master!$G$2:$G$321,"")) -> tbl-high-bll
A4: Figure ID | B4: =IF($B$1="","",_xlfn.XLOOKUP($B$1,Master!$F$2:$F$321,Master!$H$2:$H$321,"")) -> fig-high-bll | F4: integer | G4: percent1 | H4: percent1 | I4: percent1 | J4: percent1
A5: Table Rules | E5: Enter Data | F5: Region | G5: 2018 | H5: 2019 | I5: 2020 | J5: 2021
A6: Multilevel Headers | B6: FALSE | F6: Orange | G6: 4.7 | H6: 5.1 | I6: 4.7 | J6: 3.7
F7: Mid-Hudson | G7: 3.5 | H7: 3.9 | I7: 3.2 | J7: 2.8
F8: NYS excl NYC | G8: 6.5 | H8: 6.5 | I8: 5 | J8: 5.1
A9: Figure Rules | F9: NYS | G9: 3.6 | H9: 3.8 | I9: 3.2 | J9: 3.3
A10: Figure Type | B10: Line
A11: X Column | B11: Region/County
A12: Y Column
A13: X Axis Title
A14: Y Axis Title | B14: Rate per 1,000
A15: Start at Zero | B15: TRUE
A16: Pivot For Chart | B16: TRUE
A18: Source Specifications
A19: Source | B19: Source: NYS Community Health Indicator Reports Dashboard, August 2025 sourced from NYS Childhood Lead Poisoning Prevention Program https://webbi1.health.ny.gov/SASStoredProcess/guest?_program=%2FEBI%2FPHIG%2Fapps%2Fchir_dashboard%2Fchir_dashboard& p=ch&cos=33
A21: Note Specfications
A22: Note | B22: Note: High blood lead level is considered >10 Micrograms per Deciliter. Three-year averages for Orange County and single-year estimates for the Mid-Hudson Region, NYS excl NYC, and NYS.

Sheet Type Internet Access
A1: Name | B1: Type of Internet Access per Household by Municipality, 2023
A2: Table/Figure/Both | B2: Both
A3: Object ID | B3: =IF($B$1="","",_xlfn.XLOOKUP($B$1,Master!$F$2:$F$321,Master!$G$2:$G$321,"")) -> tbl-internet-access
A4: Figure ID | B4: =IF($B$1="","",_xlfn.XLOOKUP($B$1,Master!$F$2:$F$321,Master!$H$2:$H$321,"")) -> fig-internet-access | F4: integer | G4: number | H4: number | I4: percent1 | J4: number | K4: percent1 | L4: number | M4: percent1 | N4: number | O4: percent1
A5: Table Rules | E5: Enter Data | F5: Geographic Area | G5: Total # of Households | H5: Households Without Internet Access | J5: Households with Internet Subscription | L5: Households with Access but no Subscription | N5: Households with Cellular Data Only
A6: Multilevel Headers | B6: TRUE | H6: # | I6: % | J6: # | K6: % | L6: # | M6: % | N6: # | O6: %
F7: Orange County | G7: 137311 | H7: 13355 | I7: 9.7 | J7: 121963 | K7: 88.8 | L7: 1993 | M7: 145.1 | N7: 12688 | O7: 9.2
F8: Blooming Grove Town | G8: 6149 | H8: 281 | I8: 4.6 | J8: 5768 | K8: 93.8 | L8: 100 | M8: 162.6 | N8: 523 | O8: 8.5
A9: Figure Rules | F9: South Blooming Grove Village | G9: 1173 | H9: 154 | I9: 13.1 | J9: 1019 | K9: 86.9 | L9: 0 | M9: 0 | N9: 93 | O9: 7.9
A10: Figure Type | F10: Washingtonville Village | G10: 2106 | H10: 63 | I10: 3 | J10: 2011 | K10: 95.5 | L10: 32 | M10: 151.9 | N10: 236 | O10: 11.2
A11: X Column | F11: Chester Town | G11: 4458 | H11: 282 | I11: 6.3 | J11: 4143 | K11: 92.9 | L11: 33 | M11: 74 | N11: 380 | O11: 8.5
A12: Y Column | F12: Chester Village | G12: 1560 | H12: 77 | I12: 4.9 | J12: 1483 | K12: 95.1 | L12: 0 | M12: 0 | N12: 213 | O12: 13.7
A13: X Axis Title | F13: Cornwall Town | G13: 5023 | H13: 276 | I13: 5.5 | J13: 4713 | K13: 93.8 | L13: 34 | M13: 67.7 | N13: 546 | O13: 10.9
A14: Y Axis Title | F14: Cornwall-on-Hudson Village | G14: 1230 | H14: 56 | I14: 4.6 | J14: 1170 | K14: 95.1 | L14: 4 | M14: 32.5 | N14: 211 | O14: 17.2
A15: Start at Zero | F15: Crawford Town | G15: 3001 | H15: 273 | I15: 9.1 | J15: 2692 | K15: 89.7 | L15: 36 | M15: 120 | N15: 261 | O15: 8.7
A16: Pivot For Chart | F16: Deerpark Town | G16: 2993 | H16: 207 | I16: 6.9 | J16: 2774 | K16: 92.7 | L16: 12 | M16: 40.1 | N16: 338 | O16: 11.3
F17: Goshen Town | G17: 4861 | H17: 232 | I17: 4.8 | J17: 4623 | K17: 95.1 | L17: 6 | M17: 12.3 | N17: 449 | O17: 9.2
A18: Source Specifications | F18: Goshen Village | G18: 2350 | H18: 208 | I18: 8.9 | J18: 2142 | K18: 91.1 | L18: 0 | M18: 0 | N18: 228 | O18: 9.7
A19: Source | B19: Source: US Census Bureau, American Community Survey 2019–2023 5-Year Population Estimates, Table B28002-Household Income in the Last 12 Months by Presence and Type of Internet Subscription in Household, November 2025 https://data.census.gov/table/ACSDT5Y2023.B28002?q=B28002+Orange+County,+NY&g=060XX00US3607134550,360715618 5,3607148857,3607182755,3607147042,3607148153,3607178839,3607130631,3607118300,3607175781,3607150045,36 07147713,3607147999,3607150848,3607129553,3607107003,3607115308,3607131907,3607118916,3607178366,360717 7992,3607119961,3607150034,3607159388_160XX00US3646162,3629542,3630752,3655673,3678355,3676210,3634495, 3615297,3675803,3682750,3677849,3632325,3647988,3678465,3639853,3618333,3668610,3648142_050XX00US36071 | F19: Greenville Town | G19: 1645 | H19: 52 | I19: 3.2 | J19: 1580 | K19: 96 | L19: 13 | M19: 79 | N19: 163 | O19: 9.9
F20: Hamptonburgh Town | G20: 1745 | H20: 15 | I20: 0.9 | J20: 1723 | K20: 98.7 | L20: 7 | M20: 40.1 | N20: 105 | O20: 6
A21: Note Specfications | F21: Highlands Town | G21: 3938 | H21: 163 | I21: 4.1 | J21: 3738 | K21: 94.9 | L21: 37 | M21: 94 | N21: 186 | O21: 4.7
A22: Note | B22: Note: Town totals include Village totals | F22: Highland Falls Village | G22: 1648 | H22: 46 | I22: 2.8 | J22: 1587 | K22: 96.3 | L22: 15 | M22: 91 | N22: 71 | O22: 4.3
F23: Middletown City | G23: 10182 | H23: 921 | I23: 9 | J23: 9113 | K23: 89.5 | L23: 148 | M23: 145.4 | N23: 1071 | O23: 10.5
F24: Minisink Town | G24: 1526 | H24: 24 | I24: 1.6 | J24: 1483 | K24: 97.2 | L24: 19 | M24: 124.5 | N24: 126 | O24: 8.3
F25: Unionville Village | G25: 222 | H25: 15 | I25: 6.8 | J25: 201 | K25: 90.5 | L25: 6 | M25: 270.3 | N25: 16 | O25: 7.2
F26: Monroe Town | G26: 6855 | H26: 320 | I26: 4.7 | J26: 6444 | K26: 94 | L26: 91 | M26: 132.7 | N26: 359 | O26: 5.2
F27: Harriman Village (portion) | G27: 792 | H27: 45 | I27: 5.7 | J27: 731 | K27: 92.3 | L27: 16 | M27: 202 | N27: 76 | O27: 9.6
F28: Monroe Village | G28: 2886 | H28: 134 | I28: 4.6 | J28: 2711 | K28: 93.9 | L28: 41 | M28: 142.1 | N28: 185 | O28: 6.4
F29: Montgomery Town | G29: 8306 | H29: 476 | I29: 5.7 | J29: 7753 | K29: 93.3 | L29: 77 | M29: 92.7 | N29: 652 | O29: 7.8
F30: Maybrook Village | G30: 1401 | H30: 58 | I30: 4.1 | J30: 1290 | K30: 92.1 | L30: 53 | M30: 378.3 | N30: 91 | O30: 6.5
F31: Montgomery Village | G31: 1535 | H31: 43 | I31: 2.8 | J31: 1492 | K31: 97.2 | L31: 0 | M31: 0 | N31: 44 | O31: 2.9
F32: Walden Village | G32: 2621 | H32: 320 | I32: 12.2 | J32: 2291 | K32: 87.4 | L32: 10 | M32: 38.2 | N32: 351 | O32: 13.4
F33: Mount Hope Town | G33: 2094 | H33: 170 | I33: 8.1 | J33: 1910 | K33: 91.2 | L33: 14 | M33: 66.9 | N33: 218 | O33: 10.4
F34: Otisville Village | G34: 439 | H34: 10 | I34: 2.3 | J34: 426 | K34: 97 | L34: 3 | M34: 68.3 | N34: 18 | O34: 4.1
... F52: Woodbury Village | G52: 3563 | H52: 122 | I52: 3.4 | J52: 3430 | K52: 96.3 | L52: 11 | M52: 30.9 | N52: 356 | O52: 10

Sheet Pop Served OCDOS
A1: Name | B1: Population Served by Orange County Department of Social Services, 2022–2024
A2: Table/Figure/Both | B2: Both
A3: Object ID | B3: =IF($B$1="","",_xlfn.XLOOKUP($B$1,Master!$F$2:$F$321,Master!$G$2:$G$321,"")) -> tbl-pop-served-ocdss
A4: Figure ID | B4: =IF($B$1="","",_xlfn.XLOOKUP($B$1,Master!$F$2:$F$321,Master!$H$2:$H$321,"")) -> fig-pop-served-ocdss | F4: integer | G4: number | H4: number | I4: number
A5: Table Rules | E5: Enter Data | F5: Human Services | G5: 2022 | H5: 2023 | I5: 2024
A6: Multilevel Headers | B6: TRUE | F6: Number of Children Protective Services reports (children under 18 years) | G6: 3611 | H6: 3831 | I6: 3620
F7: Children in care (monthly average) | G7: 248 | H7: 220 | I7: 201
F8: Number of families receiving preventive services | G8: 120 | H8: 127 | I8: 116
A9: Figure Rules | F9: Children discharged to adoption total end of year | G9: 28 | H9: 23 | I9: 25
A10: Figure Type | F10: Average number of youths receiving Persons in Need of Supervision (PINS)/Juvenile Detention (JD) Prevention Services per month | G10: 179 | H10: 188 | I10: 184
A11: X Column | F11: Economic Independence
A12: Y Column | F12: Temporary Assistance (TA) applications filed total end of year | G12: 3434 | H12: 3855 | I12: 4181
A13: X Axis Title | F13: TA cases (end of year) | G13: 1336 | H13: 1471 | I13: 1605
A14: Y Axis Title | F14: TA recipients (end of year) | G14: 2327 | H14: 2624 | I14: 2873
A15: Start at Zero | F15: -Family Assistance (FA) cases (end of year) | G15: 504 | H15: 527 | I15: 565
A16: Pivot For Chart | F16: -Safety Net Assistance (SNA) cases (end of year) | G16: 832 | H16: 944 | I16: 1040
F17: Home Energy Assistance Program (HEAP) payments | G17: 23796 | H17: 28602 | I17: 20929
A18: Source Specifications | F18: Medicaid applications filed total end of year | G18: 1728 | H18: 2572 | I18: 3042
A19: Source | B19: Source: Data request from Orange County Department of Social Services, November 2025 | F19: Medicaid only (MA) cases (end of year) | G19: 20975 | H19: 20739 | I19: 19266
F20: Family Health Plus (FHP) cases (end of year) (including in MA only cases) | G20: 0 | H20: 0 | I20: 0
A21: Note Specfications | F21: SNAP applications filed total at end of year | G21: 12584 | H21: 14560 | I21: 12792
A22: Note | B22: Note: All end of year figures equal the amounts on December 31st of the indicated year. All counts have been rounded to the nearest whole number. Dollar amounts have been rounded to the nearest tenth. | F22: SNAP cases (end of year) | G22: 17002 | H22: 17784 | I22: 18923
F23: SNAP Dollars (TA-SNAP and NTA-SNAP) for Orange County only | G23: 20823245 | H23: 98665429 | I23: 119488674
F24: Employment of TA recipients (via Employment & Training Adm.) | G24: 254 | H24: 302 | I24: 314
F25: Homeless applicants/cases | G25: Families: 13 Singles: 45 | H25: Families: 19 Singles: 56 | I25: Families: 18 Singles: 58
F26: Cases diverted to other housing remedies or ineligible | G26: 1733 | H26: 2161 | I26: 2668
F27: Homeless individuals (mo. Average) | G27: 265 | H27: 487 | I27: 737
F28: Temporarily housed at emergency housing shelter (monthly average for Families and singles combined) | G28: HONOR: 48 Other: 63 Total: 111 | H28: HONOR: 55 Other: 56 Total: 111 | I28: HONOR: 66 Other: 58 Total: 124
F29: Temporarily housed at hotel/motel (mo. average for families and singles combined) | G29: 19 | H29: 90 | I29: 230
F30: Temporarily housed in transitional housing-Project Life (mo. average) | G30: 12 | H30: 14 | I30: 12
F31: Administrative Division | K31: `
F32: Child Support cases (end of year) | G32: 10260 | H32: 9930 | I32: 9724
F33: Child Support total collected | G33: 38251624 | H33: 39675001 | I33: 41707553
F34: DSS cases with substantiated fraud (Special Investigation results) | G34: 407 | H34: 709 | I34: 559
F35: YTD total overpayment amount charged for substantiated fraud cases | G35: 637829 | H35: 1254285 | I35: 371227
F36: Child Care Subsidy Cases (mo. average) | G36: Low Income: 324 Temp Asst: 26 Total: 351 | H36: Low Income: 486 Temp Asst: 40 Total: 526 | I36: Low Income: 624 Temp Asst: 40 Total: 664

Sheet Diseases of the Circulatory Sys
A1: Name | B1: Diseases of the Circulatory System Mortality, Case Counts and Rates per 100,000 Population by Age, Race and Ethnicity, and ZIP Code, 2020–2023
A2: Table/Figure/Both | B2: Both
A3: Object ID | B3: =IF($B$1="","",_xlfn.XLOOKUP($B$1,Master!$F$2:$F$321,Master!$G$2:$G$321,"")) -> tbl-dzcircsystem-count-rate-age-rande-zip
A4: Figure ID | B4: =IF($B$1="","",_xlfn.XLOOKUP($B$1,Master!$F$2:$F$321,Master!$H$2:$H$321,"")) -> fig-dzcircsystem-count-rate-age-rande-zip | F4: text | G4: number | H4: percent1 | I4: number | J4: percent1 | K4: number | L4: percent1 | M4: number | N4: percent1 | O4: number | P4: percent1
A5: Table Rules | E5: Enter Data | F5: Region | G5: 2020 | I5: 2021 | K5: 2022 | M5: 2023 | O5: 2020-2023
A6: Multilevel Headers | B6: TRUE | G6: # | H6: Rate | I6: # | J6: Rate | K6: # | L6: Rate | M6: # | N6: Rate | O6: # | P6: Average Rate
F7: Orange County Total | G7: 68 | H7: 17.8 | I7: 39 | J7: 9.8 | K7: 65 | L7: 16.2 | M7: 73 | N7: 18.1 | O7: 245 | P7: 15.5
F8: Age Intervals
A9: Figure Rules | F9: <1 | G9: 0 | H9: 0 | I9: s | J9: s | K9: 0 | L9: 0 | M9: s | N9: s | O9: s | P9: s
A10: Figure Type | F10: 1-9 | G10: s | H10: s | I10: 0 | J10: 0 | K10: 0 | L10: 0 | M10: 0 | N10: 0 | O10: s | P10: s
A11: X Column | F11: 10-19 | G11: 0 | H11: 0 | I11: 0 | J11: 0 | K11: 0 | L11: 0 | M11: 0 | N11: 0 | O11: 0 | P11: 0
A12: Y Column | F12: 20-24 | G12: s | H12: s | I12: s | J12: s | K12: s | L12: s | M12: s | N12: s | O12: s | P12: s
A13: X Axis Title | F13: 25-34 | G13: s | H13: s | I13: s | J13: s | K13: s | L13: s | M13: s | N13: s | O13: 14 | P13: 7.5
A14: Y Axis Title | F14: 35-44 | G14: s | H14: s | I14: s | J14: s | K14: s | L14: s | M14: s | N14: s | O14: 30 | P14: 15.7
A15: Start at Zero | F15: 45-54 | G15: 28 | H15: 53.5 | I15: 34 | J15: 63.7 | K15: 21 | L15: 40.1 | M15: 32 | N15: 62.1 | O15: 115 | P15: 54.9
A16: Pivot For Chart | F16: 55-64 | G16: 84 | H16: 172.5 | I16: 91 | J16: 177.1 | K16: 99 | L16: 193.4 | M16: 98 | N16: 190.3 | O16: 372 | P16: 183.3
F17: 65-74 | G17: 154 | H17: 488.4 | I17: 147 | J17: 439.2 | K17: 159 | L17: 469.7 | M17: 147 | N17: 421.9 | O17: 607 | P17: 454.8
A18: Source Specifications | F18: 75-84 | G18: 196 | H18: 1329.3 | I18: 209 | J18: 1369.6 | K18: 230 | L18: 1451.7 | M18: 236 | N18: 1439.3 | O18: 871 | P18: 1397.4
A19: Source | B19: Source: Special request from NYSDOH Bureau of Vital Records, July 2025 | F19: 85+ | G19: 365 | H19: 5105.6 | I19: 297 | J19: 4359.3 | K19: 295 | L19: 4202.3 | M19: 313 | N19: 4665.4 | O19: 1270 | P19: 4583.1
F20: Race and Ethnicity
A21: Note Specfications | F21: Non-Hispanic White | G21: 686 | H21: 284.4 | I21: 635 | J21: 256.2 | K21: 656 | L21: 270.4 | M21: 660 | N21: 275.9 | O21: 2637 | P21: 271.7
A22: Note | B22: s: Data are suppressed due to not meeting reporting criteria. Note: See Data Note section for more information regarding this request. This includes Circulatory System Diseases as a primary cause of death with ICD-10-CM codes of: I00–I09 (Rheumatic Heart Diseases), I10–I15 (Hypertensive Diseases), I20–I25 (Ischemic Heart Diseases), I26–I28 (Pulmonary Heart Diseases and Circulation), I30–I52 (Other Forms of Heart Disease), I60–I69 (Cerebrovascular Disease), I70–I79 (Disease of Arteries, Arterioles, and Capillaries), I80–I89 (Disease of Veins, Lymphatics, and Nodes), and I95–I99 (Other and Unspecified Disorders). Birth and death data for Orange County excludes events recorded in NYC. All rates use ACS 5-year population estimates, except for the ages under 1 year and 1–9 years, which are based on crude live births in Orange County. | F22: Non-Hispanic Black | G22: 66 | H22: 171.6 | I22: 72 | J22: 181.2 | K22: 74 | L22: 176.4 | M22: 85 | N22: 200.1 | O22: 297 | P22: 182.3
F23: Hispanic | G23: 63 | H23: 78.5 | I23: 70 | J23: 82 | K23: 61 | L23: 68.2 | M23: 74 | N23: 79.1 | O23: 268 | P23: 76.9
F24: Other | G24: 28 | H24: 126.2 | I24: 16 | J24: 63.2 | K24: 24 | L24: 88.4 | M24: 20 | N24: 70 | O24: 88 | P24: 87
F25: ZIP Code
F26: 10940 | G26: 111 | H26: 224.6 | I26: 138 | J26: 270.9 | K26: 127 | L26: 244.9 | M26: 125 | N26: 235.4 | O26: 501 | P26: 244
F27: 10950 | G27: 58 | H27: 433.4 | I27: 48 | J27: 333 | K27: 46 | L27: 317.2 | M27: 43 | N27: 291.3 | O27: 195 | P27: 343.7
F28: 12550 | G28: 153 | H28: 573.8 | I28: 115 | J28: 429 | K28: 127 | L28: 463.4 | M28: 113 | N28: 413.9 | O28: 508 | P28: 470
F29: 12771 | G29: 33 | H29: 229 | I29: 55 | J29: 370.6 | K29: 46 | L29: 318.3 | M29: 52 | N29: 362.5 | O29: 186 | P29: 320.1

Sheet Diseases Circ Mort AAR
A1: Name | B1: Diseases of the Circulatory System Mortality, Age-Adjusted Rate per 100,000, 2020–2023
A2: Table/Figure/Both | B2: Both
A3: Object ID | B3: =IF($B$1="","",_xlfn.XLOOKUP($B$1,Master!$F$2:$F$321,Master!$G$2:$G$321,"")) -> tbl-dzcircsystem-mortal-aar
A4: Figure ID | B4: =IF($B$1="","",_xlfn.XLOOKUP($B$1,Master!$F$2:$F$321,Master!$H$2:$H$321,"")) -> fig-dzcircsystem-mortal-aar | F4: integer | G4: percent1 | H4: percent1 | I4: percent1 | J4: percent1
A5: Table Rules | E5: Enter Data | F5: Region | G5: 2020 | H5: 2021 | I5: 2022 | J5: 2023
A6: Multilevel Headers | B6: FALSE | F6: Orange | G6: 198.4 | H6: 186.4 | I6: 187.1 | J6: 193.6
A9: Figure Rules
A10: Figure Type | B10: Line
A11: X Column | B11: County
A12: Y Column
A13: X Axis Title
A14: Y Axis Title | B14: Rate per 100,000
A15: Start at Zero | B15: TRUE
A16: Pivot For Chart | B16: TRUE
A18: Source Specifications
A19: Source | B19: Source: Special request from NYSDOH Bureau of Vital Records, July 2025
A21: Note Specfications
A22: Note | B22: Note: See Data Note section for more information regarding this request. This includes Circulatory System Diseases as a primary cause of death with ICD-10-CM codes of: I00–I09 (Rheumatic Heart Diseases), I10–I15 (Hypertensive Diseases), I20–I25 (Ischemic Heart Diseases), I26–I28 (Pulmonary Heart Diseases and Circulation), I30–I52 (Other Forms of Heart Disease), I60–I69 (Cerebrovascular Disease), I70–I79 (Disease of Arteries, Arterioles, and Capillaries), I80–I89 (Disease of Veins, Lymphatics, and Nodes), and I95–I99 (Other and Unspecified Disorders). Birth and death data for Orange County excludes events recorded in NYC. All rates use ACS 5-year population estimates, except for the ages under 1 year and 1–9 years, which are based on crude live births in Orange County.

Sheet Diseases Circ Mort AAR RE
A1: Name | B1: Diseases of the Circulatory System Mortality, Rate per 100,000 Population by Race and Ethnicity, 2020–2023
A2: Table/Figure/Both | B2: Both
A3: Object ID | B3: =IF($B$1="","",_xlfn.XLOOKUP($B$1,Master!$F$2:$F$321,Master!$G$2:$G$321,"")) -> tbl-dzcircsystem--mortal-rande
A4: Figure ID | B4: =IF($B$1="","",_xlfn.XLOOKUP($B$1,Master!$F$2:$F$321,Master!$H$2:$H$321,"")) -> fig-dzcircsystem--mortal-rande | F4: integer | G4: percent1 | H4: percent1 | I4: percent1 | J4: percent1
A5: Table Rules | E5: Enter Data | F5: Race and Ethnicity | G5: 2020 | H5: 2021 | I5: 2022 | J5: 2023
A6: Multilevel Headers | B6: FALSE | F6: Non-Hispanic White | G6: 284.4 | H6: 256.2 | I6: 169.2 | J6: 275.9
F7: Non-Hispanic Black | G7: 171.6 | H7: 181.2 | I7: 217.1 | J7: 200.1
F8: Non-Hispanic Asian/Pacific Islander | G8: 78.5 | H8: 82 | I8: 103.3 | J8: 79.1
A9: Figure Rules | F9: Hispanic | G9: 126.2 | H9: 63.2 | I9: 135.9 | J9: 70
A10: Figure Type | B10: Clustered Bar
A11: X Column | B11: Race and Ethnicity
A12: Y Column
A13: X Axis Title | B13: Year
A14: Y Axis Title | B14: Rate per 100,000
A15: Start at Zero | B15: TRUE
A16: Pivot For Chart | B16: TRUE
A18: Source Specifications
A19: Source | B19: Source: Special request from NYSDOH Bureau of Vital Records, July 2025
A21: Note Specfications
A22: Note | B22: Note: See Data Note section for more information regarding this request. This includes Circulatory System Diseases as a primary cause of death with ICD-10-CM codes of: I00–I09 (Rheumatic Heart Diseases), I10–I15 (Hypertensive Diseases), I20–I25 (Ischemic Heart Diseases), I26–I28 (Pulmonary Heart Diseases and Circulation), I30–I52 (Other Forms of Heart Disease), I60–I69 (Cerebrovascular Disease), I70–I79 (Disease of Arteries, Arterioles, and Capillaries), I80–I89 (Disease of Veins, Lymphatics, and Nodes), and I95–I99 (Other and Unspecified Disorders). Birth and death data for Orange County excludes events recorded in NYC. All rates use ACS 5-year population estimates, except for the ages under 1 year and 1–9 years, which are based on crude live births in Orange County.

Sheet Diseases Circ Mort AAR ZIP
A1: Name | B1: Diseases of the Circulatory System Mortality, Rate per 100,000 Population by ZIP Code, 2020–2023
A2: Table/Figure/Both | B2: Both
A3: Object ID | B3: =IF($B$1="","",_xlfn.XLOOKUP($B$1,Master!$F$2:$F$321,Master!$G$2:$G$321,"")) -> tbl-dzcircsystem--mortal-zip
A4: Figure ID | B4: =IF($B$1="","",_xlfn.XLOOKUP($B$1,Master!$F$2:$F$321,Master!$H$2:$H$321,"")) -> fig-dzcircsystem--mortal-zip | F4: integer | G4: percent1 | H4: percent1 | I4: percent1 | J4: percent1
A5: Table Rules | E5: Enter Data | F5: ZIP Code | G5: 2020 | H5: 2021 | I5: 2022 | J5: 2023
A6: Multilevel Headers | B6: FALSE | F6: 10940 | G6: 224.6 | H6: 270.9 | I6: 244.9 | J6: 235.4
F7: 10950 | G7: 433.4 | H7: 333 | I7: 317.2 | J7: 291.3
F8: 12550 | G8: 573.8 | H8: 429 | I8: 463.4 | J8: 413.9
A9: Figure Rules | F9: 12771 | G9: 229 | H9: 370.6 | I9: 318.3 | J9: 362.5
A10: Figure Type | B10: Line
A11: X Column | B11: Year
A12: Y Column
A13: X Axis Title | B13: Year
A14: Y Axis Title | B14: Rate per 100,000
A15: Start at Zero | B15: TRUE
A16: Pivot For Chart | B16: TRUE
A18: Source Specifications
A19: Source | B19: Source: Special request from NYSDOH Bureau of Vital Records, July 2025
A21: Note Specfications
A22: Note | B22: Note: See Data Note section for more information regarding this request. This includes Circulatory System Diseases as a primary cause of death with ICD-10-CM codes of: I00–I09 (Rheumatic Heart Diseases), I10–I15 (Hypertensive Diseases), I20–I25 (Ischemic Heart Diseases), I26–I28 (Pulmonary Heart Diseases and Circulation), I30–I52 (Other Forms of Heart Disease), I60–I69 (Cerebrovascular Disease), I70–I79 (Disease of Arteries, Arterioles, and Capillaries), I80–I89 (Disease of Veins, Lymphatics, and Nodes), and I95–I99 (Other and Unspecified Disorders). Birth and death data for Orange County excludes events recorded in NYC. All rates use ACS 5-year population estimates, except for the ages under 1 year and 1–9 years, which are based on crude live births in Orange County.

Sheet Diseases Circ Mort AAR SEX
A1: Name | B1: Diseases of the Circulatory System Mortality, Age-Adjusted Rate per 100,000 by Sex, 2020–2023
A2: Table/Figure/Both | B2: Both
A3: Object ID | B3: =IF($B$1="","",_xlfn.XLOOKUP($B$1,Master!$F$2:$F$321,Master!$G$2:$G$321,"")) -> tbl-dzcircsystem-mortal-sex-aar
A4: Figure ID | B4: =IF($B$1="","",_xlfn.XLOOKUP($B$1,Master!$F$2:$F$321,Master!$H$2:$H$321,"")) -> fig-dzcircsystem-mortal-sex-aar | F4: integer | G4: percent1 | H4: percent1 | I4: percent1 | J4: percent1
A5: Table Rules | E5: Enter Data | F5: Sex | G5: 2020 | H5: 2021 | I5: 2022 | J5: 2023
A6: Multilevel Headers | B6: FALSE | F6: Males | G6: 264.8 | H6: 220.2 | I6: 219.7 | J6: 238.7
F7: Females | G7: 149.1 | H7: 159.2 | I7: 158.6 | J7: 157.7
A9: Figure Rules
A10: Figure Type | B10: Line
A11: X Column | B11: Year
A12: Y Column
A13: X Axis Title | B13: Sex
A14: Y Axis Title | B14: Rate per 100,000
A15: Start at Zero | B15: TRUE
A16: Pivot For Chart | B16: TRUE
A18: Source Specifications
A19: Source | B19: Source: Vital Statistics of NYS, July 2025
A21: Note Specfications
A22: Note | B22: Note: See Data Note section for more information regarding this request. This includes Circulatory System Diseases as a primary cause of death with ICD-10-CM codes of: I00–I09 (Rheumatic Heart Diseases), I10–I15 (Hypertensive Diseases), I20–I25 (Ischemic Heart Diseases), I26–I28 (Pulmonary Heart Diseases and Circulation), I30–I52 (Other Forms of Heart Disease), I60–I69 (Cerebrovascular Disease), I70–I79 (Disease of Arteries, Arterioles, and Capillaries), I80–I89 (Disease of Veins, Lymphatics, and Nodes), and I95–I99 (Other and Unspecified Disorders). Birth and death data for Orange County excludes events recorded in NYC. All rates use ACS 5-year population estimates, except for the ages under 1 year and 1–9 years, which are based on crude live births in Orange County.

Sheet HD Mort Age RE ZIP
A1: Name | B1: Heart Disease Mortality, Case Counts and Rates per 100,000 Population by Age, Race and Ethnicity, and ZIP Code, 2020–2023
A2: Table/Figure/Both | B2: Both
A3: Object ID | B3: =IF($B$1="","",_xlfn.XLOOKUP($B$1,Master!$F$2:$F$321,Master!$G$2:$G$321,"")) -> tbl-heartdz-count-rate-age-rande-zip
A4: Figure ID | B4: =IF($B$1="","",_xlfn.XLOOKUP($B$1,Master!$F$2:$F$321,Master!$H$2:$H$321,"")) -> fig-heartdz-count-rate-age-rande-zip | F4: text | G4: number | H4: percent1 | I4: number | J4: percent1 | K4: number | L4: percent1 | M4: number | N4: percent1 | O4: number | P4: percent1
A5: Table Rules | E5: Enter Data | F5: Region | G5: 2020 | I5: 2021 | K5: 2022 | M5: 2023 | O5: Total 2020-2023
A6: Multilevel Headers | B6: TRUE | G6: # | H6: Rate | I6: # | J6: Rate | K6: # | L6: Rate | M6: # | N6: Rate | O6: # | P6: Average Rate
F7: Orange County | G7: 687 | H7: 179.8 | I7: 628 | J7: 157.7 | K7: 632 | L7: 157.5 | M7: 676 | N7: 167.4 | O7: 2623 | P7: 165.6
F8: Age Intervals
A9: Figure Rules | F9: <1 | G9: 0 | H9: 0 | I9: s | J9: s | K9: 0 | L9: 0 | M9: s | N9: s | O9: s | P9: s
A10: Figure Type | F10: 1-9 | G10: s | H10: s | I10: 0 | J10: 0 | K10: 0 | L10: 0 | M10: 0 | N10: 0 | O10: s | P10: s
A11: X Column | F11: 10-19 | G11: 0 | H11: 0 | I11: 0 | J11: 0 | K11: 0 | L11: 0 | M11: 0 | N11: 0 | O11: 0 | P11: 0
A12: Y Column | F12: 20-24 | G12: s | H12: s | I12: s | J12: s | K12: 0 | L12: 0 | M12: s | N12: s | O12: s | P12: s
A13: X Axis Title | F13: 25-34 | G13: s | H13: s | I13: s | J13: s | K13: s | L13: s | M13: s | N13: s | O13: s | P13: s
A14: Y Axis Title | F14: 35-44 | G14: s | H14: s | I14: s | J14: s | K14: s | L14: s | M14: s | N14: s | O14: 20 | P14: 10.5
A15: Start at Zero | F15: 45-54 | G15: 24 | H15: 45.8 | I15: 27 | J15: 50.6 | K15: 14 | L15: 26.7 | M15: 30 | N15: 58.2 | O15: 95 | P15: 45.4
A16: Pivot For Chart | F16: 55-64 | G16: 66 | H16: 135.5 | I16: 69 | J16: 134.3 | K16: 71 | L16: 138.7 | M16: 81 | N16: 157.3 | O16: 287 | P16: 141.4
F17: 65-74 | G17: 130 | H17: 412.3 | I17: 122 | J17: 364.5 | K17: 131 | L17: 387 | M17: 120 | N17: 344.4 | O17: 503 | P17: 377.1
A18: Source Specifications | F18: 75-84 | G18: 155 | H18: 1051.2 | I18: 167 | J18: 1094.4 | K18: 174 | L18: 1098.2 | M18: 195 | N18: 1189.2 | O18: 691 | P18: 1108.3
A19: Source | B19: Source: Special request from NYSDOH Bureau of Vital Records, July 2025 | F19: 85+ | G19: 300 | H19: 4196.4 | I19: 234 | J19: 3434.6 | K19: 234 | L19: 3333.3 | M19: 245 | N19: 3651.8 | O19: 1013 | P19: 3654
F20: Race and Ethnicity
A21: Note Specfications | F21: Non-Hispanic White | G21: 565 | H21: 234.3 | I21: 507 | J21: 204.5 | K21: 518 | L21: 213.5 | M21: 532 | N21: 222.4 | O21: 2122 | P21: 218.7
A22: Note | B22: s: Data are suppressed due to not meeting reporting criteria. Note: See Data Note section for more information regarding this request. This includes Diseases of the Heart as a primary cause of death with ICD-10-CM codes of: I00–I09 (Acute Rheumatic Fever), I11 (Hypertensive Heart Disease), I13 (Hypertensive Heart Disease and Chronic Kidney Disease), and I20–I51 (Ischemic Heart Diseases, Pulmonary Circulation Diseases, and Other forms of Heart Disease). Birth and death data for Orange County excludes events recorded in NYC. All rates use ACS 5-year population estimates, except for the ages under 1 year and 1–9 years, which are based on crude live births in Orange County. | F22: Non-Hispanic Black | G22: 46 | H22: 119.6 | I22: 58 | J22: 146 | K22: 49 | L22: 116.8 | M22: 65 | N22: 153 | O22: 218 | P22: 133.9
